Workbook

Sheet Pressupostos
B2: 1. Informação sobre o investimento e pressupostos gerais
B4: Primeiro ano de atividade | F4: 2024
B5: Número de anos até o investimento atingir o ritmo cruzeiro | F5: 2
B7: Contador | F7: 1 | G7: =F7+1 -> 2 | H7: =G7+1 -> 3 | I7: =H7+1 -> 4 | J7: =I7+1 -> 5 | K7: =J7+1 -> 6 | L7: =K7+1 -> 7 | M7: =L7+1 -> 8 | N7: =M7+1 -> 9 | ... T7: =S7+1 -> 15
B8: Indicador de projeção | F8: =IF(F7<=$F$5,1,0) -> 1 | G8: =IF(G7<=$F$5,1,0) -> 1 | H8: =IF(H7<=$F$5,1,0) -> 0 | I8: =IF(I7<=$F$5,1,0) -> 0 | J8: =IF(J7<=$F$5,1,0) -> 0 | K8: =IF(K7<=$F$5,1,0) -> 0 | L8: =IF(L7<=$F$5,1,0) -> 0 | M8: =IF(M7<=$F$5,1,0) -> 0 | ... T8: =IF(T7<=$F$5,1,0) -> 0
B10: Ano | E10: 2023 | F10: =IF(F$8=1,F$4,"") -> 2024 | G10: =IF(G$8=1,F10+1,"") -> 2025 | H10: =IF(H$8=1,G10+1,"") | I10: =IF(I$8=1,H10+1,"") | J10: =IF(J$8=1,I10+1,"") | K10: =IF(K$8=1,J10+1,"") | L10: =IF(L$8=1,K10+1,"") | M10: =IF(M$8=1,L10+1,"") | N10: =IF(N$8=1,M10+1,"") | ... T10: =IF(T$8=1,S10+1,"")
B11: Taxa de inflação | F11: =IF(F10<>"",2%,"") -> 0.02 | G11: =IF(G10<>"",2%,"") -> 0.02 | H11: =IF(H10<>"",2%,"") | I11: =IF(I10<>"",2%,"") | J11: =IF(J10<>"",2%,"") | K11: =IF(K10<>"",2%,"") | L11: =IF(L10<>"",2%,"") | M11: =IF(M10<>"",2%,"") | ... T11: =IF(T10<>"",2%,"")
B12: Iníce de crescimento dos preços | E12: 1 | F12: =IF(F10<>"",E12*(1+F11),"") -> 1.02 | G12: =IF(G10<>"",F12*(1+G11),"") -> 1.0404 | H12: =IF(H10<>"",G12*(1+H11),"") | I12: =IF(I10<>"",H12*(1+I11),"") | J12: =IF(J10<>"",I12*(1+J11),"") | K12: =IF(K10<>"",J12*(1+K11),"") | L12: =IF(L10<>"",K12*(1+L11),"") | M12: =IF(M10<>"",L12*(1+M11),"") | ... T12: =IF(T10<>"",S12*(1+T11),"")
B13: Taxa de crescimento dos salários | F13: =IF(F10<>"",2%,"") -> 0.02 | G13: =IF(G10<>"",2%,"") -> 0.02 | H13: =IF(H10<>"",2%,"") | I13: =IF(I10<>"",2%,"") | J13: =IF(J10<>"",2%,"") | K13: =IF(K10<>"",2%,"") | L13: =IF(L10<>"",2%,"") | M13: =IF(M10<>"",2%,"") | ... T13: =IF(T10<>"",2%,"")
B14: Iníce de crescimento dos salários | F14: 1 | G14: =IF(G12<>"",F14*(1+G13),"") -> 1.02 | H14: =IF(H12<>"",G14*(1+H13),"") | I14: =IF(I12<>"",H14*(1+I13),"") | J14: =IF(J12<>"",I14*(1+J13),"") | K14: =IF(K12<>"",J14*(1+K13),"") | L14: =IF(L12<>"",K14*(1+L13),"") | M14: =IF(M12<>"",L14*(1+M13),"") | N14: =IF(N12<>"",M14*(1+N13),"") | ... T14: =IF(T12<>"",S14*(1+T13),"")
B16: 2. Vendas e serviços prestados
B18: 2.1. Vendas de mercadorias (valor em euros) | F18: =IF(F$8=1,F$4,"") -> 2024 | G18: =IF(G$8=1,F18+1,"") -> 2025 | H18: =IF(H$8=1,G18+1,"") | I18: =IF(I$8=1,H18+1,"") | J18: =IF(J$8=1,I18+1,"") | K18: =IF(K$8=1,J18+1,"") | L18: =IF(L$8=1,K18+1,"") | M18: =IF(M$8=1,L18+1,"") | N18: =IF(N$8=1,M18+1,"") | ... T18: =IF(T$8=1,S18+1,"")
A19: Criar botão para adicionar os elementos que se pretenderem | B19: Mercadoria 1 | C19: Quantidade | F19: 20000 | G19: 25000 | H19: 28000 | I19: 30000 | J19: 35000
C20: Preço de Venda | F20: 10 | G20: 12 | H20: 13 | I20: 13 | J20: 14
C21: Margem Bruta | F21: 0.5 | G21: 0.5 | H21: 0.5 | I21: 0.5 | J21: 0.4
C22: Taxa de IVA | F22: 0.23 | G22: 0.23 | H22: 0.23 | I22: 0.23 | J22: 0.23
B23: Mercadoria 2 | C23: Quantidade | F23: 2000 | G23: 2500 | H23: 2800 | I23: 3000 | J23: 3500
C24: Preço de Venda | F24: 10 | G24: 12 | H24: 13 | I24: 13 | J24: 14
C25: Margem Bruta | F25: 0.5 | G25: 0.5 | H25: 0.5 | I25: 0.5 | J25: 0.4
C26: Taxa de IVA | F26: 0.23 | G26: 0.23 | H26: 0.23 | I26: 0.23 | J26: 0.23
B28: 2.2. Vendas de produtos (valor em euros) | F28: =IF(F$8=1,F$4,"") -> 2024 | G28: =IF(G$8=1,F28+1,"") -> 2025 | H28: =IF(H$8=1,G28+1,"") | I28: =IF(I$8=1,H28+1,"") | J28: =IF(J$8=1,I28+1,"") | K28: =IF(K$8=1,J28+1,"") | L28: =IF(L$8=1,K28+1,"") | M28: =IF(M$8=1,L28+1,"") | N28: =IF(N$8=1,M28+1,"") | ... T28: =IF(T$8=1,S28+1,"")
A29: Criar botão para adicionar os elementos que se pretenderem | B29: Produto 1 | C29: Quantidade | F29: 2000 | G29: 2500 | H29: 2800 | I29: 3000 | J29: 3500
C30: Preço de Venda | F30: 10 | G30: 12 | H30: 13 | I30: 13 | J30: 14
C31: Margem Bruta | F31: 0.5 | G31: 0.5 | H31: 0.5 | I31: 0.5 | J31: 0.4
C32: Taxa de IVA | F32: 0.23 | G32: 0.23 | H32: 0.23 | I32: 0.23 | J32: 0.23
B33: Produto 2 | C33: Quantidade | F33: 2000 | G33: 2500 | H33: 2800 | I33: 3000 | J33: 3500
C34: Preço de Venda | F34: 10 | G34: 12 | H34: 13 | I34: 13 | J34: 14
C35: Margem Bruta | F35: 0.5 | G35: 0.5 | H35: 0.5 | I35: 0.5 | J35: 0.4
C36: Taxa de IVA | F36: 0.23 | G36: 0.23 | H36: 0.23 | I36: 0.23 | J36: 0.23
B38: 2.3. Prestação de serviços (valor em euros) | F38: =IF(F$8=1,F$4,"") -> 2024 | G38: =IF(G$8=1,F38+1,"") -> 2025 | H38: =IF(H$8=1,G38+1,"") | I38: =IF(I$8=1,H38+1,"") | J38: =IF(J$8=1,I38+1,"") | K38: =IF(K$8=1,J38+1,"") | L38: =IF(L$8=1,K38+1,"") | M38: =IF(M$8=1,L38+1,"") | N38: =IF(N$8=1,M38+1,"") | ... T38: =IF(T$8=1,S38+1,"")
A39: Criar botão para adicionar os elementos que se pretenderem | B39: Serviço 1 | C39: Quantidade | F39: 2000 | G39: 2500 | H39: 2800 | I39: 3000 | J39: 3500
C40: Preço de Venda | F40: 10 | G40: 12 | H40: 13 | I40: 13 | J40: 14
C41: Taxa de IVA | F41: 0.23 | G41: 0.23 | H41: 0.23 | I41: 0.23 | J41: 0.23
B42: Serviço 2 | C42: Quantidade | F42: 2000 | G42: 2500 | H42: 2800 | I42: 3000 | J42: 3500
C43: Preço de Venda | F43: 10 | G43: 12 | H43: 13 | I43: 13 | J43: 14
C44: Taxa de IVA | F44: 0.23 | G44: 0.23 | H44: 0.23 | I44: 0.23 | J44: 0.23
B46: 3. Fornecimento e serviços externos (valores em euros)
B48: Descrição | D48: Taxa de IVA | E48: Valor mensal | F48: =IF(F$8=1,F$4,"") -> 2024 | G48: =IF(G$8=1,F48+1,"") -> 2025 | H48: =IF(H$8=1,G48+1,"") | I48: =IF(I$8=1,H48+1,"") | J48: =IF(J$8=1,I48+1,"") | K48: =IF(K$8=1,J48+1,"") | L48: =IF(L$8=1,K48+1,"") | M48: =IF(M$8=1,L48+1,"") | N48: =IF(N$8=1,M48+1,"") | ... T48: =IF(T$8=1,S48+1,"")
B49: Subcontratos
B50: Subcontratos | D50: 0.23 | E50: 100 | F50: =IF(F$8=1,E50*12*(1+F$11),"") -> 1224 | G50: =IF(G$8=1,F50*(1+G$11),"") -> 1248.48 | H50: =IF(H$8=1,G50*(1+H$11),"") | I50: =IF(I$8=1,H50*(1+I$11),"") | J50: =IF(J$8=1,I50*(1+J$11),"") | K50: =IF(K$8=1,J50*(1+K$11),"") | L50: =IF(L$8=1,K50*(1+L$11),"") | M50: =IF(M$8=1,L50*(1+M$11),"") | N50: =IF(N$8=1,M50*(1+N$11),"") | ... T50: =IF(T$8=1,S50*(1+T$11),"")
B51: Serviços Especializados
B52: Trabalhos Especializados | D52: 0.23 | E52: 60 | F52: =IF(F$8=1,E52*12*(1+F$11),"") -> 734.4 | G52: =IF(G$8=1,F52*(1+G$11),"") -> 749.088 | H52: =IF(H$8=1,G52*(1+H$11),"") | I52: =IF(I$8=1,H52*(1+I$11),"") | J52: =IF(J$8=1,I52*(1+J$11),"") | K52: =IF(K$8=1,J52*(1+K$11),"") | L52: =IF(L$8=1,K52*(1+L$11),"") | M52: =IF(M$8=1,L52*(1+M$11),"") | N52: =IF(N$8=1,M52*(1+N$11),"") | ... T52: =IF(T$8=1,S52*(1+T$11),"")
B53: Publicidade e Propaganda | D53: 0.23 | E53: 20 | F53: =IF(F$8=1,E53*12*(1+F$11),"") -> 244.8 | G53: =IF(G$8=1,F53*(1+G$11),"") -> 249.696 | H53: =IF(H$8=1,G53*(1+H$11),"") | I53: =IF(I$8=1,H53*(1+I$11),"") | J53: =IF(J$8=1,I53*(1+J$11),"") | K53: =IF(K$8=1,J53*(1+K$11),"") | L53: =IF(L$8=1,K53*(1+L$11),"") | M53: =IF(M$8=1,L53*(1+M$11),"") | N53: =IF(N$8=1,M53*(1+N$11),"") | ... T53: =IF(T$8=1,S53*(1+T$11),"")
B54: Vigilância e Segurança | D54: 0.23 | E54: 40 | F54: =IF(F$8=1,E54*12*(1+F$11),"") -> 489.6 | G54: =IF(G$8=1,F54*(1+G$11),"") -> 499.392 | H54: =IF(H$8=1,G54*(1+H$11),"") | I54: =IF(I$8=1,H54*(1+I$11),"") | J54: =IF(J$8=1,I54*(1+J$11),"") | K54: =IF(K$8=1,J54*(1+K$11),"") | L54: =IF(L$8=1,K54*(1+L$11),"") | M54: =IF(M$8=1,L54*(1+M$11),"") | N54: =IF(N$8=1,M54*(1+N$11),"") | ... T54: =IF(T$8=1,S54*(1+T$11),"")
B55: Honorários | D55: 0.23 | E55: 50 | F55: =IF(F$8=1,E55*12*(1+F$11),"") -> 612 | G55: =IF(G$8=1,F55*(1+G$11),"") -> 624.24 | H55: =IF(H$8=1,G55*(1+H$11),"") | I55: =IF(I$8=1,H55*(1+I$11),"") | J55: =IF(J$8=1,I55*(1+J$11),"") | K55: =IF(K$8=1,J55*(1+K$11),"") | L55: =IF(L$8=1,K55*(1+L$11),"") | M55: =IF(M$8=1,L55*(1+M$11),"") | N55: =IF(N$8=1,M55*(1+N$11),"") | ... T55: =IF(T$8=1,S55*(1+T$11),"")
B56: Comissões | D56: 0.23 | E56: 60 | F56: =IF(F$8=1,E56*12*(1+F$11),"") -> 734.4 | G56: =IF(G$8=1,F56*(1+G$11),"") -> 749.088 | H56: =IF(H$8=1,G56*(1+H$11),"") | I56: =IF(I$8=1,H56*(1+I$11),"") | J56: =IF(J$8=1,I56*(1+J$11),"") | K56: =IF(K$8=1,J56*(1+K$11),"") | L56: =IF(L$8=1,K56*(1+L$11),"") | M56: =IF(M$8=1,L56*(1+M$11),"") | N56: =IF(N$8=1,M56*(1+N$11),"") | ... T56: =IF(T$8=1,S56*(1+T$11),"")
B57: Conservação e Reparação | D57: 0.23 | E57: 100 | F57: =IF(F$8=1,E57*12*(1+F$11),"") -> 1224 | G57: =IF(G$8=1,F57*(1+G$11),"") -> 1248.48 | H57: =IF(H$8=1,G57*(1+H$11),"") | I57: =IF(I$8=1,H57*(1+I$11),"") | J57: =IF(J$8=1,I57*(1+J$11),"") | K57: =IF(K$8=1,J57*(1+K$11),"") | L57: =IF(L$8=1,K57*(1+L$11),"") | M57: =IF(M$8=1,L57*(1+M$11),"") | N57: =IF(N$8=1,M57*(1+N$11),"") | ... T57: =IF(T$8=1,S57*(1+T$11),"")
B58: Materiais
B59: Ferramentas e Utensílios de Desgaste Rápido | D59: 0.23 | E59: 20 | F59: =IF(F$8=1,E59*12*(1+F$11),"") -> 244.8 | G59: =IF(G$8=1,F59*(1+G$11),"") -> 249.696 | H59: =IF(H$8=1,G59*(1+H$11),"") | I59: =IF(I$8=1,H59*(1+I$11),"") | J59: =IF(J$8=1,I59*(1+J$11),"") | K59: =IF(K$8=1,J59*(1+K$11),"") | L59: =IF(L$8=1,K59*(1+L$11),"") | M59: =IF(M$8=1,L59*(1+M$11),"") | N59: =IF(N$8=1,M59*(1+N$11),"") | ... T59: =IF(T$8=1,S59*(1+T$11),"")
B60: Livros e Documentação Técnica | D60: 0.23 | E60: 32 | F60: =IF(F$8=1,E60*12*(1+F$11),"") -> 391.68 | G60: =IF(G$8=1,F60*(1+G$11),"") -> 399.5136 | H60: =IF(H$8=1,G60*(1+H$11),"") | I60: =IF(I$8=1,H60*(1+I$11),"") | J60: =IF(J$8=1,I60*(1+J$11),"") | K60: =IF(K$8=1,J60*(1+K$11),"") | L60: =IF(L$8=1,K60*(1+L$11),"") | M60: =IF(M$8=1,L60*(1+M$11),"") | N60: =IF(N$8=1,M60*(1+N$11),"") | ... T60: =IF(T$8=1,S60*(1+T$11),"")
B61: Material de Escritório | D61: 0.23 | E61: 14 | F61: =IF(F$8=1,E61*12*(1+F$11),"") -> 171.36 | G61: =IF(G$8=1,F61*(1+G$11),"") -> 174.7872 | H61: =IF(H$8=1,G61*(1+H$11),"") | I61: =IF(I$8=1,H61*(1+I$11),"") | J61: =IF(J$8=1,I61*(1+J$11),"") | K61: =IF(K$8=1,J61*(1+K$11),"") | L61: =IF(L$8=1,K61*(1+L$11),"") | M61: =IF(M$8=1,L61*(1+M$11),"") | N61: =IF(N$8=1,M61*(1+N$11),"") | ... T61: =IF(T$8=1,S61*(1+T$11),"")
B62: Artigos para Oferta | D62: 0.23 | E62: 25 | F62: =IF(F$8=1,E62*12*(1+F$11),"") -> 306 | G62: =IF(G$8=1,F62*(1+G$11),"") -> 312.12 | H62: =IF(H$8=1,G62*(1+H$11),"") | I62: =IF(I$8=1,H62*(1+I$11),"") | J62: =IF(J$8=1,I62*(1+J$11),"") | K62: =IF(K$8=1,J62*(1+K$11),"") | L62: =IF(L$8=1,K62*(1+L$11),"") | M62: =IF(M$8=1,L62*(1+M$11),"") | N62: =IF(N$8=1,M62*(1+N$11),"") | ... T62: =IF(T$8=1,S62*(1+T$11),"")
B63: Energia e Fluidos
B64: Eletricidade | D64: 0.23 | E64: 120 | F64: =IF(F$8=1,E64*12*(1+F$11),"") -> 1468.8 | G64: =IF(G$8=1,F64*(1+G$11),"") -> 1498.176 | H64: =IF(H$8=1,G64*(1+H$11),"") | I64: =IF(I$8=1,H64*(1+I$11),"") | J64: =IF(J$8=1,I64*(1+J$11),"") | K64: =IF(K$8=1,J64*(1+K$11),"") | L64: =IF(L$8=1,K64*(1+L$11),"") | M64: =IF(M$8=1,L64*(1+M$11),"") | N64: =IF(N$8=1,M64*(1+N$11),"") | ... T64: =IF(T$8=1,S64*(1+T$11),"")
B65: Combustíveis | D65: 0.23 | E65: 150 | F65: =IF(F$8=1,E65*12*(1+F$11),"") -> 1836 | G65: =IF(G$8=1,F65*(1+G$11),"") -> 1872.72 | H65: =IF(H$8=1,G65*(1+H$11),"") | I65: =IF(I$8=1,H65*(1+I$11),"") | J65: =IF(J$8=1,I65*(1+J$11),"") | K65: =IF(K$8=1,J65*(1+K$11),"") | L65: =IF(L$8=1,K65*(1+L$11),"") | M65: =IF(M$8=1,L65*(1+M$11),"") | N65: =IF(N$8=1,M65*(1+N$11),"") | ... T65: =IF(T$8=1,S65*(1+T$11),"")
B66: Água | D66: 0.06 | E66: 20 | F66: =IF(F$8=1,E66*12*(1+F$11),"") -> 244.8 | G66: =IF(G$8=1,F66*(1+G$11),"") -> 249.696 | H66: =IF(H$8=1,G66*(1+H$11),"") | I66: =IF(I$8=1,H66*(1+I$11),"") | J66: =IF(J$8=1,I66*(1+J$11),"") | K66: =IF(K$8=1,J66*(1+K$11),"") | L66: =IF(L$8=1,K66*(1+L$11),"") | M66: =IF(M$8=1,L66*(1+M$11),"") | N66: =IF(N$8=1,M66*(1+N$11),"") | ... T66: =IF(T$8=1,S66*(1+T$11),"")
B67: Deslocações, Estadas e Transportes
B68: Deslocações e Estadas | D68: 0.23 | E68: 10 | F68: =IF(F$8=1,E68*12*(1+F$11),"") -> 122.4 | G68: =IF(G$8=1,F68*(1+G$11),"") -> 124.848 | H68: =IF(H$8=1,G68*(1+H$11),"") | I68: =IF(I$8=1,H68*(1+I$11),"") | J68: =IF(J$8=1,I68*(1+J$11),"") | K68: =IF(K$8=1,J68*(1+K$11),"") | L68: =IF(L$8=1,K68*(1+L$11),"") | M68: =IF(M$8=1,L68*(1+M$11),"") | N68: =IF(N$8=1,M68*(1+N$11),"") | ... T68: =IF(T$8=1,S68*(1+T$11),"")
B69: Transportes de Pessoal | D69: 0.23 | E69: 50 | F69: =IF(F$8=1,E69*12*(1+F$11),"") -> 612 | G69: =IF(G$8=1,F69*(1+G$11),"") -> 624.24 | H69: =IF(H$8=1,G69*(1+H$11),"") | I69: =IF(I$8=1,H69*(1+I$11),"") | J69: =IF(J$8=1,I69*(1+J$11),"") | K69: =IF(K$8=1,J69*(1+K$11),"") | L69: =IF(L$8=1,K69*(1+L$11),"") | M69: =IF(M$8=1,L69*(1+M$11),"") | N69: =IF(N$8=1,M69*(1+N$11),"") | ... T69: =IF(T$8=1,S69*(1+T$11),"")
B70: Transportes de Mercadorias | D70: 0.23 | E70: 26 | F70: =IF(F$8=1,E70*12*(1+F$11),"") -> 318.24 | G70: =IF(G$8=1,F70*(1+G$11),"") -> 324.6048 | H70: =IF(H$8=1,G70*(1+H$11),"") | I70: =IF(I$8=1,H70*(1+I$11),"") | J70: =IF(J$8=1,I70*(1+J$11),"") | K70: =IF(K$8=1,J70*(1+K$11),"") | L70: =IF(L$8=1,K70*(1+L$11),"") | M70: =IF(M$8=1,L70*(1+M$11),"") | N70: =IF(N$8=1,M70*(1+N$11),"") | ... T70: =IF(T$8=1,S70*(1+T$11),"")
B71: Serviços Diversos
B72: Rendas e Alugueres | D72: 0 | E72: 200 | F72: =IF(F$8=1,E72*12*(1+F$11),"") -> 2448 | G72: =IF(G$8=1,F72*(1+G$11),"") -> 2496.96 | H72: =IF(H$8=1,G72*(1+H$11),"") | I72: =IF(I$8=1,H72*(1+I$11),"") | J72: =IF(J$8=1,I72*(1+J$11),"") | K72: =IF(K$8=1,J72*(1+K$11),"") | L72: =IF(L$8=1,K72*(1+L$11),"") | M72: =IF(M$8=1,L72*(1+M$11),"") | N72: =IF(N$8=1,M72*(1+N$11),"") | ... T72: =IF(T$8=1,S72*(1+T$11),"")
B73: Comunicação | D73: 0.23 | E73: 50 | F73: =IF(F$8=1,E73*12*(1+F$11),"") -> 612 | G73: =IF(G$8=1,F73*(1+G$11),"") -> 624.24 | H73: =IF(H$8=1,G73*(1+H$11),"") | I73: =IF(I$8=1,H73*(1+I$11),"") | J73: =IF(J$8=1,I73*(1+J$11),"") | K73: =IF(K$8=1,J73*(1+K$11),"") | L73: =IF(L$8=1,K73*(1+L$11),"") | M73: =IF(M$8=1,L73*(1+M$11),"") | N73: =IF(N$8=1,M73*(1+N$11),"") | ... T73: =IF(T$8=1,S73*(1+T$11),"")
B74: Seguros | D74: 0 | E74: 36 | F74: =IF(F$8=1,E74*12*(1+F$11),"") -> 440.64 | G74: =IF(G$8=1,F74*(1+G$11),"") -> 449.4528 | H74: =IF(H$8=1,G74*(1+H$11),"") | I74: =IF(I$8=1,H74*(1+I$11),"") | J74: =IF(J$8=1,I74*(1+J$11),"") | K74: =IF(K$8=1,J74*(1+K$11),"") | L74: =IF(L$8=1,K74*(1+L$11),"") | M74: =IF(M$8=1,L74*(1+M$11),"") | N74: =IF(N$8=1,M74*(1+N$11),"") | ... T74: =IF(T$8=1,S74*(1+T$11),"")
B75: Royalties | D75: 0.23 | E75: 256 | F75: =IF(F$8=1,E75*12*(1+F$11),"") -> 3133.44 | G75: =IF(G$8=1,F75*(1+G$11),"") -> 3196.1088 | H75: =IF(H$8=1,G75*(1+H$11),"") | I75: =IF(I$8=1,H75*(1+I$11),"") | J75: =IF(J$8=1,I75*(1+J$11),"") | K75: =IF(K$8=1,J75*(1+K$11),"") | L75: =IF(L$8=1,K75*(1+L$11),"") | M75: =IF(M$8=1,L75*(1+M$11),"") | N75: =IF(N$8=1,M75*(1+N$11),"") | ... T75: =IF(T$8=1,S75*(1+T$11),"")
B76: Contencioso e Notariado | D76: 0.23 | E76: 50 | F76: =IF(F$8=1,E76*12*(1+F$11),"") -> 612 | G76: =IF(G$8=1,F76*(1+G$11),"") -> 624.24 | H76: =IF(H$8=1,G76*(1+H$11),"") | I76: =IF(I$8=1,H76*(1+I$11),"") | J76: =IF(J$8=1,I76*(1+J$11),"") | K76: =IF(K$8=1,J76*(1+K$11),"") | L76: =IF(L$8=1,K76*(1+L$11),"") | M76: =IF(M$8=1,L76*(1+M$11),"") | N76: =IF(N$8=1,M76*(1+N$11),"") | ... T76: =IF(T$8=1,S76*(1+T$11),"")
B77: Despesas de Representação | D77: 0.23 | E77: 25 | F77: =IF(F$8=1,E77*12*(1+F$11),"") -> 306 | G77: =IF(G$8=1,F77*(1+G$11),"") -> 312.12 | H77: =IF(H$8=1,G77*(1+H$11),"") | I77: =IF(I$8=1,H77*(1+I$11),"") | J77: =IF(J$8=1,I77*(1+J$11),"") | K77: =IF(K$8=1,J77*(1+K$11),"") | L77: =IF(L$8=1,K77*(1+L$11),"") | M77: =IF(M$8=1,L77*(1+M$11),"") | N77: =IF(N$8=1,M77*(1+N$11),"") | ... T77: =IF(T$8=1,S77*(1+T$11),"")
B78: Limpeza, Higiene e Conforto | D78: 0.23 | E78: 50 | F78: =IF(F$8=1,E78*12*(1+F$11),"") -> 612 | G78: =IF(G$8=1,F78*(1+G$11),"") -> 624.24 | H78: =IF(H$8=1,G78*(1+H$11),"") | I78: =IF(I$8=1,H78*(1+I$11),"") | J78: =IF(J$8=1,I78*(1+J$11),"") | K78: =IF(K$8=1,J78*(1+K$11),"") | L78: =IF(L$8=1,K78*(1+L$11),"") | M78: =IF(M$8=1,L78*(1+M$11),"") | N78: =IF(N$8=1,M78*(1+N$11),"") | ... T78: =IF(T$8=1,S78*(1+T$11),"")
B79: Outros Serviços
B80: Outros Serviços | D80: 0.23 | E80: 10 | F80: =IF(F$8=1,E80*12*(1+F$11),"") -> 122.4 | G80: =IF(G$8=1,F80*(1+G$11),"") -> 124.848 | H80: =IF(H$8=1,G80*(1+H$11),"") | I80: =IF(I$8=1,H80*(1+I$11),"") | J80: =IF(J$8=1,I80*(1+J$11),"") | K80: =IF(K$8=1,J80*(1+K$11),"") | L80: =IF(L$8=1,K80*(1+L$11),"") | M80: =IF(M$8=1,L80*(1+M$11),"") | N80: =IF(N$8=1,M80*(1+N$11),"") | ... T80: =IF(T$8=1,S80*(1+T$11),"")
B82: 4. Gastos com pessoal
B84: Quadro de pessoal | F84: =IF(F$8=1,F$4,"") -> 2024 | G84: =IF(G$8=1,F84+1,"") -> 2025 | H84: =IF(H$8=1,G84+1,"") | I84: =IF(I$8=1,H84+1,"") | J84: =IF(J$8=1,I84+1,"") | K84: =IF(K$8=1,J84+1,"") | L84: =IF(L$8=1,K84+1,"") | M84: =IF(M$8=1,L84+1,"") | N84: =IF(N$8=1,M84+1,"") | ... T84: =IF(T$8=1,S84+1,"")
A85: Criar botão para adicionar os elementos que se pretenderem | B85: Gerência | C85: Nº de trabalhadores | F85: 1 | G85: 1 | H85: 1 | I85: 1 | J85: 1
C86: Salário mensal | F86: 1500 | G86: =IF(G$8=1,F86*(1+F$13),"") -> 1530 | H86: =IF(H$8=1,G86*(1+G$13),"") | I86: =IF(I$8=1,H86*(1+H$13),"") | J86: =IF(J$8=1,I86*(1+I$13),"") | K86: =IF(K$8=1,J86*(1+J$13),"") | L86: =IF(L$8=1,K86*(1+K$13),"") | M86: =IF(M$8=1,L86*(1+L$13),"") | N86: =IF(N$8=1,M86*(1+M$13),"") | ... T86: =IF(T$8=1,S86*(1+S$13),"")
B87: Administrativo | C87: Nº de trabalhadores | F87: 1 | G87: 1 | H87: 1 | I87: 1 | J87: 1
C88: Salário mensal | F88: 900 | G88: =IF(G$8=1,F88*(1+F$13),"") -> 918 | H88: =IF(H$8=1,G88*(1+G$13),"") | I88: =IF(I$8=1,H88*(1+H$13),"") | J88: =IF(J$8=1,I88*(1+I$13),"") | K88: =IF(K$8=1,J88*(1+J$13),"") | L88: =IF(L$8=1,K88*(1+K$13),"") | M88: =IF(M$8=1,L88*(1+L$13),"") | N88: =IF(N$8=1,M88*(1+M$13),"") | ... T88: =IF(T$8=1,S88*(1+S$13),"")
B89: Comerciais | C89: Nº de trabalhadores | F89: 1 | G89: =F89 -> 1 | H89: =G89 -> 1 | I89: =H89 -> 1 | J89: =I89 -> 1
C90: Salário mensal | F90: 900 | G90: =IF(G$8=1,F90*(1+F$13),"") -> 918 | H90: =IF(H$8=1,G90*(1+G$13),"") | I90: =IF(I$8=1,H90*(1+H$13),"") | J90: =IF(J$8=1,I90*(1+I$13),"") | K90: =IF(K$8=1,J90*(1+J$13),"") | L90: =IF(L$8=1,K90*(1+K$13),"") | M90: =IF(M$8=1,L90*(1+L$13),"") | N90: =IF(N$8=1,M90*(1+M$13),"") | ... T90: =IF(T$8=1,S90*(1+S$13),"")
B92: Outra informação:
B93: =_xlfn.CONCAT("Subsídio de alimentação (valor diário em ",F4,")") -> Subsídio de alimentação (valor diário em 2024) | D93: 8.5
B94: Outros gastos com pessoal (% dos Salários) | D94: 0.01
B95: Salários (valor em euros) | F95: =IF(F$8=1,F$4,"") -> 2024 | G95: =IF(G$8=1,F95+1,"") -> 2025 | H95: =IF(H$8=1,G95+1,"") | I95: =IF(I$8=1,H95+1,"") | J95: =IF(J$8=1,I95+1,"") | K95: =IF(K$8=1,J95+1,"") | L95: =IF(L$8=1,K95+1,"") | M95: =IF(M$8=1,L95+1,"") | N95: =IF(N$8=1,M95+1,"") | ... T95: =IF(T$8=1,S95+1,"")
B96: =B85 -> Gerência | F96: =IF(F$8=1,F85*F86*14,"") -> 21000 | G96: =IF(G$8=1,G85*G86*14,"") -> 21420 | H96: =IF(H$8=1,H85*H86*14,"") | I96: =IF(I$8=1,I85*I86*14,"") | J96: =IF(J$8=1,J85*J86*14,"") | K96: =IF(K$8=1,K85*K86*14,"") | L96: =IF(L$8=1,L85*L86*14,"") | M96: =IF(M$8=1,M85*M86*14,"") | ... T96: =IF(T$8=1,T85*T86*14,"")
B97: =B87 -> Administrativo | F97: =IF(F$8=1,F87*F88*14,"") -> 12600 | G97: =IF(G$8=1,G87*G88*14,"") -> 12852 | H97: =IF(H$8=1,H87*H88*14,"") | I97: =IF(I$8=1,I87*I88*14,"") | J97: =IF(J$8=1,J87*J88*14,"") | K97: =IF(K$8=1,K87*K88*14,"") | L97: =IF(L$8=1,L87*L88*14,"") | M97: =IF(M$8=1,M87*M88*14,"") | ... T97: =IF(T$8=1,T87*T88*14,"")
B98: =B89 -> Comerciais | F98: =IF(F$8=1,F89*F90*14,"") -> 12600 | G98: =IF(G$8=1,G89*G90*14,"") -> 12852 | H98: =IF(H$8=1,H89*H90*14,"") | I98: =IF(I$8=1,I89*I90*14,"") | J98: =IF(J$8=1,J89*J90*14,"") | K98: =IF(K$8=1,K89*K90*14,"") | L98: =IF(L$8=1,L89*L90*14,"") | M98: =IF(M$8=1,M89*M90*14,"") | ... T98: =IF(T$8=1,T89*T90*14,"")
B100: Subsídio de alimentação | F100: =IF(F$8=1,F$4,"") -> 2024 | G100: =IF(G$8=1,F100+1,"") -> 2025 | H100: =IF(H$8=1,G100+1,"") | I100: =IF(I$8=1,H100+1,"") | J100: =IF(J$8=1,I100+1,"") | K100: =IF(K$8=1,J100+1,"") | L100: =IF(L$8=1,K100+1,"") | M100: =IF(M$8=1,L100+1,"") | N100: =IF(N$8=1,M100+1,"") | ... T100: =IF(T$8=1,S100+1,"")
B101: Subsídio de alimentação | F101: =IF(F$8=1,(F85+F87+F89)*22*$D93*11*F$14,"") -> 6171 | G101: =IF(G$8=1,(G85+G87+G89)*22*$D93*11*G$14,"") -> 6294.42 | H101: =IF(H$8=1,(H85+H87+H89)*22*$D93*11*H$14,"") | I101: =IF(I$8=1,(I85+I87+I89)*22*$D93*11*I$14,"") | J101: =IF(J$8=1,(J85+J87+J89)*22*$D93*11*J$14,"") | K101: =IF(K$8=1,(K85+K87+K89)*22*$D93*11*K$14,"") | L101: =IF(L$8=1,(L85+L87+L89)*22*$D93*11*L$14,"") | M101: =IF(M$8=1,(M85+M87+M89)*22*$D93*11*M$14,"") | ... T101: =IF(T$8=1,(T85+T87+T89)*22*$D93*11*T$14,"")
B103: Outros gastos com pessoal | F103: =IF(F$8=1,F$4,"") -> 2024 | G103: =IF(G$8=1,F103+1,"") -> 2025 | H103: =IF(H$8=1,G103+1,"") | I103: =IF(I$8=1,H103+1,"") | J103: =IF(J$8=1,I103+1,"") | K103: =IF(K$8=1,J103+1,"") | L103: =IF(L$8=1,K103+1,"") | M103: =IF(M$8=1,L103+1,"") | N103: =IF(N$8=1,M103+1,"") | ... T103: =IF(T$8=1,S103+1,"")
B104: % do valor dos salários | F104: =IF(F$8=1,SUM(F96:F98)*$D94,"") -> 462 | G104: =IF(G$8=1,SUM(G96:G98)*$D94,"") -> 471.24 | H104: =IF(H$8=1,SUM(H96:H98)*$D94,"") | I104: =IF(I$8=1,SUM(I96:I98)*$D94,"") | J104: =IF(J$8=1,SUM(J96:J98)*$D94,"") | K104: =IF(K$8=1,SUM(K96:K98)*$D94,"") | L104: =IF(L$8=1,SUM(L96:L98)*$D94,"") | M104: =IF(M$8=1,SUM(M96:M98)*$D94,"") | ... T104: =IF(T$8=1,SUM(T96:T98)*$D94,"")
B106: 5. Outros gastos operacionais
B108: Outros gastos operacionais | D108: % | K108: =IF(K$8=1,J108+1,"") | L108: =IF(L$8=1,K108+1,"") | M108: =IF(M$8=1,L108+1,"") | N108: =IF(N$8=1,M108+1,"") | O108: =IF(O$8=1,N108+1,"") | P108: =IF(P$8=1,O108+1,"") | Q108: =IF(Q$8=1,P108+1,"") | R108: =IF(R$8=1,Q108+1,"") | ... T108: =IF(T$8=1,S108+1,"")
B109: % do volume de vendas e serviços prestados | D109: 0.01 | K109: =IF(K$8=1,$D109*DR!H4,"") | L109: =IF(L$8=1,$D109*DR!I4,"") | M109: =IF(M$8=1,$D109*DR!J4,"") | N109: =IF(N$8=1,$D109*DR!K4,"") | O109: =IF(O$8=1,$D109*DR!L4,"") | P109: =IF(P$8=1,$D109*DR!M4,"") | Q109: =IF(Q$8=1,$D109*DR!N4,"") | R109: =IF(R$8=1,$D109*DR!O4,"") | ... T109: =IF(T$8=1,$D109*DR!Q4,"")
B111: 6. Taxas fiscais e segurança social
B113: Descrição | D113: %
B114: Taxa de IRC | D114: 0.21
B115: Derrama municipal | D115: 0.015
B116: Taxa de retenção IRS | D116: 0.05
B117: Taxa de imposto de selo aplicável aos juros | D117: 0.04
B118: TSU Empresa | D118: 0.2375
B119: TSU Colaboradores | D119: 0.11
...

Sheet Sheet1
C3: Descrição | I3: Camião 1
C4: Tipo de Ativo | I4: Ativo fixo tangível
C5: Classe | I5: Equipamento de transporte
C6: Valor de aquisição | I6: 10000
C7: Vida útil | I7: 5
C8: Ano de aquisição | I8: 2023
I9: Depreciações do exercício | O9: Depreciações cumuladas | U9: Ativo líquido
B10: item | C10: Descrição | D10: Tipo de Ativo | E10: Classe | F10: V.aquisição | G10: Vida útil | H10: Ano de aquisição | I10: 2024 | J10: 2025 | K10: 2026 | L10: 2027 | M10: 2028 | N10: 2029 | O10: =I10 -> 2024 | P10: =J10 -> 2025 | Q10: =K10 -> 2026 | R10: =L10 -> 2027 | S10: =M10 -> 2028 | T10: =N10 -> 2029 | U10: =O10 -> 2024 | V10: =P10 -> 2025 | ... Z10: =T10 -> 2029
B11: 1 | C11: Camião 1 | D11: AFT | E11: =I4 -> Ativo fixo tangível | F11: 10000 | G11: 5 | H11: 2023 | I11: =IF(AND(I$10>$H11,I$10-$H11<$G11+1)=TRUE,$F11/$G11) -> 2000 | J11: =IF(AND(J$10>$H11,J$10-$H11<$G11+1)=TRUE,$F11/$G11) -> 2000 | K11: =IF(AND(K$10>$H11,K$10-$H11<$G11+1)=TRUE,$F11/$G11) -> 2000 | L11: =IF(AND(L$10>$H11,L$10-$H11<$G11+1)=TRUE,$F11/$G11) -> 2000 | M11: =IF(AND(M$10>$H11,M$10-$H11<$G11+1)=TRUE,$F11/$G11) -> 2000 | N11: =IF(AND(N$10>$H11,N$10-$H11<$G11+1)=TRUE,$F11/$G11) -> FALSE | O11: =IF(I11=FALSE,0,I11) -> 2000 | P11: =O11+IF(J11=FALSE,0,J11) -> 4000 | Q11: =P11+IF(K11=FALSE,0,K11) -> 6000 | R11: =Q11+IF(L11=FALSE,0,L11) -> 8000 | S11: =R11+IF(M11=FALSE,0,M11) -> 10000 | T11: =S11+IF(N11=FALSE,0,N11) -> 10000 | U11: =IF(I11=FALSE,0,$F11-O11) -> 8000 | V11: =IF(J11=FALSE,0,$F11-P11) -> 6000 | W11: =IF(K11=FALSE,0,$F11-Q11) -> 4000 | X11: =IF(L11=FALSE,0,$F11-R11) -> 2000 | Y11: =IF(M11=FALSE,0,$F11-S11) -> 0 | Z11: =IF(N11=FALSE,0,$F11-T11) -> 0
B12: 2 | C12: Patente | D12: AI | E12: Patentes | F12: 30000 | G12: 3 | H12: 2025 | I12: =IF(AND(I$10>$H12,I$10-$H12<$G12+1)=TRUE,$F12/$G12) -> FALSE | J12: =IF(AND(J$10>$H12,J$10-$H12<$G12+1)=TRUE,$F12/$G12) -> FALSE | K12: =IF(AND(K$10>$H12,K$10-$H12<$G12+1)=TRUE,$F12/$G12) -> 10000 | L12: =IF(AND(L$10>$H12,L$10-$H12<$G12+1)=TRUE,$F12/$G12) -> 10000 | M12: =IF(AND(M$10>$H12,M$10-$H12<$G12+1)=TRUE,$F12/$G12) -> 10000 | N12: =IF(AND(N$10>$H12,N$10-$H12<$G12+1)=TRUE,$F12/$G12) -> FALSE | O12: =N12+IF(I12=FALSE,0,I12) -> 0 | P12: =O12+IF(J12=FALSE,0,J12) -> 0 | Q12: =P12+IF(K12=FALSE,0,K12) -> 10000 | R12: =Q12+IF(L12=FALSE,0,L12) -> 20000 | S12: =R12+IF(M12=FALSE,0,M12) -> 30000 | T12: =S12+IF(N12=FALSE,0,N12) -> 30000 | U12: =IF(I12=FALSE,0,$F12-O12) -> 0 | V12: =IF(J12=FALSE,0,$F12-P12) -> 0 | W12: =IF(K12=FALSE,0,$F12-Q12) -> 20000 | X12: =IF(L12=FALSE,0,$F12-R12) -> 10000 | Y12: =IF(M12=FALSE,0,$F12-S12) -> 0 | Z12: =IF(N12=FALSE,0,$F12-T12) -> 0
B13: 3 | F13: 120000 | G13: 20 | H13: 2023 | I13: =IF(AND(I$10>$H13,I$10-$H13<$G13+1)=TRUE,$F13/$G13) -> 6000 | J13: =IF(AND(J$10>$H13,J$10-$H13<$G13+1)=TRUE,$F13/$G13) -> 6000 | K13: =IF(AND(K$10>$H13,K$10-$H13<$G13+1)=TRUE,$F13/$G13) -> 6000 | L13: =IF(AND(L$10>$H13,L$10-$H13<$G13+1)=TRUE,$F13/$G13) -> 6000 | M13: =IF(AND(M$10>$H13,M$10-$H13<$G13+1)=TRUE,$F13/$G13) -> 6000 | N13: =IF(AND(N$10>$H13,N$10-$H13<$G13+1)=TRUE,$F13/$G13) -> 6000 | O13: =N13+IF(I13=FALSE,0,I13) -> 12000 | P13: =O13+IF(J13=FALSE,0,J13) -> 18000 | Q13: =P13+IF(K13=FALSE,0,K13) -> 24000 | R13: =Q13+IF(L13=FALSE,0,L13) -> 30000 | S13: =R13+IF(M13=FALSE,0,M13) -> 36000 | T13: =S13+IF(N13=FALSE,0,N13) -> 42000 | U13: =IF(I13=FALSE,0,$F13-O13) -> 108000 | V13: =IF(J13=FALSE,0,$F13-P13) -> 102000 | W13: =IF(K13=FALSE,0,$F13-Q13) -> 96000 | X13: =IF(L13=FALSE,0,$F13-R13) -> 90000 | Y13: =IF(M13=FALSE,0,$F13-S13) -> 84000 | Z13: =IF(N13=FALSE,0,$F13-T13) -> 78000
F14: 5000 | G14: 4 | H14: 2023 | I14: =IF(AND(I$10>$H14,I$10-$H14<$G14+1)=TRUE,$F14/$G14) -> 1250 | J14: =IF(AND(J$10>$H14,J$10-$H14<$G14+1)=TRUE,$F14/$G14) -> 1250 | K14: =IF(AND(K$10>$H14,K$10-$H14<$G14+1)=TRUE,$F14/$G14) -> 1250 | L14: =IF(AND(L$10>$H14,L$10-$H14<$G14+1)=TRUE,$F14/$G14) -> 1250 | M14: =IF(AND(M$10>$H14,M$10-$H14<$G14+1)=TRUE,$F14/$G14) -> FALSE | N14: =IF(AND(N$10>$H14,N$10-$H14<$G14+1)=TRUE,$F14/$G14) -> FALSE | O14: =N14+IF(I14=FALSE,0,I14) -> 1250 | P14: =O14+IF(J14=FALSE,0,J14) -> 2500 | Q14: =P14+IF(K14=FALSE,0,K14) -> 3750 | R14: =Q14+IF(L14=FALSE,0,L14) -> 5000 | S14: =R14+IF(M14=FALSE,0,M14) -> 5000 | T14: =S14+IF(N14=FALSE,0,N14) -> 5000 | U14: =IF(I14=FALSE,0,$F14-O14) -> 3750 | V14: =IF(J14=FALSE,0,$F14-P14) -> 2500 | W14: =IF(K14=FALSE,0,$F14-Q14) -> 1250 | X14: =IF(L14=FALSE,0,$F14-R14) -> 0 | Y14: =IF(M14=FALSE,0,$F14-S14) -> 0 | Z14: =IF(N14=FALSE,0,$F14-T14) -> 0

Sheet Compras
B2: COMPRAS DE MERCADORIAS E MATÉRIAS PRIMAS
B3: Descrição | C3: =IF(Pressupostos!F$10<>"",Pressupostos!F$10,"") -> 2024 | D3: =IF(Pressupostos!G$10<>"",Pressupostos!G$10,"") -> 2025 | E3: =IF(Pressupostos!H$10<>"",Pressupostos!H$10,"") | F3: =IF(Pressupostos!I$10<>"",Pressupostos!I$10,"") | G3: =IF(Pressupostos!J$10<>"",Pressupostos!J$10,"") | H3: =IF(Pressupostos!K$10<>"",Pressupostos!K$10,"") | I3: =IF(Pressupostos!L$10<>"",Pressupostos!L$10,"") | J3: =IF(Pressupostos!M$10<>"",Pressupostos!M$10,"") | ... Q3: =IF(Pressupostos!T$10<>"",Pressupostos!T$10,"")
B4: Custo das mercadorias vendidas:
B5: =+Pressupostos!B19 -> Mercadoria 1 | C5: =IF(Pressupostos!F$10<>"",Pressupostos!F19*Pressupostos!F20*(1-Pressupostos!F21),"") -> 100000 | D5: =IF(Pressupostos!G$10<>"",Pressupostos!G19*Pressupostos!G20*(1-Pressupostos!G21),"") -> 150000 | E5: =IF(Pressupostos!H$10<>"",Pressupostos!H19*Pressupostos!H20*(1-Pressupostos!H21),"") | F5: =IF(Pressupostos!I$10<>"",Pressupostos!I19*Pressupostos!I20*(1-Pressupostos!I21),"") | G5: =IF(Pressupostos!J$10<>"",Pressupostos!J19*Pressupostos!J20*(1-Pressupostos!J21),"") | H5: =IF(Pressupostos!K$10<>"",Pressupostos!K19*Pressupostos!K20*(1-Pressupostos!K21),"") | I5: =IF(Pressupostos!L$10<>"",Pressupostos!L19*Pressupostos!L20*(1-Pressupostos!L21),"") | J5: =IF(Pressupostos!M$10<>"",Pressupostos!M19*Pressupostos!M20*(1-Pressupostos!M21),"") | ... Q5: =IF(Pressupostos!T$10<>"",Pressupostos!T19*Pressupostos!T20*(1-Pressupostos!T21),"")
B6: =+Pressupostos!B23 -> Mercadoria 2 | C6: =IF(Pressupostos!F$10<>"",Pressupostos!F23*Pressupostos!F24*(1-Pressupostos!F25),"") -> 10000 | D6: =IF(Pressupostos!G$10<>"",Pressupostos!G23*Pressupostos!G24*(1-Pressupostos!G25),"") -> 15000 | E6: =IF(Pressupostos!H$10<>"",Pressupostos!H23*Pressupostos!H24*(1-Pressupostos!H25),"") | F6: =IF(Pressupostos!I$10<>"",Pressupostos!I23*Pressupostos!I24*(1-Pressupostos!I25),"") | G6: =IF(Pressupostos!J$10<>"",Pressupostos!J23*Pressupostos!J24*(1-Pressupostos!J25),"") | H6: =IF(Pressupostos!K$10<>"",Pressupostos!K23*Pressupostos!K24*(1-Pressupostos!K25),"") | I6: =IF(Pressupostos!L$10<>"",Pressupostos!L23*Pressupostos!L24*(1-Pressupostos!L25),"") | J6: =IF(Pressupostos!M$10<>"",Pressupostos!M23*Pressupostos!M24*(1-Pressupostos!M25),"") | ... Q6: =IF(Pressupostos!T$10<>"",Pressupostos!T23*Pressupostos!T24*(1-Pressupostos!T25),"")
B7: Custo das matérias consumidas:
B8: =_xlfn.CONCAT("Matérias-primas do ",Pressupostos!B29) -> Matérias-primas do Produto 1 | C8: =IF(Pressupostos!F$10<>"",Pressupostos!F29*Pressupostos!F30*(1-Pressupostos!F31),"") -> 10000 | D8: =IF(Pressupostos!G$10<>"",Pressupostos!G29*Pressupostos!G30*(1-Pressupostos!G31),"") -> 15000 | E8: =IF(Pressupostos!H$10<>"",Pressupostos!H29*Pressupostos!H30*(1-Pressupostos!H31),"") | F8: =IF(Pressupostos!I$10<>"",Pressupostos!I29*Pressupostos!I30*(1-Pressupostos!I31),"") | G8: =IF(Pressupostos!J$10<>"",Pressupostos!J29*Pressupostos!J30*(1-Pressupostos!J31),"") | H8: =IF(Pressupostos!K$10<>"",Pressupostos!K29*Pressupostos!K30*(1-Pressupostos!K31),"") | I8: =IF(Pressupostos!L$10<>"",Pressupostos!L29*Pressupostos!L30*(1-Pressupostos!L31),"") | J8: =IF(Pressupostos!M$10<>"",Pressupostos!M29*Pressupostos!M30*(1-Pressupostos!M31),"") | ... Q8: =IF(Pressupostos!T$10<>"",Pressupostos!T29*Pressupostos!T30*(1-Pressupostos!T31),"")
B9: =_xlfn.CONCAT("Matérias-primas do ",Pressupostos!B33) -> Matérias-primas do Produto 2 | C9: =IF(Pressupostos!F$10<>"",Pressupostos!F33*Pressupostos!F34*(1-Pressupostos!F35),"") -> 10000 | D9: =IF(Pressupostos!G$10<>"",Pressupostos!G33*Pressupostos!G34*(1-Pressupostos!G35),"") -> 15000 | E9: =IF(Pressupostos!H$10<>"",Pressupostos!H33*Pressupostos!H34*(1-Pressupostos!H35),"") | F9: =IF(Pressupostos!I$10<>"",Pressupostos!I33*Pressupostos!I34*(1-Pressupostos!I35),"") | G9: =IF(Pressupostos!J$10<>"",Pressupostos!J33*Pressupostos!J34*(1-Pressupostos!J35),"") | H9: =IF(Pressupostos!K$10<>"",Pressupostos!K33*Pressupostos!K34*(1-Pressupostos!K35),"") | I9: =IF(Pressupostos!L$10<>"",Pressupostos!L33*Pressupostos!L34*(1-Pressupostos!L35),"") | J9: =IF(Pressupostos!M$10<>"",Pressupostos!M33*Pressupostos!M34*(1-Pressupostos!M35),"") | ... Q9: =IF(Pressupostos!T$10<>"",Pressupostos!T33*Pressupostos!T34*(1-Pressupostos!T35),"")
B10: Stock final de mercadorias:
B11: =B5 -> Mercadoria 1 | C11: =IF(Pressupostos!F$10<>"",C5/12*Pressupostos!$D$125,"") -> 4166.6667 | D11: =IF(Pressupostos!G$10<>"",D5/12*Pressupostos!$D$125,"") -> 6250 | E11: =IF(Pressupostos!H$10<>"",E5/12*Pressupostos!$D$125,"") | F11: =IF(Pressupostos!I$10<>"",F5/12*Pressupostos!$D$125,"") | G11: =IF(Pressupostos!J$10<>"",G5/12*Pressupostos!$D$125,"") | H11: =IF(Pressupostos!K$10<>"",H5/12*Pressupostos!$D$125,"") | I11: =IF(Pressupostos!L$10<>"",I5/12*Pressupostos!$D$125,"") | J11: =IF(Pressupostos!M$10<>"",J5/12*Pressupostos!$D$125,"") | ... Q11: =IF(Pressupostos!T$10<>"",Q5/12*Pressupostos!$D$125,"")
B12: =B6 -> Mercadoria 2 | C12: =IF(Pressupostos!F$10<>"",C6/12*Pressupostos!$D$125,"") -> 416.66667 | D12: =IF(Pressupostos!G$10<>"",D6/12*Pressupostos!$D$125,"") -> 625 | E12: =IF(Pressupostos!H$10<>"",E6/12*Pressupostos!$D$125,"") | F12: =IF(Pressupostos!I$10<>"",F6/12*Pressupostos!$D$125,"") | G12: =IF(Pressupostos!J$10<>"",G6/12*Pressupostos!$D$125,"") | H12: =IF(Pressupostos!K$10<>"",H6/12*Pressupostos!$D$125,"") | I12: =IF(Pressupostos!L$10<>"",I6/12*Pressupostos!$D$125,"") | J12: =IF(Pressupostos!M$10<>"",J6/12*Pressupostos!$D$125,"") | ... Q12: =IF(Pressupostos!T$10<>"",Q6/12*Pressupostos!$D$125,"")
B13: Stock final de matérias.primas:
B14: =+B8 -> Matérias-primas do Produto 1 | C14: =IF(Pressupostos!F$10<>"",C8/12*Pressupostos!$D$126,"") -> 416.66667 | D14: =IF(Pressupostos!G$10<>"",D8/12*Pressupostos!$D$126,"") -> 625 | E14: =IF(Pressupostos!H$10<>"",E8/12*Pressupostos!$D$126,"") | F14: =IF(Pressupostos!I$10<>"",F8/12*Pressupostos!$D$126,"") | G14: =IF(Pressupostos!J$10<>"",G8/12*Pressupostos!$D$126,"") | H14: =IF(Pressupostos!K$10<>"",H8/12*Pressupostos!$D$126,"") | I14: =IF(Pressupostos!L$10<>"",I8/12*Pressupostos!$D$126,"") | J14: =IF(Pressupostos!M$10<>"",J8/12*Pressupostos!$D$126,"") | ... Q14: =IF(Pressupostos!T$10<>"",Q8/12*Pressupostos!$D$126,"")
B15: =+B9 -> Matérias-primas do Produto 2 | C15: =IF(Pressupostos!F$10<>"",C9/12*Pressupostos!$D$126,"") -> 416.66667 | D15: =IF(Pressupostos!G$10<>"",D9/12*Pressupostos!$D$126,"") -> 625 | E15: =IF(Pressupostos!H$10<>"",E9/12*Pressupostos!$D$126,"") | F15: =IF(Pressupostos!I$10<>"",F9/12*Pressupostos!$D$126,"") | G15: =IF(Pressupostos!J$10<>"",G9/12*Pressupostos!$D$126,"") | H15: =IF(Pressupostos!K$10<>"",H9/12*Pressupostos!$D$126,"") | I15: =IF(Pressupostos!L$10<>"",I9/12*Pressupostos!$D$126,"") | J15: =IF(Pressupostos!M$10<>"",J9/12*Pressupostos!$D$126,"") | ... Q15: =IF(Pressupostos!T$10<>"",Q9/12*Pressupostos!$D$126,"")
B16: Stock inicial de mercadorias:
B17: =B11 -> Mercadoria 1 | D17: =IF(Pressupostos!G$10<>"",C11,"") -> 4166.6667 | E17: =IF(Pressupostos!H$10<>"",D11,"") | F17: =IF(Pressupostos!I$10<>"",E11,"") | G17: =IF(Pressupostos!J$10<>"",F11,"") | H17: =IF(Pressupostos!K$10<>"",G11,"") | I17: =IF(Pressupostos!L$10<>"",H11,"") | J17: =IF(Pressupostos!M$10<>"",I11,"") | K17: =IF(Pressupostos!N$10<>"",J11,"") | ... Q17: =IF(Pressupostos!T$10<>"",P11,"")
B18: =B12 -> Mercadoria 2 | D18: =IF(Pressupostos!G$10<>"",C12,"") -> 416.66667 | E18: =IF(Pressupostos!H$10<>"",D12,"") | F18: =IF(Pressupostos!I$10<>"",E12,"") | G18: =IF(Pressupostos!J$10<>"",F12,"") | H18: =IF(Pressupostos!K$10<>"",G12,"") | I18: =IF(Pressupostos!L$10<>"",H12,"") | J18: =IF(Pressupostos!M$10<>"",I12,"") | K18: =IF(Pressupostos!N$10<>"",J12,"") | ... Q18: =IF(Pressupostos!T$10<>"",P12,"")
B19: Stock inicial de matérias.primas:
B20: =+B14 -> Matérias-primas do Produto 1 | D20: =IF(Pressupostos!G$10<>"",C14,"") -> 416.66667 | E20: =IF(Pressupostos!H$10<>"",D14,"") | F20: =IF(Pressupostos!I$10<>"",E14,"") | G20: =IF(Pressupostos!J$10<>"",F14,"") | H20: =IF(Pressupostos!K$10<>"",G14,"") | I20: =IF(Pressupostos!L$10<>"",H14,"") | J20: =IF(Pressupostos!M$10<>"",I14,"") | K20: =IF(Pressupostos!N$10<>"",J14,"") | ... Q20: =IF(Pressupostos!T$10<>"",P14,"")
B21: =+B15 -> Matérias-primas do Produto 2 | D21: =IF(Pressupostos!G$10<>"",C15,"") -> 416.66667 | E21: =IF(Pressupostos!H$10<>"",D15,"") | F21: =IF(Pressupostos!I$10<>"",E15,"") | G21: =IF(Pressupostos!J$10<>"",F15,"") | H21: =IF(Pressupostos!K$10<>"",G15,"") | I21: =IF(Pressupostos!L$10<>"",H15,"") | J21: =IF(Pressupostos!M$10<>"",I15,"") | K21: =IF(Pressupostos!N$10<>"",J15,"") | ... Q21: =IF(Pressupostos!T$10<>"",P15,"")
B22: Compras de mercadorias:
B23: =B17 -> Mercadoria 1 | C23: =IF(Pressupostos!F$10<>"",C5+C11-C17,"") -> 104166.67 | D23: =IF(Pressupostos!G$10<>"",D5+D11-D17,"") -> 152083.33 | E23: =IF(Pressupostos!H$10<>"",E5+E11-E17,"") | F23: =IF(Pressupostos!I$10<>"",F5+F11-F17,"") | G23: =IF(Pressupostos!J$10<>"",G5+G11-G17,"") | H23: =IF(Pressupostos!K$10<>"",H5+H11-H17,"") | I23: =IF(Pressupostos!L$10<>"",I5+I11-I17,"") | J23: =IF(Pressupostos!M$10<>"",J5+J11-J17,"") | ... Q23: =IF(Pressupostos!T$10<>"",Q5+Q11-Q17,"")
B24: =B18 -> Mercadoria 2 | C24: =IF(Pressupostos!F$10<>"",C6+C12-C18,"") -> 10416.667 | D24: =IF(Pressupostos!G$10<>"",D6+D12-D18,"") -> 15208.333 | E24: =IF(Pressupostos!H$10<>"",E6+E12-E18,"") | F24: =IF(Pressupostos!I$10<>"",F6+F12-F18,"") | G24: =IF(Pressupostos!J$10<>"",G6+G12-G18,"") | H24: =IF(Pressupostos!K$10<>"",H6+H12-H18,"") | I24: =IF(Pressupostos!L$10<>"",I6+I12-I18,"") | J24: =IF(Pressupostos!M$10<>"",J6+J12-J18,"") | ... Q24: =IF(Pressupostos!T$10<>"",Q6+Q12-Q18,"")
B25: Compra de matérias-primas:
B26: =B20 -> Matérias-primas do Produto 1 | C26: =IF(Pressupostos!F$10<>"",C8+C14-C20,"") -> 10416.667 | D26: =IF(Pressupostos!G$10<>"",D8+D14-D20,"") -> 15208.333 | E26: =IF(Pressupostos!H$10<>"",E8+E14-E20,"") | F26: =IF(Pressupostos!I$10<>"",F8+F14-F20,"") | G26: =IF(Pressupostos!J$10<>"",G8+G14-G20,"") | H26: =IF(Pressupostos!K$10<>"",H8+H14-H20,"") | I26: =IF(Pressupostos!L$10<>"",I8+I14-I20,"") | J26: =IF(Pressupostos!M$10<>"",J8+J14-J20,"") | ... Q26: =IF(Pressupostos!T$10<>"",Q8+Q14-Q20,"")
B27: =B21 -> Matérias-primas do Produto 2 | C27: =IF(Pressupostos!F$10<>"",C9+C15-C21,"") -> 10416.667 | D27: =IF(Pressupostos!G$10<>"",D9+D15-D21,"") -> 15208.333 | E27: =IF(Pressupostos!H$10<>"",E9+E15-E21,"") | F27: =IF(Pressupostos!I$10<>"",F9+F15-F21,"") | G27: =IF(Pressupostos!J$10<>"",G9+G15-G21,"") | H27: =IF(Pressupostos!K$10<>"",H9+H15-H21,"") | I27: =IF(Pressupostos!L$10<>"",I9+I15-I21,"") | J27: =IF(Pressupostos!M$10<>"",J9+J15-J21,"") | ... Q27: =IF(Pressupostos!T$10<>"",Q9+Q15-Q21,"")
B30: VARIAÇÃO DOS INVENTÁRIOS DA PRODUÇÃO
B31: Descrição | C31: =IF(Pressupostos!F$10<>"",Pressupostos!F$10,"") -> 2024 | D31: =IF(Pressupostos!G$10<>"",Pressupostos!G$10,"") -> 2025 | E31: =IF(Pressupostos!H$10<>"",Pressupostos!H$10,"") | F31: =IF(Pressupostos!I$10<>"",Pressupostos!I$10,"") | G31: =IF(Pressupostos!J$10<>"",Pressupostos!J$10,"") | H31: =IF(Pressupostos!K$10<>"",Pressupostos!K$10,"") | I31: =IF(Pressupostos!L$10<>"",Pressupostos!L$10,"") | J31: =IF(Pressupostos!M$10<>"",Pressupostos!M$10,"") | ... Q31: =IF(Pressupostos!T$10<>"",Pressupostos!T$10,"")
B32: Variação dos inventários da produção
B33: Stock inicial de produtos acabados | D33: =IF(Pressupostos!G$10<>"",C34,"") -> 12500 | E33: =IF(Pressupostos!H$10<>"",D34,"") | F33: =IF(Pressupostos!I$10<>"",E34,"") | G33: =IF(Pressupostos!J$10<>"",F34,"") | H33: =IF(Pressupostos!K$10<>"",G34,"") | I33: =IF(Pressupostos!L$10<>"",H34,"") | J33: =IF(Pressupostos!M$10<>"",I34,"") | K33: =IF(Pressupostos!N$10<>"",J34,"") | ... Q33: =IF(Pressupostos!T$10<>"",P34,"")
B34: Stock final de produtos acabados | C34: =IF(Pressupostos!F$10<>"",DR!C4/12*Pressupostos!$D$127,"") -> 12500 | D34: =IF(Pressupostos!G$10<>"",DR!D4/12*Pressupostos!$D$127,"") -> 18750 | E34: =IF(Pressupostos!H$10<>"",DR!E4/12*Pressupostos!$D$127,"") | F34: =IF(Pressupostos!I$10<>"",DR!F4/12*Pressupostos!$D$127,"") | G34: =IF(Pressupostos!J$10<>"",DR!G4/12*Pressupostos!$D$127,"") | H34: =IF(Pressupostos!K$10<>"",DR!H4/12*Pressupostos!$D$127,"") | I34: =IF(Pressupostos!L$10<>"",DR!I4/12*Pressupostos!$D$127,"") | J34: =IF(Pressupostos!M$10<>"",DR!J4/12*Pressupostos!$D$127,"") | ... Q34: =IF(Pressupostos!T$10<>"",DR!Q4/12*Pressupostos!$D$127,"")
B35: Variação dos inventários da produção | C35: =IF(Pressupostos!F$10<>"",C34-C33,"") -> 12500 | D35: =IF(Pressupostos!G$10<>"",D34-D33,"") -> 6250 | E35: =IF(Pressupostos!H$10<>"",E34-E33,"") | F35: =IF(Pressupostos!I$10<>"",F34-F33,"") | G35: =IF(Pressupostos!J$10<>"",G34-G33,"") | H35: =IF(Pressupostos!K$10<>"",H34-H33,"") | I35: =IF(Pressupostos!L$10<>"",I34-I33,"") | J35: =IF(Pressupostos!M$10<>"",J34-J33,"") | ... Q35: =IF(Pressupostos!T$10<>"",Q34-Q33,"")

Sheet DR
B2: DEMONSTRAÇÃO DE RESULTADOS PREVISIONAIS
B3: Descrição | C3: =IF(Pressupostos!F10<>"",Pressupostos!F10,"") -> 2024 | D3: =IF(Pressupostos!G10<>"",Pressupostos!G10,"") -> 2025 | E3: =IF(Pressupostos!H10<>"",Pressupostos!H10,"") | F3: =IF(Pressupostos!I10<>"",Pressupostos!I10,"") | G3: =IF(Pressupostos!J10<>"",Pressupostos!J10,"") | H3: =IF(Pressupostos!K10<>"",Pressupostos!K10,"") | I3: =IF(Pressupostos!L10<>"",Pressupostos!L10,"") | J3: =IF(Pressupostos!M10<>"",Pressupostos!M10,"") | ... Q3: =IF(Pressupostos!T10<>"",Pressupostos!T10,"")
B4: Vendas e prestação de serviços | C4: =IF(Pressupostos!F$8=1,Pressupostos!F19*Pressupostos!F20+Pressupostos!F23*Pressupostos!F24+Pressupostos!F29*Pressupostos!F30+Pressupostos!F33*Pressupostos!F34+Pressupostos!F39*Pressupostos!F40+Pressupostos!F42*Pressupostos!F43,"") -> 300000 | D4: =IF(Pressupostos!G$8=1,Pressupostos!G19*Pressupostos!G20+Pressupostos!G23*Pressupostos!G24+Pressupostos!G29*Pressupostos!G30+Pressupostos!G33*Pressupostos!G34+Pressupostos!G39*Pressupostos!G40+Pressupostos!G42*Pressupostos!G43,"") -> 450000 | E4: =IF(Pressupostos!H$8=1,Pressupostos!H19*Pressupostos!H20+Pressupostos!H23*Pressupostos!H24+Pressupostos!H29*Pressupostos!H30+Pressupostos!H33*Pressupostos!H34+Pressupostos!H39*Pressupostos!H40+Pressupostos!H42*Pressupostos!H43,"") | F4: =IF(Pressupostos!I$8=1,Pressupostos!I19*Pressupostos!I20+Pressupostos!I23*Pressupostos!I24+Pressupostos!I29*Pressupostos!I30+Pressupostos!I33*Pressupostos!I34+Pressupostos!I39*Pressupostos!I40+Pressupostos!I42*Pressupostos!I43,"") | G4: =IF(Pressupostos!J$8=1,Pressupostos!J19*Pressupostos!J20+Pressupostos!J23*Pressupostos!J24+Pressupostos!J29*Pressupostos!J30+Pressupostos!J33*Pressupostos!J34+Pressupostos!J39*Pressupostos!J40+Pressupostos!J42*Pressupostos!J43,"") | H4: =IF(Pressupostos!K$8=1,Pressupostos!K19*Pressupostos!K20+Pressupostos!K23*Pressupostos!K24+Pressupostos!K29+Pressupostos!K30+Pressupostos!K33*Pressupostos!K34+Pressupostos!K39*Pressupostos!K40+Pressupostos!K42*Pressupostos!K43,"") | I4: =IF(Pressupostos!L$8=1,Pressupostos!L19*Pressupostos!L20+Pressupostos!L23*Pressupostos!L24+Pressupostos!L29+Pressupostos!L30+Pressupostos!L33*Pressupostos!L34+Pressupostos!L39*Pressupostos!L40+Pressupostos!L42*Pressupostos!L43,"") | J4: =IF(Pressupostos!M$8=1,Pressupostos!M19*Pressupostos!M20+Pressupostos!M23*Pressupostos!M24+Pressupostos!M29+Pressupostos!M30+Pressupostos!M33*Pressupostos!M34+Pressupostos!M39*Pressupostos!M40+Pressupostos!M42*Pressupostos!M43,"") | K4: =IF(Pressupostos!N$8=1,Pressupostos!N19*Pressupostos!N20+Pressupostos!N23*Pressupostos!N24+Pressupostos!N29+Pressupostos!N30+Pressupostos!N33*Pressupostos!N34+Pressupostos!N39*Pressupostos!N40+Pressupostos!N42*Pressupostos!N43,"") | L4: =IF(Pressupostos!O$8=1,Pressupostos!O19*Pressupostos!O20+Pressupostos!O23*Pressupostos!O24+Pressupostos!O29+Pressupostos!O30+Pressupostos!O33*Pressupostos!O34+Pressupostos!O39*Pressupostos!O40+Pressupostos!O42*Pressupostos!O43,"") | M4: =IF(Pressupostos!P$8=1,Pressupostos!P19*Pressupostos!P20+Pressupostos!P23*Pressupostos!P24+Pressupostos!P29+Pressupostos!P30+Pressupostos!P33*Pressupostos!P34+Pressupostos!P39*Pressupostos!P40+Pressupostos!P42*Pressupostos!P43,"") | N4: =IF(Pressupostos!Q$8=1,Pressupostos!Q19*Pressupostos!Q20+Pressupostos!Q23*Pressupostos!Q24+Pressupostos!Q29+Pressupostos!Q30+Pressupostos!Q33*Pressupostos!Q34+Pressupostos!Q39*Pressupostos!Q40+Pressupostos!Q42*Pressupostos!Q43,"") | O4: =IF(Pressupostos!R$8=1,Pressupostos!R19*Pressupostos!R20+Pressupostos!R23*Pressupostos!R24+Pressupostos!R29+Pressupostos!R30+Pressupostos!R33*Pressupostos!R34+Pressupostos!R39*Pressupostos!R40+Pressupostos!R42*Pressupostos!R43,"") | ... Q4: =IF(Pressupostos!T$8=1,Pressupostos!T19*Pressupostos!T20+Pressupostos!T23*Pressupostos!T24+Pressupostos!T29+Pressupostos!T30+Pressupostos!T33*Pressupostos!T34+Pressupostos!T39*Pressupostos!T40+Pressupostos!T42*Pressupostos!T43,"")
B5: Variação nos inventários da produção | C5: =Compras!C35 -> 12500 | D5: =Compras!D35 -> 6250 | E5: =Compras!E35 | F5: =Compras!F35 | G5: =Compras!G35 | H5: =Compras!H35 | I5: =Compras!I35 | J5: =Compras!J35 | ... Q5: =Compras!Q35
B6: Custo das mercadorias vendidas e matérias consumidas | C6: =IF(Pressupostos!F$8=1,-SUM(Compras!C5:C6)-SUM(Compras!C8:C9),"") -> -130000 | D6: =IF(Pressupostos!G$8=1,-SUM(Compras!D5:D6)-SUM(Compras!D8:D9),"") -> -195000 | E6: =IF(Pressupostos!H$8=1,-SUM(Compras!E5:E6)-SUM(Compras!E8:E9),"") | F6: =IF(Pressupostos!I$8=1,-SUM(Compras!F5:F6)-SUM(Compras!F8:F9),"") | G6: =IF(Pressupostos!J$8=1,-SUM(Compras!G5:G6)-SUM(Compras!G8:G9),"") | H6: =IF(Pressupostos!K$8=1,-SUM(Compras!H5:H6)-SUM(Compras!H8:H9),"") | I6: =IF(Pressupostos!L$8=1,-SUM(Compras!I5:I6)-SUM(Compras!I8:I9),"") | J6: =IF(Pressupostos!M$8=1,-SUM(Compras!J5:J6)-SUM(Compras!J8:J9),"") | ... Q6: =IF(Pressupostos!T$8=1,-SUM(Compras!Q5:Q6)-SUM(Compras!Q8:Q9),"")
B7: Fornecimentos e serviços externos | C7: =IF(Pressupostos!F$8=1,-E83-SUM(Pressupostos!F52:F57)-SUM(Pressupostos!F59:F62)-SUM(Pressupostos!F64:F66)-SUM(Pressupostos!F68:F70)-SUM(Pressupostos!F72:F78)-Pressupostos!F80,"") -> -18041.76 | D7: =IF(Pressupostos!G$8=1,-F83-SUM(Pressupostos!G52:G57)-SUM(Pressupostos!G59:G62)-SUM(Pressupostos!G64:G66)-SUM(Pressupostos!G68:G70)-SUM(Pressupostos!G72:G78)-Pressupostos!G80,"") -> -18402.595 | E7: =IF(Pressupostos!H$8=1,-G83-SUM(Pressupostos!H52:H57)-SUM(Pressupostos!H59:H62)-SUM(Pressupostos!H64:H66)-SUM(Pressupostos!H68:H70)-SUM(Pressupostos!H72:H78)-Pressupostos!H80,"") | F7: =IF(Pressupostos!I$8=1,-H83-SUM(Pressupostos!I52:I57)-SUM(Pressupostos!I59:I62)-SUM(Pressupostos!I64:I66)-SUM(Pressupostos!I68:I70)-SUM(Pressupostos!I72:I78)-Pressupostos!I80,"") | G7: =IF(Pressupostos!J$8=1,-I83-SUM(Pressupostos!J52:J57)-SUM(Pressupostos!J59:J62)-SUM(Pressupostos!J64:J66)-SUM(Pressupostos!J68:J70)-SUM(Pressupostos!J72:J78)-Pressupostos!J80,"") | H7: =IF(Pressupostos!K$8=1,-J83-SUM(Pressupostos!K52:K57)-SUM(Pressupostos!K59:K62)-SUM(Pressupostos!K64:K66)-SUM(Pressupostos!K68:K70)-SUM(Pressupostos!K72:K78)-Pressupostos!K80,"") | I7: =IF(Pressupostos!L$8=1,-K83-SUM(Pressupostos!L52:L57)-SUM(Pressupostos!L59:L62)-SUM(Pressupostos!L64:L66)-SUM(Pressupostos!L68:L70)-SUM(Pressupostos!L72:L78)-Pressupostos!L80,"") | J7: =IF(Pressupostos!M$8=1,-L83-SUM(Pressupostos!M52:M57)-SUM(Pressupostos!M59:M62)-SUM(Pressupostos!M64:M66)-SUM(Pressupostos!M68:M70)-SUM(Pressupostos!M72:M78)-Pressupostos!M80,"") | ... Q7: =IF(Pressupostos!T$8=1,-S83-SUM(Pressupostos!T52:T57)-SUM(Pressupostos!T59:T62)-SUM(Pressupostos!T64:T66)-SUM(Pressupostos!T68:T70)-SUM(Pressupostos!T72:T78)-Pressupostos!T80,"")
B8: Gastos com pessoal | C8: =IF(Pressupostos!F$8=1,-SUM(Pressupostos!F96:F98)*(1+Pressupostos!$D$118)-Pressupostos!F101-Pressupostos!F104,"") -> -63805.5 | D8: =IF(Pressupostos!G$8=1,-SUM(Pressupostos!G96:G98)*(1+Pressupostos!$D$118)-Pressupostos!G101-Pressupostos!G104,"") -> -65081.61 | E8: =IF(Pressupostos!H$8=1,-SUM(Pressupostos!H96:H98)*(1+Pressupostos!$D$118)-Pressupostos!H101-Pressupostos!H104,"") | F8: =IF(Pressupostos!I$8=1,-SUM(Pressupostos!I96:I98)*(1+Pressupostos!$D$118)-Pressupostos!I101-Pressupostos!I104,"") | G8: =IF(Pressupostos!J$8=1,-SUM(Pressupostos!J96:J98)*(1+Pressupostos!$D$118)-Pressupostos!J101-Pressupostos!J104,"") | H8: =IF(Pressupostos!K$8=1,-SUM(Pressupostos!K96:K98)*(1+Pressupostos!$D$118)-Pressupostos!K101-Pressupostos!K104,"") | I8: =IF(Pressupostos!L$8=1,-SUM(Pressupostos!L96:L98)*(1+Pressupostos!$D$118)-Pressupostos!L101-Pressupostos!L104,"") | J8: =IF(Pressupostos!M$8=1,-SUM(Pressupostos!M96:M98)*(1+Pressupostos!$D$118)-Pressupostos!M101-Pressupostos!M104,"") | ... Q8: =IF(Pressupostos!T$8=1,-SUM(Pressupostos!T96:T98)*(1+Pressupostos!$D$118)-Pressupostos!T101-Pressupostos!T104,"")
B9: Outros rendimentos e gastos | C9: =IF(Pressupostos!F$8=1,-Pressupostos!$D$109*DR!C4+Compras!C35,"") -> 9500 | D9: =IF(Pressupostos!G$8=1,-Pressupostos!$D$109*DR!D4+Compras!D35,"") -> 1750 | E9: =IF(Pressupostos!H$8=1,-Pressupostos!$D$109*DR!E4+Compras!E35,"") | F9: =IF(Pressupostos!I$8=1,-Pressupostos!$D$109*DR!F4+Compras!F35,"") | G9: =IF(Pressupostos!J$8=1,-Pressupostos!$D$109*DR!G4+Compras!G35,"") | H9: =IF(Pressupostos!K$8=1,-Pressupostos!$D$109*DR!H4+Compras!H35,"") | I9: =IF(Pressupostos!L$8=1,-Pressupostos!$D$109*DR!I4+Compras!I35,"") | J9: =IF(Pressupostos!M$8=1,-Pressupostos!$D$109*DR!J4+Compras!J35,"") | ... Q9: =IF(Pressupostos!T$8=1,-Pressupostos!$D$109*DR!Q4+Compras!Q35,"")
B10: EBITDA | C10: =IF(Pressupostos!F$8=1,SUM(C4:C9),"") -> 110152.74 | D10: =IF(Pressupostos!G$8=1,SUM(D4:D9),"") -> 179515.79 | E10: =IF(Pressupostos!H$8=1,SUM(E4:E9),"") | F10: =IF(Pressupostos!I$8=1,SUM(F4:F9),"") | G10: =IF(Pressupostos!J$8=1,SUM(G4:G9),"") | H10: =IF(Pressupostos!K$8=1,SUM(H4:H9),"") | I10: =IF(Pressupostos!L$8=1,SUM(I4:I9),"") | J10: =IF(Pressupostos!M$8=1,SUM(J4:J9),"") | ... Q10: =IF(Pressupostos!T$8=1,SUM(Q4:Q9),"")
B11: Gastos de depreciação e de amortização | C11: =IF(Pressupostos!F$8=1,-SUM(Pressupostos!F252:F253),"") -> -33700 | D11: =IF(Pressupostos!G$8=1,-SUM(Pressupostos!G252:G253),"") -> -38200 | E11: =IF(Pressupostos!H$8=1,-SUM(Pressupostos!H252:H253),"") | F11: =IF(Pressupostos!I$8=1,-SUM(Pressupostos!I252:I253),"") | G11: =IF(Pressupostos!J$8=1,-SUM(Pressupostos!J252:J253),"") | H11: =IF(Pressupostos!K$8=1,-SUM(Pressupostos!K252:K253),"") | I11: =IF(Pressupostos!L$8=1,-SUM(Pressupostos!L252:L253),"") | J11: =IF(Pressupostos!M$8=1,-SUM(Pressupostos!M252:M253),"") | ... Q11: =IF(Pressupostos!T$8=1,-SUM(Pressupostos!T252:T253),"")
B12: EBIT | C12: =IF(Pressupostos!F$8=1,C10+C11,"") -> 76452.74 | D12: =IF(Pressupostos!G$8=1,D10+D11,"") -> 141315.79 | E12: =IF(Pressupostos!H$8=1,E10+E11,"") | F12: =IF(Pressupostos!I$8=1,F10+F11,"") | G12: =IF(Pressupostos!J$8=1,G10+G11,"") | H12: =IF(Pressupostos!K$8=1,H10+H11,"") | I12: =IF(Pressupostos!L$8=1,I10+I11,"") | J12: =IF(Pressupostos!M$8=1,J10+J11,"") | ... Q12: =IF(Pressupostos!T$8=1,Q10+Q11,"")
B13: Gastos de financiamento | C13: =IF(Pressupostos!F$8=1,-Empréstimo!F201-Empréstimo!F202,"") -> -7896.2385 | D13: =IF(Pressupostos!G$8=1,-Empréstimo!G201-Empréstimo!G202,"") -> -2524.95 | E13: =IF(Pressupostos!H$8=1,-Empréstimo!H201-Empréstimo!H202,"") | F13: =IF(Pressupostos!I$8=1,-Empréstimo!I201-Empréstimo!I202,"") | G13: =IF(Pressupostos!J$8=1,-Empréstimo!J201-Empréstimo!J202,"") | H13: =IF(Pressupostos!K$8=1,-Empréstimo!K201-Empréstimo!K202,"") | I13: =IF(Pressupostos!L$8=1,-Empréstimo!L201-Empréstimo!L202,"") | J13: =IF(Pressupostos!M$8=1,-Empréstimo!M201-Empréstimo!M202,"") | ... Q13: =IF(Pressupostos!T$8=1,-Empréstimo!T201-Empréstimo!T202,"")
B14: Resultado antes impostos | C14: =IF(Pressupostos!F$8=1,C12+C13,"") -> 68556.502 | D14: =IF(Pressupostos!G$8=1,D12+D13,"") -> 138790.84 | E14: =IF(Pressupostos!H$8=1,E12+E13,"") | F14: =IF(Pressupostos!I$8=1,F12+F13,"") | G14: =IF(Pressupostos!J$8=1,G12+G13,"") | H14: =IF(Pressupostos!K$8=1,H12+H13,"") | I14: =IF(Pressupostos!L$8=1,I12+I13,"") | J14: =IF(Pressupostos!M$8=1,J12+J13,"") | ... Q14: =IF(Pressupostos!T$8=1,Q12+Q13,"")
A15: 1 | B15: Imposto sobre o rendimento do período | C15: =IF(Pressupostos!F$8=1,-C24,"") -> -15425.213 | D15: =IF(Pressupostos!G$8=1,-D24,"") -> -31227.94 | E15: =IF(Pressupostos!H$8=1,-E24,"") | F15: =IF(Pressupostos!I$8=1,-F24,"") | G15: =IF(Pressupostos!J$8=1,-G24,"") | H15: =IF(Pressupostos!K$8=1,-H24,"") | I15: =IF(Pressupostos!L$8=1,-I24,"") | J15: =IF(Pressupostos!M$8=1,-J24,"") | ... Q15: =IF(Pressupostos!T$8=1,-Q24,"")
B16: Resultado líquido do período | C16: =IF(Pressupostos!F$8=1,C14+C15,"") -> 53131.289 | D16: =IF(Pressupostos!G$8=1,D14+D15,"") -> 107562.9 | E16: =IF(Pressupostos!H$8=1,E14+E15,"") | F16: =IF(Pressupostos!I$8=1,F14+F15,"") | G16: =IF(Pressupostos!J$8=1,G14+G15,"") | H16: =IF(Pressupostos!K$8=1,H14+H15,"") | I16: =IF(Pressupostos!L$8=1,I14+I15,"") | J16: =IF(Pressupostos!M$8=1,J14+J15,"") | ... Q16: =IF(Pressupostos!T$8=1,Q14+Q15,"")
B18: Lucro Tributável | C18: =IF(Pressupostos!F$8=1,IF(C14<0,0,C14),"") -> 68556.502 | D18: =IF(Pressupostos!G$8=1,IF(D14<0,0,D14),"") -> 138790.84 | E18: =IF(Pressupostos!H$8=1,IF(E14<0,0,E14),"") | F18: =IF(Pressupostos!I$8=1,IF(F14<0,0,F14),"") | G18: =IF(Pressupostos!J$8=1,IF(G14<0,0,G14),"") | H18: =IF(Pressupostos!K$8=1,IF(H14<0,0,H14),"") | I18: =IF(Pressupostos!L$8=1,IF(I14<0,0,I14),"") | J18: =IF(Pressupostos!M$8=1,IF(J14<0,0,J14),"") | ... Q18: =IF(Pressupostos!T$8=1,IF(Q14<0,0,Q14),"")
B19: Prejuízos Fiscais | C19: =IF(Pressupostos!F$8=1,IF(C14>0,0,C14),"") -> 0 | D19: =IF(Pressupostos!G$8=1,IF(D14>0,0,D14),"") -> 0 | E19: =IF(Pressupostos!H$8=1,IF(E14>0,0,E14),"") | F19: =IF(Pressupostos!I$8=1,IF(F14>0,0,F14),"") | G19: =IF(Pressupostos!J$8=1,IF(G14>0,0,G14),"") | H19: =IF(Pressupostos!K$8=1,IF(H14>0,0,H14),"") | I19: =IF(Pressupostos!L$8=1,IF(I14>0,0,I14),"") | J19: =IF(Pressupostos!M$8=1,IF(J14>0,0,J14),"") | ... Q19: =IF(Pressupostos!T$8=1,IF(Q14>0,0,Q14),"")
A20: 1 | B20: Prejuízos Fiscais Acumulados Dedutíveis | C20: =IF(Pressupostos!F$8=1,IF(C19>0,0,C19),"") -> 0 | D20: =IF(Pressupostos!G$8=1,IF((D19+C20+C22)>0,0,D19+C20+C22),"") -> 0 | E20: =IF(Pressupostos!H$8=1,IF((E19+D20+D22)>0,0,E19+D20+D22),"") | F20: =IF(Pressupostos!I$8=1,IF((F19+E20+E22)>0,0,F19+E20+E22),"") | G20: =IF(Pressupostos!J$8=1,IF((G19+F20+F22)>0,0,G19+F20+F22),"") | H20: =IF(Pressupostos!K$8=1,IF((H19+G20+G22)>0,0,H19+G20+G22),"") | I20: =IF(Pressupostos!L$8=1,IF((I19+H20+H22)>0,0,I19+H20+H22),"") | J20: =IF(Pressupostos!M$8=1,IF((J19+I20+I22)>0,0,J19+I20+I22),"") | K20: =IF(Pressupostos!N$8=1,IF((K19+J20+J22)>0,0,K19+J20+J22),"") | ... Q20: =IF(Pressupostos!T$8=1,IF((Q19+P20+P22)>0,0,Q19+P20+P22),"")
B21: Limite de dedução dos Prejuízos Fiscais | C21: =IF(Pressupostos!F$8=1,IF(C18>0,C18,0),"") -> 68556.502 | D21: =IF(Pressupostos!G$8=1,IF(D18>0,D18,0),"") -> 138790.84 | E21: =IF(Pressupostos!H$8=1,IF(E18>0,E18,0),"") | F21: =IF(Pressupostos!I$8=1,IF(F18>0,F18,0),"") | G21: =IF(Pressupostos!J$8=1,IF(G18>0,G18,0),"") | H21: =IF(Pressupostos!K$8=1,IF(H18>0,H18,0),"") | I21: =IF(Pressupostos!L$8=1,IF(I18>0,I18,0),"") | J21: =IF(Pressupostos!M$8=1,IF(J18>0,J18,0),"") | ... Q21: =IF(Pressupostos!T$8=1,IF(Q18>0,Q18,0),"")
B22: Prejuízos fiscais dedutíveis do período | C22: =IF(Pressupostos!F$8=1,IF(C21>0,MIN(-C20,C18),0),"") -> 0 | D22: =IF(Pressupostos!G$8=1,IF(D21>0,MIN(-D20,D18),0),"") -> 0 | E22: =IF(Pressupostos!H$8=1,IF(E21>0,MIN(-E20,E18),0),"") | F22: =IF(Pressupostos!I$8=1,IF(F21>0,MIN(-F20,F18),0),"") | G22: =IF(Pressupostos!J$8=1,IF(G21>0,MIN(-G20,G18),0),"") | H22: =IF(Pressupostos!K$8=1,IF(H21>0,MIN(-H20,H18),0),"") | I22: =IF(Pressupostos!L$8=1,IF(I21>0,MIN(-I20,I18),0),"") | J22: =IF(Pressupostos!M$8=1,IF(J21>0,MIN(-J20,J18),0),"") | ... Q22: =IF(Pressupostos!T$8=1,IF(Q21>0,MIN(-Q20,Q18),0),"")
B23: Matéria Coletável | C23: =IF(Pressupostos!F$8=1,C18-C22,"") -> 68556.502 | D23: =IF(Pressupostos!G$8=1,D18-D22,"") -> 138790.84 | E23: =IF(Pressupostos!H$8=1,E18-E22,"") | F23: =IF(Pressupostos!I$8=1,F18-F22,"") | G23: =IF(Pressupostos!J$8=1,G18-G22,"") | H23: =IF(Pressupostos!K$8=1,H18-H22,"") | I23: =IF(Pressupostos!L$8=1,I18-I22,"") | J23: =IF(Pressupostos!M$8=1,J18-J22,"") | ... Q23: =IF(Pressupostos!T$8=1,Q18-Q22,"")
B24: IRC + Derrama | C24: =IF(Pressupostos!F$8=1,C23*Pressupostos!$D$114+C18*Pressupostos!$D$115,"") -> 15425.213 | D24: =IF(Pressupostos!G$8=1,D23*Pressupostos!$D$114+D18*Pressupostos!$D$115,"") -> 31227.94 | E24: =IF(Pressupostos!H$8=1,E23*Pressupostos!$D$114+E18*Pressupostos!$D$115,"") | F24: =IF(Pressupostos!I$8=1,F23*Pressupostos!$D$114+F18*Pressupostos!$D$115,"") | G24: =IF(Pressupostos!J$8=1,G23*Pressupostos!$D$114+G18*Pressupostos!$D$115,"") | H24: =IF(Pressupostos!K$8=1,H23*Pressupostos!$D$114+H18*Pressupostos!$D$115,"") | I24: =IF(Pressupostos!L$8=1,I23*Pressupostos!$D$114+I18*Pressupostos!$D$115,"") | J24: =IF(Pressupostos!M$8=1,J23*Pressupostos!$D$114+J18*Pressupostos!$D$115,"") | ... Q24: =IF(Pressupostos!T$8=1,Q23*Pressupostos!$D$114+Q18*Pressupostos!$D$115,"")
B25: Taxa efetiva de IRC | C25: =IF(Pressupostos!F$8=1,-C15/C14,"") -> 0.225 | D25: =IF(Pressupostos!G$8=1,-D15/D14,"") -> 0.225 | E25: =IF(Pressupostos!H$8=1,-E15/E14,"") | F25: =IF(Pressupostos!I$8=1,-F15/F14,"") | G25: =IF(Pressupostos!J$8=1,-G15/G14,"") | H25: =IF(Pressupostos!K$8=1,-H15/H14,"") | I25: =IF(Pressupostos!L$8=1,-I15/I14,"") | J25: =IF(Pressupostos!M$8=1,-J15/J14,"") | ... Q25: =IF(Pressupostos!T$8=1,-Q15/Q14,"")

Sheet Empréstimo
B3: EMPRÉSTIMO BANCÁRIO DE MÉDIO E LONGO PRAZO
B5: Montante: | E5: =Pressupostos!F263 -> 173600
B6: Taxa de juro anual nominal: | E6: =Pressupostos!E266 -> 0.05
B7: Sistema de amortização | E7: Amortização através de prestações mensais, constantes e postecipadas de capital e juros
B8: Prazo | E8: =Pressupostos!F5 -> 2 | F8: anos
B9: Custos de emissão (em % do empréstimo) | E9: =Pressupostos!E268 -> 0.005
B10: Taxa de imposto de selo sobre os juros | E10: =Pressupostos!E269 -> 0.04
B11: Prestação mensal | E11: =PMT(E6/12,E8*12,-E5,0,0) -> 7616.0733
B13: Mês | C13: Data | D13: Capital em dívida | E13: Juros | F13: Reembolso | G13: Prestação | H13: Outras despesas | I13: Economia fiscal | J13: Cash-flow | L13: Taxa de IRC EIetiva
B14: 0 | C14: =DATE(Pressupostos!F4-1,12,31) -> 45291 | D14: =E5 -> 173600 | H14: =E5*E9 -> 868 | J14: =IF(ISNUMBER(B15)=TRUE,D14-G14-H14+I14,"") -> 172732
B15: =IF(B14<>"",IF(B14+1<=E$8*12,B14+1,""),"") -> 1 | C15: =IF(ISNUMBER(B15)=TRUE,EOMONTH(C14,1),"") -> 45322 | D15: =IF(ISNUMBER(B15)=TRUE,D14-F14,"") -> 173600 | E15: =IF(ISNUMBER(B15)=TRUE,D15*$E$6/12,"") -> 723.33333 | F15: =IF(ISNUMBER(B15)=TRUE,G15-E15,"") -> 6892.7399 | G15: =IF(ISNUMBER(B15)=TRUE,$E$11,"") -> 7616.0733 | H15: =IF(ISNUMBER(B15)=TRUE,E15*$E$10,"") -> 28.933333 | I15: =IF(ISNUMBER(B15)=TRUE,(E15+H15+$H$14/($E$8*12))*L15,"") -> 177.3975 | J15: =IF(ISNUMBER(B15)=TRUE,-G15-H15+I15,"") -> -7467.6091 | L15: =IF(ISNUMBER(B15)=TRUE,DR!C$25,"") -> 0.225
B16: =IF(B15<>"",IF(B15+1<=E$8*12,B15+1,""),"") -> 2 | C16: =IF(ISNUMBER(B16)=TRUE,EOMONTH(C15,1),"") -> 45351 | D16: =IF(ISNUMBER(B16)=TRUE,D15-F15,"") -> 166707.26 | E16: =IF(ISNUMBER(B16)=TRUE,D16*$E$6/12,"") -> 694.61358 | F16: =IF(ISNUMBER(B16)=TRUE,G16-E16,"") -> 6921.4597 | G16: =IF(ISNUMBER(B16)=TRUE,$E$11,"") -> 7616.0733 | H16: =IF(ISNUMBER(B16)=TRUE,E16*$E$10,"") -> 27.784543 | I16: =IF(ISNUMBER(B16)=TRUE,(E16+H16+$H$14/($E$8*12))*L16,"") -> 170.67708 | J16: =IF(ISNUMBER(B16)=TRUE,-G16-H16+I16,"") -> -7473.1807 | L16: =IF(ISNUMBER(B16)=TRUE,DR!C$25,"") -> 0.225
B17: =IF(B16<>"",IF(B16+1<=E$8*12,B16+1,""),"") -> 3 | C17: =IF(ISNUMBER(B17)=TRUE,EOMONTH(C16,1),"") -> 45382 | D17: =IF(ISNUMBER(B17)=TRUE,D16-F16,"") -> 159785.8 | E17: =IF(ISNUMBER(B17)=TRUE,D17*$E$6/12,"") -> 665.77417 | F17: =IF(ISNUMBER(B17)=TRUE,G17-E17,"") -> 6950.2991 | G17: =IF(ISNUMBER(B17)=TRUE,$E$11,"") -> 7616.0733 | H17: =IF(ISNUMBER(B17)=TRUE,E17*$E$10,"") -> 26.630967 | I17: =IF(ISNUMBER(B17)=TRUE,(E17+H17+$H$14/($E$8*12))*L17,"") -> 163.92866 | J17: =IF(ISNUMBER(B17)=TRUE,-G17-H17+I17,"") -> -7478.7756 | L17: =IF(ISNUMBER(B17)=TRUE,DR!C$25,"") -> 0.225
B18: =IF(B17<>"",IF(B17+1<=E$8*12,B17+1,""),"") -> 4 | C18: =IF(ISNUMBER(B18)=TRUE,EOMONTH(C17,1),"") -> 45412 | D18: =IF(ISNUMBER(B18)=TRUE,D17-F17,"") -> 152835.5 | E18: =IF(ISNUMBER(B18)=TRUE,D18*$E$6/12,"") -> 636.81459 | F18: =IF(ISNUMBER(B18)=TRUE,G18-E18,"") -> 6979.2587 | G18: =IF(ISNUMBER(B18)=TRUE,$E$11,"") -> 7616.0733 | H18: =IF(ISNUMBER(B18)=TRUE,E18*$E$10,"") -> 25.472584 | I18: =IF(ISNUMBER(B18)=TRUE,(E18+H18+$H$14/($E$8*12))*L18,"") -> 157.15211 | J18: =IF(ISNUMBER(B18)=TRUE,-G18-H18+I18,"") -> -7484.3937 | L18: =IF(ISNUMBER(B18)=TRUE,DR!C$25,"") -> 0.225
B19: =IF(B18<>"",IF(B18+1<=E$8*12,B18+1,""),"") -> 5 | C19: =IF(ISNUMBER(B19)=TRUE,EOMONTH(C18,1),"") -> 45443 | D19: =IF(ISNUMBER(B19)=TRUE,D18-F18,"") -> 145856.24 | E19: =IF(ISNUMBER(B19)=TRUE,D19*$E$6/12,"") -> 607.73434 | F19: =IF(ISNUMBER(B19)=TRUE,G19-E19,"") -> 7008.3389 | G19: =IF(ISNUMBER(B19)=TRUE,$E$11,"") -> 7616.0733 | H19: =IF(ISNUMBER(B19)=TRUE,E19*$E$10,"") -> 24.309374 | I19: =IF(ISNUMBER(B19)=TRUE,(E19+H19+$H$14/($E$8*12))*L19,"") -> 150.34734 | J19: =IF(ISNUMBER(B19)=TRUE,-G19-H19+I19,"") -> -7490.0353 | L19: =IF(ISNUMBER(B19)=TRUE,DR!C$25,"") -> 0.225
B20: =IF(B19<>"",IF(B19+1<=E$8*12,B19+1,""),"") -> 6 | C20: =IF(ISNUMBER(B20)=TRUE,EOMONTH(C19,1),"") -> 45473 | D20: =IF(ISNUMBER(B20)=TRUE,D19-F19,"") -> 138847.9 | E20: =IF(ISNUMBER(B20)=TRUE,D20*$E$6/12,"") -> 578.53293 | F20: =IF(ISNUMBER(B20)=TRUE,G20-E20,"") -> 7037.5403 | G20: =IF(ISNUMBER(B20)=TRUE,$E$11,"") -> 7616.0733 | H20: =IF(ISNUMBER(B20)=TRUE,E20*$E$10,"") -> 23.141317 | I20: =IF(ISNUMBER(B20)=TRUE,(E20+H20+$H$14/($E$8*12))*L20,"") -> 143.51421 | J20: =IF(ISNUMBER(B20)=TRUE,-G20-H20+I20,"") -> -7495.7004 | L20: =IF(ISNUMBER(B20)=TRUE,DR!C$25,"") -> 0.225
B21: =IF(B20<>"",IF(B20+1<=E$8*12,B20+1,""),"") -> 7 | C21: =IF(ISNUMBER(B21)=TRUE,EOMONTH(C20,1),"") -> 45504 | D21: =IF(ISNUMBER(B21)=TRUE,D20-F20,"") -> 131810.36 | E21: =IF(ISNUMBER(B21)=TRUE,D21*$E$6/12,"") -> 549.20985 | F21: =IF(ISNUMBER(B21)=TRUE,G21-E21,"") -> 7066.8634 | G21: =IF(ISNUMBER(B21)=TRUE,$E$11,"") -> 7616.0733 | H21: =IF(ISNUMBER(B21)=TRUE,E21*$E$10,"") -> 21.968394 | I21: =IF(ISNUMBER(B21)=TRUE,(E21+H21+$H$14/($E$8*12))*L21,"") -> 136.6526 | J21: =IF(ISNUMBER(B21)=TRUE,-G21-H21+I21,"") -> -7501.389 | L21: =IF(ISNUMBER(B21)=TRUE,DR!C$25,"") -> 0.225
B22: =IF(B21<>"",IF(B21+1<=E$8*12,B21+1,""),"") -> 8 | C22: =IF(ISNUMBER(B22)=TRUE,EOMONTH(C21,1),"") -> 45535 | D22: =IF(ISNUMBER(B22)=TRUE,D21-F21,"") -> 124743.5 | E22: =IF(ISNUMBER(B22)=TRUE,D22*$E$6/12,"") -> 519.76458 | F22: =IF(ISNUMBER(B22)=TRUE,G22-E22,"") -> 7096.3087 | G22: =IF(ISNUMBER(B22)=TRUE,$E$11,"") -> 7616.0733 | H22: =IF(ISNUMBER(B22)=TRUE,E22*$E$10,"") -> 20.790583 | I22: =IF(ISNUMBER(B22)=TRUE,(E22+H22+$H$14/($E$8*12))*L22,"") -> 129.76241 | J22: =IF(ISNUMBER(B22)=TRUE,-G22-H22+I22,"") -> -7507.1014 | L22: =IF(ISNUMBER(B22)=TRUE,DR!C$25,"") -> 0.225
B23: =IF(B22<>"",IF(B22+1<=E$8*12,B22+1,""),"") -> 9 | C23: =IF(ISNUMBER(B23)=TRUE,EOMONTH(C22,1),"") -> 45565 | D23: =IF(ISNUMBER(B23)=TRUE,D22-F22,"") -> 117647.19 | E23: =IF(ISNUMBER(B23)=TRUE,D23*$E$6/12,"") -> 490.19663 | F23: =IF(ISNUMBER(B23)=TRUE,G23-E23,"") -> 7125.8766 | G23: =IF(ISNUMBER(B23)=TRUE,$E$11,"") -> 7616.0733 | H23: =IF(ISNUMBER(B23)=TRUE,E23*$E$10,"") -> 19.607865 | I23: =IF(ISNUMBER(B23)=TRUE,(E23+H23+$H$14/($E$8*12))*L23,"") -> 122.84351 | J23: =IF(ISNUMBER(B23)=TRUE,-G23-H23+I23,"") -> -7512.8376 | L23: =IF(ISNUMBER(B23)=TRUE,DR!C$25,"") -> 0.225
B24: =IF(B23<>"",IF(B23+1<=E$8*12,B23+1,""),"") -> 10 | C24: =IF(ISNUMBER(B24)=TRUE,EOMONTH(C23,1),"") -> 45596 | D24: =IF(ISNUMBER(B24)=TRUE,D23-F23,"") -> 110521.31 | E24: =IF(ISNUMBER(B24)=TRUE,D24*$E$6/12,"") -> 460.50548 | F24: =IF(ISNUMBER(B24)=TRUE,G24-E24,"") -> 7155.5678 | G24: =IF(ISNUMBER(B24)=TRUE,$E$11,"") -> 7616.0733 | H24: =IF(ISNUMBER(B24)=TRUE,E24*$E$10,"") -> 18.420219 | I24: =IF(ISNUMBER(B24)=TRUE,(E24+H24+$H$14/($E$8*12))*L24,"") -> 115.89578 | J24: =IF(ISNUMBER(B24)=TRUE,-G24-H24+I24,"") -> -7518.5977 | L24: =IF(ISNUMBER(B24)=TRUE,DR!C$25,"") -> 0.225
B25: =IF(B24<>"",IF(B24+1<=E$8*12,B24+1,""),"") -> 11 | C25: =IF(ISNUMBER(B25)=TRUE,EOMONTH(C24,1),"") -> 45626 | D25: =IF(ISNUMBER(B25)=TRUE,D24-F24,"") -> 103365.75 | E25: =IF(ISNUMBER(B25)=TRUE,D25*$E$6/12,"") -> 430.69061 | F25: =IF(ISNUMBER(B25)=TRUE,G25-E25,"") -> 7185.3826 | G25: =IF(ISNUMBER(B25)=TRUE,$E$11,"") -> 7616.0733 | H25: =IF(ISNUMBER(B25)=TRUE,E25*$E$10,"") -> 17.227624 | I25: =IF(ISNUMBER(B25)=TRUE,(E25+H25+$H$14/($E$8*12))*L25,"") -> 108.9191 | J25: =IF(ISNUMBER(B25)=TRUE,-G25-H25+I25,"") -> -7524.3818 | L25: =IF(ISNUMBER(B25)=TRUE,DR!C$25,"") -> 0.225
B26: =IF(B25<>"",IF(B25+1<=E$8*12,B25+1,""),"") -> 12 | C26: =IF(ISNUMBER(B26)=TRUE,EOMONTH(C25,1),"") -> 45657 | D26: =IF(ISNUMBER(B26)=TRUE,D25-F25,"") -> 96180.364 | E26: =IF(ISNUMBER(B26)=TRUE,D26*$E$6/12,"") -> 400.75152 | F26: =IF(ISNUMBER(B26)=TRUE,G26-E26,"") -> 7215.3217 | G26: =IF(ISNUMBER(B26)=TRUE,$E$11,"") -> 7616.0733 | H26: =IF(ISNUMBER(B26)=TRUE,E26*$E$10,"") -> 16.030061 | I26: =IF(ISNUMBER(B26)=TRUE,(E26+H26+$H$14/($E$8*12))*L26,"") -> 101.91336 | J26: =IF(ISNUMBER(B26)=TRUE,-G26-H26+I26,"") -> -7530.19 | L26: =IF(ISNUMBER(B26)=TRUE,DR!C$25,"") -> 0.225
B27: =IF(B26<>"",IF(B26+1<=E$8*12,B26+1,""),"") -> 13 | C27: =IF(ISNUMBER(B27)=TRUE,EOMONTH(C26,1),"") -> 45688 | D27: =IF(ISNUMBER(B27)=TRUE,D26-F26,"") -> 88965.043 | E27: =IF(ISNUMBER(B27)=TRUE,D27*$E$6/12,"") -> 370.68768 | F27: =IF(ISNUMBER(B27)=TRUE,G27-E27,"") -> 7245.3856 | G27: =IF(ISNUMBER(B27)=TRUE,$E$11,"") -> 7616.0733 | H27: =IF(ISNUMBER(B27)=TRUE,E27*$E$10,"") -> 14.827507 | I27: =IF(ISNUMBER(B27)=TRUE,(E27+H27+$H$14/($E$8*12))*L27,"") -> 94.878416 | J27: =IF(ISNUMBER(B27)=TRUE,-G27-H27+I27,"") -> -7536.0223 | L27: =IF(ISNUMBER(B27)=TRUE,DR!D$25,"") -> 0.225
B28: =IF(B27<>"",IF(B27+1<=E$8*12,B27+1,""),"") -> 14 | C28: =IF(ISNUMBER(B28)=TRUE,EOMONTH(C27,1),"") -> 45716 | D28: =IF(ISNUMBER(B28)=TRUE,D27-F27,"") -> 81719.657 | E28: =IF(ISNUMBER(B28)=TRUE,D28*$E$6/12,"") -> 340.49857 | F28: =IF(ISNUMBER(B28)=TRUE,G28-E28,"") -> 7275.5747 | G28: =IF(ISNUMBER(B28)=TRUE,$E$11,"") -> 7616.0733 | H28: =IF(ISNUMBER(B28)=TRUE,E28*$E$10,"") -> 13.619943 | I28: =IF(ISNUMBER(B28)=TRUE,(E28+H28+$H$14/($E$8*12))*L28,"") -> 87.814166 | J28: =IF(ISNUMBER(B28)=TRUE,-G28-H28+I28,"") -> -7541.879 | L28: =IF(ISNUMBER(B28)=TRUE,DR!D$25,"") -> 0.225
B29: =IF(B28<>"",IF(B28+1<=E$8*12,B28+1,""),"") -> 15 | C29: =IF(ISNUMBER(B29)=TRUE,EOMONTH(C28,1),"") -> 45747 | D29: =IF(ISNUMBER(B29)=TRUE,D28-F28,"") -> 74444.082 | E29: =IF(ISNUMBER(B29)=TRUE,D29*$E$6/12,"") -> 310.18368 | F29: =IF(ISNUMBER(B29)=TRUE,G29-E29,"") -> 7305.8896 | G29: =IF(ISNUMBER(B29)=TRUE,$E$11,"") -> 7616.0733 | H29: =IF(ISNUMBER(B29)=TRUE,E29*$E$10,"") -> 12.407347 | I29: =IF(ISNUMBER(B29)=TRUE,(E29+H29+$H$14/($E$8*12))*L29,"") -> 80.72048 | J29: =IF(ISNUMBER(B29)=TRUE,-G29-H29+I29,"") -> -7547.7601 | L29: =IF(ISNUMBER(B29)=TRUE,DR!D$25,"") -> 0.225
B30: =IF(B29<>"",IF(B29+1<=E$8*12,B29+1,""),"") -> 16 | C30: =IF(ISNUMBER(B30)=TRUE,EOMONTH(C29,1),"") -> 45777 | D30: =IF(ISNUMBER(B30)=TRUE,D29-F29,"") -> 67138.193 | E30: =IF(ISNUMBER(B30)=TRUE,D30*$E$6/12,"") -> 279.74247 | F30: =IF(ISNUMBER(B30)=TRUE,G30-E30,"") -> 7336.3308 | G30: =IF(ISNUMBER(B30)=TRUE,$E$11,"") -> 7616.0733 | H30: =IF(ISNUMBER(B30)=TRUE,E30*$E$10,"") -> 11.189699 | I30: =IF(ISNUMBER(B30)=TRUE,(E30+H30+$H$14/($E$8*12))*L30,"") -> 73.597238 | J30: =IF(ISNUMBER(B30)=TRUE,-G30-H30+I30,"") -> -7553.6657 | L30: =IF(ISNUMBER(B30)=TRUE,DR!D$25,"") -> 0.225
B31: =IF(B30<>"",IF(B30+1<=E$8*12,B30+1,""),"") -> 17 | C31: =IF(ISNUMBER(B31)=TRUE,EOMONTH(C30,1),"") -> 45808 | D31: =IF(ISNUMBER(B31)=TRUE,D30-F30,"") -> 59801.862 | E31: =IF(ISNUMBER(B31)=TRUE,D31*$E$6/12,"") -> 249.17442 | F31: =IF(ISNUMBER(B31)=TRUE,G31-E31,"") -> 7366.8988 | G31: =IF(ISNUMBER(B31)=TRUE,$E$11,"") -> 7616.0733 | H31: =IF(ISNUMBER(B31)=TRUE,E31*$E$10,"") -> 9.966977 | I31: =IF(ISNUMBER(B31)=TRUE,(E31+H31+$H$14/($E$8*12))*L31,"") -> 66.444315 | J31: =IF(ISNUMBER(B31)=TRUE,-G31-H31+I31,"") -> -7559.5959 | L31: =IF(ISNUMBER(B31)=TRUE,DR!D$25,"") -> 0.225
B32: =IF(B31<>"",IF(B31+1<=E$8*12,B31+1,""),"") -> 18 | C32: =IF(ISNUMBER(B32)=TRUE,EOMONTH(C31,1),"") -> 45838 | D32: =IF(ISNUMBER(B32)=TRUE,D31-F31,"") -> 52434.963 | E32: =IF(ISNUMBER(B32)=TRUE,D32*$E$6/12,"") -> 218.47901 | F32: =IF(ISNUMBER(B32)=TRUE,G32-E32,"") -> 7397.5942 | G32: =IF(ISNUMBER(B32)=TRUE,$E$11,"") -> 7616.0733 | H32: =IF(ISNUMBER(B32)=TRUE,E32*$E$10,"") -> 8.7391605 | I32: =IF(ISNUMBER(B32)=TRUE,(E32+H32+$H$14/($E$8*12))*L32,"") -> 59.261589 | J32: =IF(ISNUMBER(B32)=TRUE,-G32-H32+I32,"") -> -7565.5508 | L32: =IF(ISNUMBER(B32)=TRUE,DR!D$25,"") -> 0.225
B33: =IF(B32<>"",IF(B32+1<=E$8*12,B32+1,""),"") -> 19 | C33: =IF(ISNUMBER(B33)=TRUE,EOMONTH(C32,1),"") -> 45869 | D33: =IF(ISNUMBER(B33)=TRUE,D32-F32,"") -> 45037.369 | E33: =IF(ISNUMBER(B33)=TRUE,D33*$E$6/12,"") -> 187.6557 | F33: =IF(ISNUMBER(B33)=TRUE,G33-E33,"") -> 7428.4176 | G33: =IF(ISNUMBER(B33)=TRUE,$E$11,"") -> 7616.0733 | H33: =IF(ISNUMBER(B33)=TRUE,E33*$E$10,"") -> 7.5062281 | I33: =IF(ISNUMBER(B33)=TRUE,(E33+H33+$H$14/($E$8*12))*L33,"") -> 52.048935 | J33: =IF(ISNUMBER(B33)=TRUE,-G33-H33+I33,"") -> -7571.5306 | L33: =IF(ISNUMBER(B33)=TRUE,DR!D$25,"") -> 0.225
B34: =IF(B33<>"",IF(B33+1<=E$8*12,B33+1,""),"") -> 20 | C34: =IF(ISNUMBER(B34)=TRUE,EOMONTH(C33,1),"") -> 45900 | D34: =IF(ISNUMBER(B34)=TRUE,D33-F33,"") -> 37608.951 | E34: =IF(ISNUMBER(B34)=TRUE,D34*$E$6/12,"") -> 156.70396 | F34: =IF(ISNUMBER(B34)=TRUE,G34-E34,"") -> 7459.3693 | G34: =IF(ISNUMBER(B34)=TRUE,$E$11,"") -> 7616.0733 | H34: =IF(ISNUMBER(B34)=TRUE,E34*$E$10,"") -> 6.2681585 | I34: =IF(ISNUMBER(B34)=TRUE,(E34+H34+$H$14/($E$8*12))*L34,"") -> 44.806227 | J34: =IF(ISNUMBER(B34)=TRUE,-G34-H34+I34,"") -> -7577.5352 | L34: =IF(ISNUMBER(B34)=TRUE,DR!D$25,"") -> 0.225
B35: =IF(B34<>"",IF(B34+1<=E$8*12,B34+1,""),"") -> 21 | C35: =IF(ISNUMBER(B35)=TRUE,EOMONTH(C34,1),"") -> 45930 | D35: =IF(ISNUMBER(B35)=TRUE,D34-F34,"") -> 30149.582 | E35: =IF(ISNUMBER(B35)=TRUE,D35*$E$6/12,"") -> 125.62326 | F35: =IF(ISNUMBER(B35)=TRUE,G35-E35,"") -> 7490.45 | G35: =IF(ISNUMBER(B35)=TRUE,$E$11,"") -> 7616.0733 | H35: =IF(ISNUMBER(B35)=TRUE,E35*$E$10,"") -> 5.0249303 | I35: =IF(ISNUMBER(B35)=TRUE,(E35+H35+$H$14/($E$8*12))*L35,"") -> 37.533342 | J35: =IF(ISNUMBER(B35)=TRUE,-G35-H35+I35,"") -> -7583.5648 | L35: =IF(ISNUMBER(B35)=TRUE,DR!D$25,"") -> 0.225
B36: =IF(B35<>"",IF(B35+1<=E$8*12,B35+1,""),"") -> 22 | C36: =IF(ISNUMBER(B36)=TRUE,EOMONTH(C35,1),"") -> 45961 | D36: =IF(ISNUMBER(B36)=TRUE,D35-F35,"") -> 22659.132 | E36: =IF(ISNUMBER(B36)=TRUE,D36*$E$6/12,"") -> 94.41305 | F36: =IF(ISNUMBER(B36)=TRUE,G36-E36,"") -> 7521.6602 | G36: =IF(ISNUMBER(B36)=TRUE,$E$11,"") -> 7616.0733 | H36: =IF(ISNUMBER(B36)=TRUE,E36*$E$10,"") -> 3.776522 | I36: =IF(ISNUMBER(B36)=TRUE,(E36+H36+$H$14/($E$8*12))*L36,"") -> 30.230154 | J36: =IF(ISNUMBER(B36)=TRUE,-G36-H36+I36,"") -> -7589.6196 | L36: =IF(ISNUMBER(B36)=TRUE,DR!D$25,"") -> 0.225
B37: =IF(B36<>"",IF(B36+1<=E$8*12,B36+1,""),"") -> 23 | C37: =IF(ISNUMBER(B37)=TRUE,EOMONTH(C36,1),"") -> 45991 | D37: =IF(ISNUMBER(B37)=TRUE,D36-F36,"") -> 15137.472 | E37: =IF(ISNUMBER(B37)=TRUE,D37*$E$6/12,"") -> 63.072799 | F37: =IF(ISNUMBER(B37)=TRUE,G37-E37,"") -> 7553.0005 | G37: =IF(ISNUMBER(B37)=TRUE,$E$11,"") -> 7616.0733 | H37: =IF(ISNUMBER(B37)=TRUE,E37*$E$10,"") -> 2.522912 | I37: =IF(ISNUMBER(B37)=TRUE,(E37+H37+$H$14/($E$8*12))*L37,"") -> 22.896535 | J37: =IF(ISNUMBER(B37)=TRUE,-G37-H37+I37,"") -> -7595.6996 | L37: =IF(ISNUMBER(B37)=TRUE,DR!D$25,"") -> 0.225
B38: =IF(B37<>"",IF(B37+1<=E$8*12,B37+1,""),"") -> 24 | C38: =IF(ISNUMBER(B38)=TRUE,EOMONTH(C37,1),"") -> 46022 | D38: =IF(ISNUMBER(B38)=TRUE,D37-F37,"") -> 7584.4713 | E38: =IF(ISNUMBER(B38)=TRUE,D38*$E$6/12,"") -> 31.601964 | F38: =IF(ISNUMBER(B38)=TRUE,G38-E38,"") -> 7584.4713 | G38: =IF(ISNUMBER(B38)=TRUE,$E$11,"") -> 7616.0733 | H38: =IF(ISNUMBER(B38)=TRUE,E38*$E$10,"") -> 1.2640785 | I38: =IF(ISNUMBER(B38)=TRUE,(E38+H38+$H$14/($E$8*12))*L38,"") -> 15.53236 | J38: =IF(ISNUMBER(B38)=TRUE,-G38-H38+I38,"") -> -7601.805 | L38: =IF(ISNUMBER(B38)=TRUE,DR!D$25,"") -> 0.225
B39: =IF(B38<>"",IF(B38+1<=E$8*12,B38+1,""),"") | C39: =IF(ISNUMBER(B39)=TRUE,EOMONTH(C38,1),"") | D39: =IF(ISNUMBER(B39)=TRUE,D38-F38,"") | E39: =IF(ISNUMBER(B39)=TRUE,D39*$E$6/12,"") | F39: =IF(ISNUMBER(B39)=TRUE,G39-E39,"") | G39: =IF(ISNUMBER(B39)=TRUE,$E$11,"") | H39: =IF(ISNUMBER(B39)=TRUE,E39*$E$10,"") | I39: =IF(ISNUMBER(B39)=TRUE,(E39+H39+$H$14/($E$8*12))*L39,"") | J39: =IF(ISNUMBER(B39)=TRUE,-G39-H39+I39,"") | L39: =IF(ISNUMBER(B39)=TRUE,DR!E$25,"")
B40: =IF(B39<>"",IF(B39+1<=E$8*12,B39+1,""),"") | C40: =IF(ISNUMBER(B40)=TRUE,EOMONTH(C39,1),"") | D40: =IF(ISNUMBER(B40)=TRUE,D39-F39,"") | E40: =IF(ISNUMBER(B40)=TRUE,D40*$E$6/12,"") | F40: =IF(ISNUMBER(B40)=TRUE,G40-E40,"") | G40: =IF(ISNUMBER(B40)=TRUE,$E$11,"") | H40: =IF(ISNUMBER(B40)=TRUE,E40*$E$10,"") | I40: =IF(ISNUMBER(B40)=TRUE,(E40+H40+$H$14/($E$8*12))*L40,"") | J40: =IF(ISNUMBER(B40)=TRUE,-G40-H40+I40,"") | L40: =IF(ISNUMBER(B40)=TRUE,DR!E$25,"")
B41: =IF(B40<>"",IF(B40+1<=E$8*12,B40+1,""),"") | C41: =IF(ISNUMBER(B41)=TRUE,EOMONTH(C40,1),"") | D41: =IF(ISNUMBER(B41)=TRUE,D40-F40,"") | E41: =IF(ISNUMBER(B41)=TRUE,D41*$E$6/12,"") | F41: =IF(ISNUMBER(B41)=TRUE,G41-E41,"") | G41: =IF(ISNUMBER(B41)=TRUE,$E$11,"") | H41: =IF(ISNUMBER(B41)=TRUE,E41*$E$10,"") | I41: =IF(ISNUMBER(B41)=TRUE,(E41+H41+$H$14/($E$8*12))*L41,"") | J41: =IF(ISNUMBER(B41)=TRUE,-G41-H41+I41,"") | L41: =IF(ISNUMBER(B41)=TRUE,DR!E$25,"")
B42: =IF(B41<>"",IF(B41+1<=E$8*12,B41+1,""),"") | C42: =IF(ISNUMBER(B42)=TRUE,EOMONTH(C41,1),"") | D42: =IF(ISNUMBER(B42)=TRUE,D41-F41,"") | E42: =IF(ISNUMBER(B42)=TRUE,D42*$E$6/12,"") | F42: =IF(ISNUMBER(B42)=TRUE,G42-E42,"") | G42: =IF(ISNUMBER(B42)=TRUE,$E$11,"") | H42: =IF(ISNUMBER(B42)=TRUE,E42*$E$10,"") | I42: =IF(ISNUMBER(B42)=TRUE,(E42+H42+$H$14/($E$8*12))*L42,"") | J42: =IF(ISNUMBER(B42)=TRUE,-G42-H42+I42,"") | L42: =IF(ISNUMBER(B42)=TRUE,DR!E$25,"")
B43: =IF(B42<>"",IF(B42+1<=E$8*12,B42+1,""),"") | C43: =IF(ISNUMBER(B43)=TRUE,EOMONTH(C42,1),"") | D43: =IF(ISNUMBER(B43)=TRUE,D42-F42,"") | E43: =IF(ISNUMBER(B43)=TRUE,D43*$E$6/12,"") | F43: =IF(ISNUMBER(B43)=TRUE,G43-E43,"") | G43: =IF(ISNUMBER(B43)=TRUE,$E$11,"") | H43: =IF(ISNUMBER(B43)=TRUE,E43*$E$10,"") | I43: =IF(ISNUMBER(B43)=TRUE,(E43+H43+$H$14/($E$8*12))*L43,"") | J43: =IF(ISNUMBER(B43)=TRUE,-G43-H43+I43,"") | L43: =IF(ISNUMBER(B43)=TRUE,DR!E$25,"")
B44: =IF(B43<>"",IF(B43+1<=E$8*12,B43+1,""),"") | C44: =IF(ISNUMBER(B44)=TRUE,EOMONTH(C43,1),"") | D44: =IF(ISNUMBER(B44)=TRUE,D43-F43,"") | E44: =IF(ISNUMBER(B44)=TRUE,D44*$E$6/12,"") | F44: =IF(ISNUMBER(B44)=TRUE,G44-E44,"") | G44: =IF(ISNUMBER(B44)=TRUE,$E$11,"") | H44: =IF(ISNUMBER(B44)=TRUE,E44*$E$10,"") | I44: =IF(ISNUMBER(B44)=TRUE,(E44+H44+$H$14/($E$8*12))*L44,"") | J44: =IF(ISNUMBER(B44)=TRUE,-G44-H44+I44,"") | L44: =IF(ISNUMBER(B44)=TRUE,DR!E$25,"")
B45: =IF(B44<>"",IF(B44+1<=E$8*12,B44+1,""),"") | C45: =IF(ISNUMBER(B45)=TRUE,EOMONTH(C44,1),"") | D45: =IF(ISNUMBER(B45)=TRUE,D44-F44,"") | E45: =IF(ISNUMBER(B45)=TRUE,D45*$E$6/12,"") | F45: =IF(ISNUMBER(B45)=TRUE,G45-E45,"") | G45: =IF(ISNUMBER(B45)=TRUE,$E$11,"") | H45: =IF(ISNUMBER(B45)=TRUE,E45*$E$10,"") | I45: =IF(ISNUMBER(B45)=TRUE,(E45+H45+$H$14/($E$8*12))*L45,"") | J45: =IF(ISNUMBER(B45)=TRUE,-G45-H45+I45,"") | L45: =IF(ISNUMBER(B45)=TRUE,DR!E$25,"")
B46: =IF(B45<>"",IF(B45+1<=E$8*12,B45+1,""),"") | C46: =IF(ISNUMBER(B46)=TRUE,EOMONTH(C45,1),"") | D46: =IF(ISNUMBER(B46)=TRUE,D45-F45,"") | E46: =IF(ISNUMBER(B46)=TRUE,D46*$E$6/12,"") | F46: =IF(ISNUMBER(B46)=TRUE,G46-E46,"") | G46: =IF(ISNUMBER(B46)=TRUE,$E$11,"") | H46: =IF(ISNUMBER(B46)=TRUE,E46*$E$10,"") | I46: =IF(ISNUMBER(B46)=TRUE,(E46+H46+$H$14/($E$8*12))*L46,"") | J46: =IF(ISNUMBER(B46)=TRUE,-G46-H46+I46,"") | L46: =IF(ISNUMBER(B46)=TRUE,DR!E$25,"")
B47: =IF(B46<>"",IF(B46+1<=E$8*12,B46+1,""),"") | C47: =IF(ISNUMBER(B47)=TRUE,EOMONTH(C46,1),"") | D47: =IF(ISNUMBER(B47)=TRUE,D46-F46,"") | E47: =IF(ISNUMBER(B47)=TRUE,D47*$E$6/12,"") | F47: =IF(ISNUMBER(B47)=TRUE,G47-E47,"") | G47: =IF(ISNUMBER(B47)=TRUE,$E$11,"") | H47: =IF(ISNUMBER(B47)=TRUE,E47*$E$10,"") | I47: =IF(ISNUMBER(B47)=TRUE,(E47+H47+$H$14/($E$8*12))*L47,"") | J47: =IF(ISNUMBER(B47)=TRUE,-G47-H47+I47,"") | L47: =IF(ISNUMBER(B47)=TRUE,DR!E$25,"")
B48: =IF(B47<>"",IF(B47+1<=E$8*12,B47+1,""),"") | C48: =IF(ISNUMBER(B48)=TRUE,EOMONTH(C47,1),"") | D48: =IF(ISNUMBER(B48)=TRUE,D47-F47,"") | E48: =IF(ISNUMBER(B48)=TRUE,D48*$E$6/12,"") | F48: =IF(ISNUMBER(B48)=TRUE,G48-E48,"") | G48: =IF(ISNUMBER(B48)=TRUE,$E$11,"") | H48: =IF(ISNUMBER(B48)=TRUE,E48*$E$10,"") | I48: =IF(ISNUMBER(B48)=TRUE,(E48+H48+$H$14/($E$8*12))*L48,"") | J48: =IF(ISNUMBER(B48)=TRUE,-G48-H48+I48,"") | L48: =IF(ISNUMBER(B48)=TRUE,DR!E$25,"")
B49: =IF(B48<>"",IF(B48+1<=E$8*12,B48+1,""),"") | C49: =IF(ISNUMBER(B49)=TRUE,EOMONTH(C48,1),"") | D49: =IF(ISNUMBER(B49)=TRUE,D48-F48,"") | E49: =IF(ISNUMBER(B49)=TRUE,D49*$E$6/12,"") | F49: =IF(ISNUMBER(B49)=TRUE,G49-E49,"") | G49: =IF(ISNUMBER(B49)=TRUE,$E$11,"") | H49: =IF(ISNUMBER(B49)=TRUE,E49*$E$10,"") | I49: =IF(ISNUMBER(B49)=TRUE,(E49+H49+$H$14/($E$8*12))*L49,"") | J49: =IF(ISNUMBER(B49)=TRUE,-G49-H49+I49,"") | L49: =IF(ISNUMBER(B49)=TRUE,DR!E$25,"")
B50: =IF(B49<>"",IF(B49+1<=E$8*12,B49+1,""),"") | C50: =IF(ISNUMBER(B50)=TRUE,EOMONTH(C49,1),"") | D50: =IF(ISNUMBER(B50)=TRUE,D49-F49,"") | E50: =IF(ISNUMBER(B50)=TRUE,D50*$E$6/12,"") | F50: =IF(ISNUMBER(B50)=TRUE,G50-E50,"") | G50: =IF(ISNUMBER(B50)=TRUE,$E$11,"") | H50: =IF(ISNUMBER(B50)=TRUE,E50*$E$10,"") | I50: =IF(ISNUMBER(B50)=TRUE,(E50+H50+$H$14/($E$8*12))*L50,"") | J50: =IF(ISNUMBER(B50)=TRUE,-G50-H50+I50,"") | L50: =IF(ISNUMBER(B50)=TRUE,DR!E$25,"")
B51: =IF(B50<>"",IF(B50+1<=E$8*12,B50+1,""),"") | C51: =IF(ISNUMBER(B51)=TRUE,EOMONTH(C50,1),"") | D51: =IF(ISNUMBER(B51)=TRUE,D50-F50,"") | E51: =IF(ISNUMBER(B51)=TRUE,D51*$E$6/12,"") | F51: =IF(ISNUMBER(B51)=TRUE,G51-E51,"") | G51: =IF(ISNUMBER(B51)=TRUE,$E$11,"") | H51: =IF(ISNUMBER(B51)=TRUE,E51*$E$10,"") | I51: =IF(ISNUMBER(B51)=TRUE,(E51+H51+$H$14/($E$8*12))*L51,"") | J51: =IF(ISNUMBER(B51)=TRUE,-G51-H51+I51,"") | L51: =IF(ISNUMBER(B51)=TRUE,DR!F$25,"")
B52: =IF(B51<>"",IF(B51+1<=E$8*12,B51+1,""),"") | C52: =IF(ISNUMBER(B52)=TRUE,EOMONTH(C51,1),"") | D52: =IF(ISNUMBER(B52)=TRUE,D51-F51,"") | E52: =IF(ISNUMBER(B52)=TRUE,D52*$E$6/12,"") | F52: =IF(ISNUMBER(B52)=TRUE,G52-E52,"") | G52: =IF(ISNUMBER(B52)=TRUE,$E$11,"") | H52: =IF(ISNUMBER(B52)=TRUE,E52*$E$10,"") | I52: =IF(ISNUMBER(B52)=TRUE,(E52+H52+$H$14/($E$8*12))*L52,"") | J52: =IF(ISNUMBER(B52)=TRUE,-G52-H52+I52,"") | L52: =IF(ISNUMBER(B52)=TRUE,DR!F$25,"")
B53: =IF(B52<>"",IF(B52+1<=E$8*12,B52+1,""),"") | C53: =IF(ISNUMBER(B53)=TRUE,EOMONTH(C52,1),"") | D53: =IF(ISNUMBER(B53)=TRUE,D52-F52,"") | E53: =IF(ISNUMBER(B53)=TRUE,D53*$E$6/12,"") | F53: =IF(ISNUMBER(B53)=TRUE,G53-E53,"") | G53: =IF(ISNUMBER(B53)=TRUE,$E$11,"") | H53: =IF(ISNUMBER(B53)=TRUE,E53*$E$10,"") | I53: =IF(ISNUMBER(B53)=TRUE,(E53+H53+$H$14/($E$8*12))*L53,"") | J53: =IF(ISNUMBER(B53)=TRUE,-G53-H53+I53,"") | L53: =IF(ISNUMBER(B53)=TRUE,DR!F$25,"")
B54: =IF(B53<>"",IF(B53+1<=E$8*12,B53+1,""),"") | C54: =IF(ISNUMBER(B54)=TRUE,EOMONTH(C53,1),"") | D54: =IF(ISNUMBER(B54)=TRUE,D53-F53,"") | E54: =IF(ISNUMBER(B54)=TRUE,D54*$E$6/12,"") | F54: =IF(ISNUMBER(B54)=TRUE,G54-E54,"") | G54: =IF(ISNUMBER(B54)=TRUE,$E$11,"") | H54: =IF(ISNUMBER(B54)=TRUE,E54*$E$10,"") | I54: =IF(ISNUMBER(B54)=TRUE,(E54+H54+$H$14/($E$8*12))*L54,"") | J54: =IF(ISNUMBER(B54)=TRUE,-G54-H54+I54,"") | L54: =IF(ISNUMBER(B54)=TRUE,DR!F$25,"")
B55: =IF(B54<>"",IF(B54+1<=E$8*12,B54+1,""),"") | C55: =IF(ISNUMBER(B55)=TRUE,EOMONTH(C54,1),"") | D55: =IF(ISNUMBER(B55)=TRUE,D54-F54,"") | E55: =IF(ISNUMBER(B55)=TRUE,D55*$E$6/12,"") | F55: =IF(ISNUMBER(B55)=TRUE,G55-E55,"") | G55: =IF(ISNUMBER(B55)=TRUE,$E$11,"") | H55: =IF(ISNUMBER(B55)=TRUE,E55*$E$10,"") | I55: =IF(ISNUMBER(B55)=TRUE,(E55+H55+$H$14/($E$8*12))*L55,"") | J55: =IF(ISNUMBER(B55)=TRUE,-G55-H55+I55,"") | L55: =IF(ISNUMBER(B55)=TRUE,DR!F$25,"")
B56: =IF(B55<>"",IF(B55+1<=E$8*12,B55+1,""),"") | C56: =IF(ISNUMBER(B56)=TRUE,EOMONTH(C55,1),"") | D56: =IF(ISNUMBER(B56)=TRUE,D55-F55,"") | E56: =IF(ISNUMBER(B56)=TRUE,D56*$E$6/12,"") | F56: =IF(ISNUMBER(B56)=TRUE,G56-E56,"") | G56: =IF(ISNUMBER(B56)=TRUE,$E$11,"") | H56: =IF(ISNUMBER(B56)=TRUE,E56*$E$10,"") | I56: =IF(ISNUMBER(B56)=TRUE,(E56+H56+$H$14/($E$8*12))*L56,"") | J56: =IF(ISNUMBER(B56)=TRUE,-G56-H56+I56,"") | L56: =IF(ISNUMBER(B56)=TRUE,DR!F$25,"")
B57: =IF(B56<>"",IF(B56+1<=E$8*12,B56+1,""),"") | C57: =IF(ISNUMBER(B57)=TRUE,EOMONTH(C56,1),"") | D57: =IF(ISNUMBER(B57)=TRUE,D56-F56,"") | E57: =IF(ISNUMBER(B57)=TRUE,D57*$E$6/12,"") | F57: =IF(ISNUMBER(B57)=TRUE,G57-E57,"") | G57: =IF(ISNUMBER(B57)=TRUE,$E$11,"") | H57: =IF(ISNUMBER(B57)=TRUE,E57*$E$10,"") | I57: =IF(ISNUMBER(B57)=TRUE,(E57+H57+$H$14/($E$8*12))*L57,"") | J57: =IF(ISNUMBER(B57)=TRUE,-G57-H57+I57,"") | L57: =IF(ISNUMBER(B57)=TRUE,DR!F$25,"")
B58: =IF(B57<>"",IF(B57+1<=E$8*12,B57+1,""),"") | C58: =IF(ISNUMBER(B58)=TRUE,EOMONTH(C57,1),"") | D58: =IF(ISNUMBER(B58)=TRUE,D57-F57,"") | E58: =IF(ISNUMBER(B58)=TRUE,D58*$E$6/12,"") | F58: =IF(ISNUMBER(B58)=TRUE,G58-E58,"") | G58: =IF(ISNUMBER(B58)=TRUE,$E$11,"") | H58: =IF(ISNUMBER(B58)=TRUE,E58*$E$10,"") | I58: =IF(ISNUMBER(B58)=TRUE,(E58+H58+$H$14/($E$8*12))*L58,"") | J58: =IF(ISNUMBER(B58)=TRUE,-G58-H58+I58,"") | L58: =IF(ISNUMBER(B58)=TRUE,DR!F$25,"")
B59: =IF(B58<>"",IF(B58+1<=E$8*12,B58+1,""),"") | C59: =IF(ISNUMBER(B59)=TRUE,EOMONTH(C58,1),"") | D59: =IF(ISNUMBER(B59)=TRUE,D58-F58,"") | E59: =IF(ISNUMBER(B59)=TRUE,D59*$E$6/12,"") | F59: =IF(ISNUMBER(B59)=TRUE,G59-E59,"") | G59: =IF(ISNUMBER(B59)=TRUE,$E$11,"") | H59: =IF(ISNUMBER(B59)=TRUE,E59*$E$10,"") | I59: =IF(ISNUMBER(B59)=TRUE,(E59+H59+$H$14/($E$8*12))*L59,"") | J59: =IF(ISNUMBER(B59)=TRUE,-G59-H59+I59,"") | L59: =IF(ISNUMBER(B59)=TRUE,DR!F$25,"")
B60: =IF(B59<>"",IF(B59+1<=E$8*12,B59+1,""),"") | C60: =IF(ISNUMBER(B60)=TRUE,EOMONTH(C59,1),"") | D60: =IF(ISNUMBER(B60)=TRUE,D59-F59,"") | E60: =IF(ISNUMBER(B60)=TRUE,D60*$E$6/12,"") | F60: =IF(ISNUMBER(B60)=TRUE,G60-E60,"") | G60: =IF(ISNUMBER(B60)=TRUE,$E$11,"") | H60: =IF(ISNUMBER(B60)=TRUE,E60*$E$10,"") | I60: =IF(ISNUMBER(B60)=TRUE,(E60+H60+$H$14/($E$8*12))*L60,"") | J60: =IF(ISNUMBER(B60)=TRUE,-G60-H60+I60,"") | L60: =IF(ISNUMBER(B60)=TRUE,DR!F$25,"")
B61: =IF(B60<>"",IF(B60+1<=E$8*12,B60+1,""),"") | C61: =IF(ISNUMBER(B61)=TRUE,EOMONTH(C60,1),"") | D61: =IF(ISNUMBER(B61)=TRUE,D60-F60,"") | E61: =IF(ISNUMBER(B61)=TRUE,D61*$E$6/12,"") | F61: =IF(ISNUMBER(B61)=TRUE,G61-E61,"") | G61: =IF(ISNUMBER(B61)=TRUE,$E$11,"") | H61: =IF(ISNUMBER(B61)=TRUE,E61*$E$10,"") | I61: =IF(ISNUMBER(B61)=TRUE,(E61+H61+$H$14/($E$8*12))*L61,"") | J61: =IF(ISNUMBER(B61)=TRUE,-G61-H61+I61,"") | L61: =IF(ISNUMBER(B61)=TRUE,DR!F$25,"")
B62: =IF(B61<>"",IF(B61+1<=E$8*12,B61+1,""),"") | C62: =IF(ISNUMBER(B62)=TRUE,EOMONTH(C61,1),"") | D62: =IF(ISNUMBER(B62)=TRUE,D61-F61,"") | E62: =IF(ISNUMBER(B62)=TRUE,D62*$E$6/12,"") | F62: =IF(ISNUMBER(B62)=TRUE,G62-E62,"") | G62: =IF(ISNUMBER(B62)=TRUE,$E$11,"") | H62: =IF(ISNUMBER(B62)=TRUE,E62*$E$10,"") | I62: =IF(ISNUMBER(B62)=TRUE,(E62+H62+$H$14/($E$8*12))*L62,"") | J62: =IF(ISNUMBER(B62)=TRUE,-G62-H62+I62,"") | L62: =IF(ISNUMBER(B62)=TRUE,DR!F$25,"")
B63: =IF(B62<>"",IF(B62+1<=E$8*12,B62+1,""),"") | C63: =IF(ISNUMBER(B63)=TRUE,EOMONTH(C62,1),"") | D63: =IF(ISNUMBER(B63)=TRUE,D62-F62,"") | E63: =IF(ISNUMBER(B63)=TRUE,D63*$E$6/12,"") | F63: =IF(ISNUMBER(B63)=TRUE,G63-E63,"") | G63: =IF(ISNUMBER(B63)=TRUE,$E$11,"") | H63: =IF(ISNUMBER(B63)=TRUE,E63*$E$10,"") | I63: =IF(ISNUMBER(B63)=TRUE,(E63+H63+$H$14/($E$8*12))*L63,"") | J63: =IF(ISNUMBER(B63)=TRUE,-G63-H63+I63,"") | L63: =IF(ISNUMBER(B63)=TRUE,DR!G$25,"")
B64: =IF(B63<>"",IF(B63+1<=E$8*12,B63+1,""),"") | C64: =IF(ISNUMBER(B64)=TRUE,EOMONTH(C63,1),"") | D64: =IF(ISNUMBER(B64)=TRUE,D63-F63,"") | E64: =IF(ISNUMBER(B64)=TRUE,D64*$E$6/12,"") | F64: =IF(ISNUMBER(B64)=TRUE,G64-E64,"") | G64: =IF(ISNUMBER(B64)=TRUE,$E$11,"") | H64: =IF(ISNUMBER(B64)=TRUE,E64*$E$10,"") | I64: =IF(ISNUMBER(B64)=TRUE,(E64+H64+$H$14/($E$8*12))*L64,"") | J64: =IF(ISNUMBER(B64)=TRUE,-G64-H64+I64,"") | L64: =IF(ISNUMBER(B64)=TRUE,DR!G$25,"")
B65: =IF(B64<>"",IF(B64+1<=E$8*12,B64+1,""),"") | C65: =IF(ISNUMBER(B65)=TRUE,EOMONTH(C64,1),"") | D65: =IF(ISNUMBER(B65)=TRUE,D64-F64,"") | E65: =IF(ISNUMBER(B65)=TRUE,D65*$E$6/12,"") | F65: =IF(ISNUMBER(B65)=TRUE,G65-E65,"") | G65: =IF(ISNUMBER(B65)=TRUE,$E$11,"") | H65: =IF(ISNUMBER(B65)=TRUE,E65*$E$10,"") | I65: =IF(ISNUMBER(B65)=TRUE,(E65+H65+$H$14/($E$8*12))*L65,"") | J65: =IF(ISNUMBER(B65)=TRUE,-G65-H65+I65,"") | L65: =IF(ISNUMBER(B65)=TRUE,DR!G$25,"")
B66: =IF(B65<>"",IF(B65+1<=E$8*12,B65+1,""),"") | C66: =IF(ISNUMBER(B66)=TRUE,EOMONTH(C65,1),"") | D66: =IF(ISNUMBER(B66)=TRUE,D65-F65,"") | E66: =IF(ISNUMBER(B66)=TRUE,D66*$E$6/12,"") | F66: =IF(ISNUMBER(B66)=TRUE,G66-E66,"") | G66: =IF(ISNUMBER(B66)=TRUE,$E$11,"") | H66: =IF(ISNUMBER(B66)=TRUE,E66*$E$10,"") | I66: =IF(ISNUMBER(B66)=TRUE,(E66+H66+$H$14/($E$8*12))*L66,"") | J66: =IF(ISNUMBER(B66)=TRUE,-G66-H66+I66,"") | L66: =IF(ISNUMBER(B66)=TRUE,DR!G$25,"")
B67: =IF(B66<>"",IF(B66+1<=E$8*12,B66+1,""),"") | C67: =IF(ISNUMBER(B67)=TRUE,EOMONTH(C66,1),"") | D67: =IF(ISNUMBER(B67)=TRUE,D66-F66,"") | E67: =IF(ISNUMBER(B67)=TRUE,D67*$E$6/12,"") | F67: =IF(ISNUMBER(B67)=TRUE,G67-E67,"") | G67: =IF(ISNUMBER(B67)=TRUE,$E$11,"") | H67: =IF(ISNUMBER(B67)=TRUE,E67*$E$10,"") | I67: =IF(ISNUMBER(B67)=TRUE,(E67+H67+$H$14/($E$8*12))*L67,"") | J67: =IF(ISNUMBER(B67)=TRUE,-G67-H67+I67,"") | L67: =IF(ISNUMBER(B67)=TRUE,DR!G$25,"")
B68: =IF(B67<>"",IF(B67+1<=E$8*12,B67+1,""),"") | C68: =IF(ISNUMBER(B68)=TRUE,EOMONTH(C67,1),"") | D68: =IF(ISNUMBER(B68)=TRUE,D67-F67,"") | E68: =IF(ISNUMBER(B68)=TRUE,D68*$E$6/12,"") | F68: =IF(ISNUMBER(B68)=TRUE,G68-E68,"") | G68: =IF(ISNUMBER(B68)=TRUE,$E$11,"") | H68: =IF(ISNUMBER(B68)=TRUE,E68*$E$10,"") | I68: =IF(ISNUMBER(B68)=TRUE,(E68+H68+$H$14/($E$8*12))*L68,"") | J68: =IF(ISNUMBER(B68)=TRUE,-G68-H68+I68,"") | L68: =IF(ISNUMBER(B68)=TRUE,DR!G$25,"")
B69: =IF(B68<>"",IF(B68+1<=E$8*12,B68+1,""),"") | C69: =IF(ISNUMBER(B69)=TRUE,EOMONTH(C68,1),"") | D69: =IF(ISNUMBER(B69)=TRUE,D68-F68,"") | E69: =IF(ISNUMBER(B69)=TRUE,D69*$E$6/12,"") | F69: =IF(ISNUMBER(B69)=TRUE,G69-E69,"") | G69: =IF(ISNUMBER(B69)=TRUE,$E$11,"") | H69: =IF(ISNUMBER(B69)=TRUE,E69*$E$10,"") | I69: =IF(ISNUMBER(B69)=TRUE,(E69+H69+$H$14/($E$8*12))*L69,"") | J69: =IF(ISNUMBER(B69)=TRUE,-G69-H69+I69,"") | L69: =IF(ISNUMBER(B69)=TRUE,DR!G$25,"")
B70: =IF(B69<>"",IF(B69+1<=E$8*12,B69+1,""),"") | C70: =IF(ISNUMBER(B70)=TRUE,EOMONTH(C69,1),"") | D70: =IF(ISNUMBER(B70)=TRUE,D69-F69,"") | E70: =IF(ISNUMBER(B70)=TRUE,D70*$E$6/12,"") | F70: =IF(ISNUMBER(B70)=TRUE,G70-E70,"") | G70: =IF(ISNUMBER(B70)=TRUE,$E$11,"") | H70: =IF(ISNUMBER(B70)=TRUE,E70*$E$10,"") | I70: =IF(ISNUMBER(B70)=TRUE,(E70+H70+$H$14/($E$8*12))*L70,"") | J70: =IF(ISNUMBER(B70)=TRUE,-G70-H70+I70,"") | L70: =IF(ISNUMBER(B70)=TRUE,DR!G$25,"")
B71: =IF(B70<>"",IF(B70+1<=E$8*12,B70+1,""),"") | C71: =IF(ISNUMBER(B71)=TRUE,EOMONTH(C70,1),"") | D71: =IF(ISNUMBER(B71)=TRUE,D70-F70,"") | E71: =IF(ISNUMBER(B71)=TRUE,D71*$E$6/12,"") | F71: =IF(ISNUMBER(B71)=TRUE,G71-E71,"") | G71: =IF(ISNUMBER(B71)=TRUE,$E$11,"") | H71: =IF(ISNUMBER(B71)=TRUE,E71*$E$10,"") | I71: =IF(ISNUMBER(B71)=TRUE,(E71+H71+$H$14/($E$8*12))*L71,"") | J71: =IF(ISNUMBER(B71)=TRUE,-G71-H71+I71,"") | L71: =IF(ISNUMBER(B71)=TRUE,DR!G$25,"")
B72: =IF(B71<>"",IF(B71+1<=E$8*12,B71+1,""),"") | C72: =IF(ISNUMBER(B72)=TRUE,EOMONTH(C71,1),"") | D72: =IF(ISNUMBER(B72)=TRUE,D71-F71,"") | E72: =IF(ISNUMBER(B72)=TRUE,D72*$E$6/12,"") | F72: =IF(ISNUMBER(B72)=TRUE,G72-E72,"") | G72: =IF(ISNUMBER(B72)=TRUE,$E$11,"") | H72: =IF(ISNUMBER(B72)=TRUE,E72*$E$10,"") | I72: =IF(ISNUMBER(B72)=TRUE,(E72+H72+$H$14/($E$8*12))*L72,"") | J72: =IF(ISNUMBER(B72)=TRUE,-G72-H72+I72,"") | L72: =IF(ISNUMBER(B72)=TRUE,DR!G$25,"")
B73: =IF(B72<>"",IF(B72+1<=E$8*12,B72+1,""),"") | C73: =IF(ISNUMBER(B73)=TRUE,EOMONTH(C72,1),"") | D73: =IF(ISNUMBER(B73)=TRUE,D72-F72,"") | E73: =IF(ISNUMBER(B73)=TRUE,D73*$E$6/12,"") | F73: =IF(ISNUMBER(B73)=TRUE,G73-E73,"") | G73: =IF(ISNUMBER(B73)=TRUE,$E$11,"") | H73: =IF(ISNUMBER(B73)=TRUE,E73*$E$10,"") | I73: =IF(ISNUMBER(B73)=TRUE,(E73+H73+$H$14/($E$8*12))*L73,"") | J73: =IF(ISNUMBER(B73)=TRUE,-G73-H73+I73,"") | L73: =IF(ISNUMBER(B73)=TRUE,DR!G$25,"")
B74: =IF(B73<>"",IF(B73+1<=E$8*12,B73+1,""),"") | C74: =IF(ISNUMBER(B74)=TRUE,EOMONTH(C73,1),"") | D74: =IF(ISNUMBER(B74)=TRUE,D73-F73,"") | E74: =IF(ISNUMBER(B74)=TRUE,D74*$E$6/12,"") | F74: =IF(ISNUMBER(B74)=TRUE,G74-E74,"") | G74: =IF(ISNUMBER(B74)=TRUE,$E$11,"") | H74: =IF(ISNUMBER(B74)=TRUE,E74*$E$10,"") | I74: =IF(ISNUMBER(B74)=TRUE,(E74+H74+$H$14/($E$8*12))*L74,"") | J74: =IF(ISNUMBER(B74)=TRUE,-G74-H74+I74,"") | L74: =IF(ISNUMBER(B74)=TRUE,DR!G$25,"")
B75: =IF(B74<>"",IF(B74+1<=E$8*12,B74+1,""),"") | C75: =IF(ISNUMBER(B75)=TRUE,EOMONTH(C74,1),"") | D75: =IF(ISNUMBER(B75)=TRUE,D74-F74,"") | E75: =IF(ISNUMBER(B75)=TRUE,D75*$E$6/12,"") | F75: =IF(ISNUMBER(B75)=TRUE,G75-E75,"") | G75: =IF(ISNUMBER(B75)=TRUE,$E$11,"") | H75: =IF(ISNUMBER(B75)=TRUE,E75*$E$10,"") | I75: =IF(ISNUMBER(B75)=TRUE,(E75+H75+$H$14/($E$8*12))*L75,"") | J75: =IF(ISNUMBER(B75)=TRUE,-G75-H75+I75,"") | L75: =IF(ISNUMBER(B75)=TRUE,DR!H$25,"")
B76: =IF(B75<>"",IF(B75+1<=E$8*12,B75+1,""),"") | C76: =IF(ISNUMBER(B76)=TRUE,EOMONTH(C75,1),"") | D76: =IF(ISNUMBER(B76)=TRUE,D75-F75,"") | E76: =IF(ISNUMBER(B76)=TRUE,D76*$E$6/12,"") | F76: =IF(ISNUMBER(B76)=TRUE,G76-E76,"") | G76: =IF(ISNUMBER(B76)=TRUE,$E$11,"") | H76: =IF(ISNUMBER(B76)=TRUE,E76*$E$10,"") | I76: =IF(ISNUMBER(B76)=TRUE,(E76+H76+$H$14/($E$8*12))*L76,"") | J76: =IF(ISNUMBER(B76)=TRUE,-G76-H76+I76,"") | L76: =IF(ISNUMBER(B76)=TRUE,DR!H$25,"")
B77: =IF(B76<>"",IF(B76+1<=E$8*12,B76+1,""),"") | C77: =IF(ISNUMBER(B77)=TRUE,EOMONTH(C76,1),"") | D77: =IF(ISNUMBER(B77)=TRUE,D76-F76,"") | E77: =IF(ISNUMBER(B77)=TRUE,D77*$E$6/12,"") | F77: =IF(ISNUMBER(B77)=TRUE,G77-E77,"") | G77: =IF(ISNUMBER(B77)=TRUE,$E$11,"") | H77: =IF(ISNUMBER(B77)=TRUE,E77*$E$10,"") | I77: =IF(ISNUMBER(B77)=TRUE,(E77+H77+$H$14/($E$8*12))*L77,"") | J77: =IF(ISNUMBER(B77)=TRUE,-G77-H77+I77,"") | L77: =IF(ISNUMBER(B77)=TRUE,DR!H$25,"")
B78: =IF(B77<>"",IF(B77+1<=E$8*12,B77+1,""),"") | C78: =IF(ISNUMBER(B78)=TRUE,EOMONTH(C77,1),"") | D78: =IF(ISNUMBER(B78)=TRUE,D77-F77,"") | E78: =IF(ISNUMBER(B78)=TRUE,D78*$E$6/12,"") | F78: =IF(ISNUMBER(B78)=TRUE,G78-E78,"") | G78: =IF(ISNUMBER(B78)=TRUE,$E$11,"") | H78: =IF(ISNUMBER(B78)=TRUE,E78*$E$10,"") | I78: =IF(ISNUMBER(B78)=TRUE,(E78+H78+$H$14/($E$8*12))*L78,"") | J78: =IF(ISNUMBER(B78)=TRUE,-G78-H78+I78,"") | L78: =IF(ISNUMBER(B78)=TRUE,DR!H$25,"")
B79: =IF(B78<>"",IF(B78+1<=E$8*12,B78+1,""),"") | C79: =IF(ISNUMBER(B79)=TRUE,EOMONTH(C78,1),"") | D79: =IF(ISNUMBER(B79)=TRUE,D78-F78,"") | E79: =IF(ISNUMBER(B79)=TRUE,D79*$E$6/12,"") | F79: =IF(ISNUMBER(B79)=TRUE,G79-E79,"") | G79: =IF(ISNUMBER(B79)=TRUE,$E$11,"") | H79: =IF(ISNUMBER(B79)=TRUE,E79*$E$10,"") | I79: =IF(ISNUMBER(B79)=TRUE,(E79+H79+$H$14/($E$8*12))*L79,"") | J79: =IF(ISNUMBER(B79)=TRUE,-G79-H79+I79,"") | L79: =IF(ISNUMBER(B79)=TRUE,DR!H$25,"")
B80: =IF(B79<>"",IF(B79+1<=E$8*12,B79+1,""),"") | C80: =IF(ISNUMBER(B80)=TRUE,EOMONTH(C79,1),"") | D80: =IF(ISNUMBER(B80)=TRUE,D79-F79,"") | E80: =IF(ISNUMBER(B80)=TRUE,D80*$E$6/12,"") | F80: =IF(ISNUMBER(B80)=TRUE,G80-E80,"") | G80: =IF(ISNUMBER(B80)=TRUE,$E$11,"") | H80: =IF(ISNUMBER(B80)=TRUE,E80*$E$10,"") | I80: =IF(ISNUMBER(B80)=TRUE,(E80+H80+$H$14/($E$8*12))*L80,"") | J80: =IF(ISNUMBER(B80)=TRUE,-G80-H80+I80,"") | L80: =IF(ISNUMBER(B80)=TRUE,DR!H$25,"")
B81: =IF(B80<>"",IF(B80+1<=E$8*12,B80+1,""),"") | C81: =IF(ISNUMBER(B81)=TRUE,EOMONTH(C80,1),"") | D81: =IF(ISNUMBER(B81)=TRUE,D80-F80,"") | E81: =IF(ISNUMBER(B81)=TRUE,D81*$E$6/12,"") | F81: =IF(ISNUMBER(B81)=TRUE,G81-E81,"") | G81: =IF(ISNUMBER(B81)=TRUE,$E$11,"") | H81: =IF(ISNUMBER(B81)=TRUE,E81*$E$10,"") | I81: =IF(ISNUMBER(B81)=TRUE,(E81+H81+$H$14/($E$8*12))*L81,"") | J81: =IF(ISNUMBER(B81)=TRUE,-G81-H81+I81,"") | L81: =IF(ISNUMBER(B81)=TRUE,DR!H$25,"")
B82: =IF(B81<>"",IF(B81+1<=E$8*12,B81+1,""),"") | C82: =IF(ISNUMBER(B82)=TRUE,EOMONTH(C81,1),"") | D82: =IF(ISNUMBER(B82)=TRUE,D81-F81,"") | E82: =IF(ISNUMBER(B82)=TRUE,D82*$E$6/12,"") | F82: =IF(ISNUMBER(B82)=TRUE,G82-E82,"") | G82: =IF(ISNUMBER(B82)=TRUE,$E$11,"") | H82: =IF(ISNUMBER(B82)=TRUE,E82*$E$10,"") | I82: =IF(ISNUMBER(B82)=TRUE,(E82+H82+$H$14/($E$8*12))*L82,"") | J82: =IF(ISNUMBER(B82)=TRUE,-G82-H82+I82,"") | L82: =IF(ISNUMBER(B82)=TRUE,DR!H$25,"")
B83: =IF(B82<>"",IF(B82+1<=E$8*12,B82+1,""),"") | C83: =IF(ISNUMBER(B83)=TRUE,EOMONTH(C82,1),"") | D83: =IF(ISNUMBER(B83)=TRUE,D82-F82,"") | E83: =IF(ISNUMBER(B83)=TRUE,D83*$E$6/12,"") | F83: =IF(ISNUMBER(B83)=TRUE,G83-E83,"") | G83: =IF(ISNUMBER(B83)=TRUE,$E$11,"") | H83: =IF(ISNUMBER(B83)=TRUE,E83*$E$10,"") | I83: =IF(ISNUMBER(B83)=TRUE,(E83+H83+$H$14/($E$8*12))*L83,"") | J83: =IF(ISNUMBER(B83)=TRUE,-G83-H83+I83,"") | L83: =IF(ISNUMBER(B83)=TRUE,DR!H$25,"")
B84: =IF(B83<>"",IF(B83+1<=E$8*12,B83+1,""),"") | C84: =IF(ISNUMBER(B84)=TRUE,EOMONTH(C83,1),"") | D84: =IF(ISNUMBER(B84)=TRUE,D83-F83,"") | E84: =IF(ISNUMBER(B84)=TRUE,D84*$E$6/12,"") | F84: =IF(ISNUMBER(B84)=TRUE,G84-E84,"") | G84: =IF(ISNUMBER(B84)=TRUE,$E$11,"") | H84: =IF(ISNUMBER(B84)=TRUE,E84*$E$10,"") | I84: =IF(ISNUMBER(B84)=TRUE,(E84+H84+$H$14/($E$8*12))*L84,"") | J84: =IF(ISNUMBER(B84)=TRUE,-G84-H84+I84,"") | L84: =IF(ISNUMBER(B84)=TRUE,DR!H$25,"")
B85: =IF(B84<>"",IF(B84+1<=E$8*12,B84+1,""),"") | C85: =IF(ISNUMBER(B85)=TRUE,EOMONTH(C84,1),"") | D85: =IF(ISNUMBER(B85)=TRUE,D84-F84,"") | E85: =IF(ISNUMBER(B85)=TRUE,D85*$E$6/12,"") | F85: =IF(ISNUMBER(B85)=TRUE,G85-E85,"") | G85: =IF(ISNUMBER(B85)=TRUE,$E$11,"") | H85: =IF(ISNUMBER(B85)=TRUE,E85*$E$10,"") | I85: =IF(ISNUMBER(B85)=TRUE,(E85+H85+$H$14/($E$8*12))*L85,"") | J85: =IF(ISNUMBER(B85)=TRUE,-G85-H85+I85,"") | L85: =IF(ISNUMBER(B85)=TRUE,DR!H$25,"")
B86: =IF(B85<>"",IF(B85+1<=E$8*12,B85+1,""),"") | C86: =IF(ISNUMBER(B86)=TRUE,EOMONTH(C85,1),"") | D86: =IF(ISNUMBER(B86)=TRUE,D85-F85,"") | E86: =IF(ISNUMBER(B86)=TRUE,D86*$E$6/12,"") | F86: =IF(ISNUMBER(B86)=TRUE,G86-E86,"") | G86: =IF(ISNUMBER(B86)=TRUE,$E$11,"") | H86: =IF(ISNUMBER(B86)=TRUE,E86*$E$10,"") | I86: =IF(ISNUMBER(B86)=TRUE,(E86+H86+$H$14/($E$8*12))*L86,"") | J86: =IF(ISNUMBER(B86)=TRUE,-G86-H86+I86,"") | L86: =IF(ISNUMBER(B86)=TRUE,DR!H$25,"")
B87: =IF(B86<>"",IF(B86+1<=E$8*12,B86+1,""),"") | C87: =IF(ISNUMBER(B87)=TRUE,EOMONTH(C86,1),"") | D87: =IF(ISNUMBER(B87)=TRUE,D86-F86,"") | E87: =IF(ISNUMBER(B87)=TRUE,D87*$E$6/12,"") | F87: =IF(ISNUMBER(B87)=TRUE,G87-E87,"") | G87: =IF(ISNUMBER(B87)=TRUE,$E$11,"") | H87: =IF(ISNUMBER(B87)=TRUE,E87*$E$10,"") | I87: =IF(ISNUMBER(B87)=TRUE,(E87+H87+$H$14/($E$8*12))*L87,"") | J87: =IF(ISNUMBER(B87)=TRUE,-G87-H87+I87,"") | L87: =IF(ISNUMBER(B87)=TRUE,DR!I$25,"")
B88: =IF(B87<>"",IF(B87+1<=E$8*12,B87+1,""),"") | C88: =IF(ISNUMBER(B88)=TRUE,EOMONTH(C87,1),"") | D88: =IF(ISNUMBER(B88)=TRUE,D87-F87,"") | E88: =IF(ISNUMBER(B88)=TRUE,D88*$E$6/12,"") | F88: =IF(ISNUMBER(B88)=TRUE,G88-E88,"") | G88: =IF(ISNUMBER(B88)=TRUE,$E$11,"") | H88: =IF(ISNUMBER(B88)=TRUE,E88*$E$10,"") | I88: =IF(ISNUMBER(B88)=TRUE,(E88+H88+$H$14/($E$8*12))*L88,"") | J88: =IF(ISNUMBER(B88)=TRUE,-G88-H88+I88,"") | L88: =IF(ISNUMBER(B88)=TRUE,DR!I$25,"")
B89: =IF(B88<>"",IF(B88+1<=E$8*12,B88+1,""),"") | C89: =IF(ISNUMBER(B89)=TRUE,EOMONTH(C88,1),"") | D89: =IF(ISNUMBER(B89)=TRUE,D88-F88,"") | E89: =IF(ISNUMBER(B89)=TRUE,D89*$E$6/12,"") | F89: =IF(ISNUMBER(B89)=TRUE,G89-E89,"") | G89: =IF(ISNUMBER(B89)=TRUE,$E$11,"") | H89: =IF(ISNUMBER(B89)=TRUE,E89*$E$10,"") | I89: =IF(ISNUMBER(B89)=TRUE,(E89+H89+$H$14/($E$8*12))*L89,"") | J89: =IF(ISNUMBER(B89)=TRUE,-G89-H89+I89,"") | L89: =IF(ISNUMBER(B89)=TRUE,DR!I$25,"")
B90: =IF(B89<>"",IF(B89+1<=E$8*12,B89+1,""),"") | C90: =IF(ISNUMBER(B90)=TRUE,EOMONTH(C89,1),"") | D90: =IF(ISNUMBER(B90)=TRUE,D89-F89,"") | E90: =IF(ISNUMBER(B90)=TRUE,D90*$E$6/12,"") | F90: =IF(ISNUMBER(B90)=TRUE,G90-E90,"") | G90: =IF(ISNUMBER(B90)=TRUE,$E$11,"") | H90: =IF(ISNUMBER(B90)=TRUE,E90*$E$10,"") | I90: =IF(ISNUMBER(B90)=TRUE,(E90+H90+$H$14/($E$8*12))*L90,"") | J90: =IF(ISNUMBER(B90)=TRUE,-G90-H90+I90,"") | L90: =IF(ISNUMBER(B90)=TRUE,DR!I$25,"")
B91: =IF(B90<>"",IF(B90+1<=E$8*12,B90+1,""),"") | C91: =IF(ISNUMBER(B91)=TRUE,EOMONTH(C90,1),"") | D91: =IF(ISNUMBER(B91)=TRUE,D90-F90,"") | E91: =IF(ISNUMBER(B91)=TRUE,D91*$E$6/12,"") | F91: =IF(ISNUMBER(B91)=TRUE,G91-E91,"") | G91: =IF(ISNUMBER(B91)=TRUE,$E$11,"") | H91: =IF(ISNUMBER(B91)=TRUE,E91*$E$10,"") | I91: =IF(ISNUMBER(B91)=TRUE,(E91+H91+$H$14/($E$8*12))*L91,"") | J91: =IF(ISNUMBER(B91)=TRUE,-G91-H91+I91,"") | L91: =IF(ISNUMBER(B91)=TRUE,DR!I$25,"")
B92: =IF(B91<>"",IF(B91+1<=E$8*12,B91+1,""),"") | C92: =IF(ISNUMBER(B92)=TRUE,EOMONTH(C91,1),"") | D92: =IF(ISNUMBER(B92)=TRUE,D91-F91,"") | E92: =IF(ISNUMBER(B92)=TRUE,D92*$E$6/12,"") | F92: =IF(ISNUMBER(B92)=TRUE,G92-E92,"") | G92: =IF(ISNUMBER(B92)=TRUE,$E$11,"") | H92: =IF(ISNUMBER(B92)=TRUE,E92*$E$10,"") | I92: =IF(ISNUMBER(B92)=TRUE,(E92+H92+$H$14/($E$8*12))*L92,"") | J92: =IF(ISNUMBER(B92)=TRUE,-G92-H92+I92,"") | L92: =IF(ISNUMBER(B92)=TRUE,DR!I$25,"")
B93: =IF(B92<>"",IF(B92+1<=E$8*12,B92+1,""),"") | C93: =IF(ISNUMBER(B93)=TRUE,EOMONTH(C92,1),"") | D93: =IF(ISNUMBER(B93)=TRUE,D92-F92,"") | E93: =IF(ISNUMBER(B93)=TRUE,D93*$E$6/12,"") | F93: =IF(ISNUMBER(B93)=TRUE,G93-E93,"") | G93: =IF(ISNUMBER(B93)=TRUE,$E$11,"") | H93: =IF(ISNUMBER(B93)=TRUE,E93*$E$10,"") | I93: =IF(ISNUMBER(B93)=TRUE,(E93+H93+$H$14/($E$8*12))*L93,"") | J93: =IF(ISNUMBER(B93)=TRUE,-G93-H93+I93,"") | L93: =IF(ISNUMBER(B93)=TRUE,DR!I$25,"")
B94: =IF(B93<>"",IF(B93+1<=E$8*12,B93+1,""),"") | C94: =IF(ISNUMBER(B94)=TRUE,EOMONTH(C93,1),"") | D94: =IF(ISNUMBER(B94)=TRUE,D93-F93,"") | E94: =IF(ISNUMBER(B94)=TRUE,D94*$E$6/12,"") | F94: =IF(ISNUMBER(B94)=TRUE,G94-E94,"") | G94: =IF(ISNUMBER(B94)=TRUE,$E$11,"") | H94: =IF(ISNUMBER(B94)=TRUE,E94*$E$10,"") | I94: =IF(ISNUMBER(B94)=TRUE,(E94+H94+$H$14/($E$8*12))*L94,"") | J94: =IF(ISNUMBER(B94)=TRUE,-G94-H94+I94,"") | L94: =IF(ISNUMBER(B94)=TRUE,DR!I$25,"")
B95: =IF(B94<>"",IF(B94+1<=E$8*12,B94+1,""),"") | C95: =IF(ISNUMBER(B95)=TRUE,EOMONTH(C94,1),"") | D95: =IF(ISNUMBER(B95)=TRUE,D94-F94,"") | E95: =IF(ISNUMBER(B95)=TRUE,D95*$E$6/12,"") | F95: =IF(ISNUMBER(B95)=TRUE,G95-E95,"") | G95: =IF(ISNUMBER(B95)=TRUE,$E$11,"") | H95: =IF(ISNUMBER(B95)=TRUE,E95*$E$10,"") | I95: =IF(ISNUMBER(B95)=TRUE,(E95+H95+$H$14/($E$8*12))*L95,"") | J95: =IF(ISNUMBER(B95)=TRUE,-G95-H95+I95,"") | L95: =IF(ISNUMBER(B95)=TRUE,DR!I$25,"")
B96: =IF(B95<>"",IF(B95+1<=E$8*12,B95+1,""),"") | C96: =IF(ISNUMBER(B96)=TRUE,EOMONTH(C95,1),"") | D96: =IF(ISNUMBER(B96)=TRUE,D95-F95,"") | E96: =IF(ISNUMBER(B96)=TRUE,D96*$E$6/12,"") | F96: =IF(ISNUMBER(B96)=TRUE,G96-E96,"") | G96: =IF(ISNUMBER(B96)=TRUE,$E$11,"") | H96: =IF(ISNUMBER(B96)=TRUE,E96*$E$10,"") | I96: =IF(ISNUMBER(B96)=TRUE,(E96+H96+$H$14/($E$8*12))*L96,"") | J96: =IF(ISNUMBER(B96)=TRUE,-G96-H96+I96,"") | L96: =IF(ISNUMBER(B96)=TRUE,DR!I$25,"")
B97: =IF(B96<>"",IF(B96+1<=E$8*12,B96+1,""),"") | C97: =IF(ISNUMBER(B97)=TRUE,EOMONTH(C96,1),"") | D97: =IF(ISNUMBER(B97)=TRUE,D96-F96,"") | E97: =IF(ISNUMBER(B97)=TRUE,D97*$E$6/12,"") | F97: =IF(ISNUMBER(B97)=TRUE,G97-E97,"") | G97: =IF(ISNUMBER(B97)=TRUE,$E$11,"") | H97: =IF(ISNUMBER(B97)=TRUE,E97*$E$10,"") | I97: =IF(ISNUMBER(B97)=TRUE,(E97+H97+$H$14/($E$8*12))*L97,"") | J97: =IF(ISNUMBER(B97)=TRUE,-G97-H97+I97,"") | L97: =IF(ISNUMBER(B97)=TRUE,DR!I$25,"")
B98: =IF(B97<>"",IF(B97+1<=E$8*12,B97+1,""),"") | C98: =IF(ISNUMBER(B98)=TRUE,EOMONTH(C97,1),"") | D98: =IF(ISNUMBER(B98)=TRUE,D97-F97,"") | E98: =IF(ISNUMBER(B98)=TRUE,D98*$E$6/12,"") | F98: =IF(ISNUMBER(B98)=TRUE,G98-E98,"") | G98: =IF(ISNUMBER(B98)=TRUE,$E$11,"") | H98: =IF(ISNUMBER(B98)=TRUE,E98*$E$10,"") | I98: =IF(ISNUMBER(B98)=TRUE,(E98+H98+$H$14/($E$8*12))*L98,"") | J98: =IF(ISNUMBER(B98)=TRUE,-G98-H98+I98,"") | L98: =IF(ISNUMBER(B98)=TRUE,DR!I$25,"")
B99: =IF(B98<>"",IF(B98+1<=E$8*12,B98+1,""),"") | C99: =IF(ISNUMBER(B99)=TRUE,EOMONTH(C98,1),"") | D99: =IF(ISNUMBER(B99)=TRUE,D98-F98,"") | E99: =IF(ISNUMBER(B99)=TRUE,D99*$E$6/12,"") | F99: =IF(ISNUMBER(B99)=TRUE,G99-E99,"") | G99: =IF(ISNUMBER(B99)=TRUE,$E$11,"") | H99: =IF(ISNUMBER(B99)=TRUE,E99*$E$10,"") | I99: =IF(ISNUMBER(B99)=TRUE,(E99+H99+$H$14/($E$8*12))*L99,"") | J99: =IF(ISNUMBER(B99)=TRUE,-G99-H99+I99,"") | L99: =IF(ISNUMBER(B99)=TRUE,DR!J$25,"")
B100: =IF(B99<>"",IF(B99+1<=E$8*12,B99+1,""),"") | C100: =IF(ISNUMBER(B100)=TRUE,EOMONTH(C99,1),"") | D100: =IF(ISNUMBER(B100)=TRUE,D99-F99,"") | E100: =IF(ISNUMBER(B100)=TRUE,D100*$E$6/12,"") | F100: =IF(ISNUMBER(B100)=TRUE,G100-E100,"") | G100: =IF(ISNUMBER(B100)=TRUE,$E$11,"") | H100: =IF(ISNUMBER(B100)=TRUE,E100*$E$10,"") | I100: =IF(ISNUMBER(B100)=TRUE,(E100+H100+$H$14/($E$8*12))*L100,"") | J100: =IF(ISNUMBER(B100)=TRUE,-G100-H100+I100,"") | L100: =IF(ISNUMBER(B100)=TRUE,DR!J$25,"")
B101: =IF(B100<>"",IF(B100+1<=E$8*12,B100+1,""),"") | C101: =IF(ISNUMBER(B101)=TRUE,EOMONTH(C100,1),"") | D101: =IF(ISNUMBER(B101)=TRUE,D100-F100,"") | E101: =IF(ISNUMBER(B101)=TRUE,D101*$E$6/12,"") | F101: =IF(ISNUMBER(B101)=TRUE,G101-E101,"") | G101: =IF(ISNUMBER(B101)=TRUE,$E$11,"") | H101: =IF(ISNUMBER(B101)=TRUE,E101*$E$10,"") | I101: =IF(ISNUMBER(B101)=TRUE,(E101+H101+$H$14/($E$8*12))*L101,"") | J101: =IF(ISNUMBER(B101)=TRUE,-G101-H101+I101,"") | L101: =IF(ISNUMBER(B101)=TRUE,DR!J$25,"")
B102: =IF(B101<>"",IF(B101+1<=E$8*12,B101+1,""),"") | C102: =IF(ISNUMBER(B102)=TRUE,EOMONTH(C101,1),"") | D102: =IF(ISNUMBER(B102)=TRUE,D101-F101,"") | E102: =IF(ISNUMBER(B102)=TRUE,D102*$E$6/12,"") | F102: =IF(ISNUMBER(B102)=TRUE,G102-E102,"") | G102: =IF(ISNUMBER(B102)=TRUE,$E$11,"") | H102: =IF(ISNUMBER(B102)=TRUE,E102*$E$10,"") | I102: =IF(ISNUMBER(B102)=TRUE,(E102+H102+$H$14/($E$8*12))*L102,"") | J102: =IF(ISNUMBER(B102)=TRUE,-G102-H102+I102,"") | L102: =IF(ISNUMBER(B102)=TRUE,DR!J$25,"")
B103: =IF(B102<>"",IF(B102+1<=E$8*12,B102+1,""),"") | C103: =IF(ISNUMBER(B103)=TRUE,EOMONTH(C102,1),"") | D103: =IF(ISNUMBER(B103)=TRUE,D102-F102,"") | E103: =IF(ISNUMBER(B103)=TRUE,D103*$E$6/12,"") | F103: =IF(ISNUMBER(B103)=TRUE,G103-E103,"") | G103: =IF(ISNUMBER(B103)=TRUE,$E$11,"") | H103: =IF(ISNUMBER(B103)=TRUE,E103*$E$10,"") | I103: =IF(ISNUMBER(B103)=TRUE,(E103+H103+$H$14/($E$8*12))*L103,"") | J103: =IF(ISNUMBER(B103)=TRUE,-G103-H103+I103,"") | L103: =IF(ISNUMBER(B103)=TRUE,DR!J$25,"")
B104: =IF(B103<>"",IF(B103+1<=E$8*12,B103+1,""),"") | C104: =IF(ISNUMBER(B104)=TRUE,EOMONTH(C103,1),"") | D104: =IF(ISNUMBER(B104)=TRUE,D103-F103,"") | E104: =IF(ISNUMBER(B104)=TRUE,D104*$E$6/12,"") | F104: =IF(ISNUMBER(B104)=TRUE,G104-E104,"") | G104: =IF(ISNUMBER(B104)=TRUE,$E$11,"") | H104: =IF(ISNUMBER(B104)=TRUE,E104*$E$10,"") | I104: =IF(ISNUMBER(B104)=TRUE,(E104+H104+$H$14/($E$8*12))*L104,"") | J104: =IF(ISNUMBER(B104)=TRUE,-G104-H104+I104,"") | L104: =IF(ISNUMBER(B104)=TRUE,DR!J$25,"")
...

Sheet NFM
B2: ESTADO E OUTROS ENTES PÚBLICOS
B3: Descrição | C3: =IF(Pressupostos!F$10<>"",Pressupostos!F$10-1,"") -> 2023 | D3: =IF(Pressupostos!F$10<>"",Pressupostos!F$10,"") -> 2024 | E3: =IF(Pressupostos!G$10<>"",Pressupostos!G$10,"") -> 2025 | F3: =IF(Pressupostos!H$10<>"",Pressupostos!H$10,"") | G3: =IF(Pressupostos!I$10<>"",Pressupostos!I$10,"") | H3: =IF(Pressupostos!J$10<>"",Pressupostos!J$10,"") | I3: =IF(Pressupostos!K$10<>"",Pressupostos!K$10,"") | J3: =IF(Pressupostos!L$10<>"",Pressupostos!L$10,"") | K3: =IF(Pressupostos!M$10<>"",Pressupostos!M$10,"") | ... R3: =IF(Pressupostos!T$10<>"",Pressupostos!T$10,"")
B4: Imposto sobre o valor acrescentado:
B5: IVA liquidado | D5: =IF(D$3<>"",Pressupostos!F19*Pressupostos!F21*Pressupostos!F22+Pressupostos!F23*Pressupostos!F24*Pressupostos!F26+Pressupostos!F29+Pressupostos!F30*Pressupostos!F32+Pressupostos!F33*Pressupostos!F34*Pressupostos!F36+Pressupostos!F39*Pressupostos!F40*Pressupostos!F41+Pressupostos!F42*Pressupostos!F43*Pressupostos!F44,"") -> 22702.3 | E5: =IF(E$3<>"",Pressupostos!G19*Pressupostos!G21*Pressupostos!G22+Pressupostos!G23*Pressupostos!G24*Pressupostos!G26+Pressupostos!G29+Pressupostos!G30*Pressupostos!G32+Pressupostos!G33*Pressupostos!G34*Pressupostos!G36+Pressupostos!G39*Pressupostos!G40*Pressupostos!G41+Pressupostos!G42*Pressupostos!G43*Pressupostos!G44,"") -> 32977.76 | F5: =IF(F$3<>"",Pressupostos!H19*Pressupostos!H21*Pressupostos!H22+Pressupostos!H23*Pressupostos!H24*Pressupostos!H26+Pressupostos!H29+Pressupostos!H30*Pressupostos!H32+Pressupostos!H33*Pressupostos!H34*Pressupostos!H36+Pressupostos!H39*Pressupostos!H40*Pressupostos!H41+Pressupostos!H42*Pressupostos!H43*Pressupostos!H44,"") | G5: =IF(G$3<>"",Pressupostos!I19*Pressupostos!I21*Pressupostos!I22+Pressupostos!I23*Pressupostos!I24*Pressupostos!I26+Pressupostos!I29+Pressupostos!I30*Pressupostos!I32+Pressupostos!I33*Pressupostos!I34*Pressupostos!I36+Pressupostos!I39*Pressupostos!I40*Pressupostos!I41+Pressupostos!I42*Pressupostos!I43*Pressupostos!I44,"") | H5: =IF(H$3<>"",Pressupostos!J19*Pressupostos!J21*Pressupostos!J22+Pressupostos!J23*Pressupostos!J24*Pressupostos!J26+Pressupostos!J29+Pressupostos!J30*Pressupostos!J32+Pressupostos!J33*Pressupostos!J34*Pressupostos!J36+Pressupostos!J39*Pressupostos!J40*Pressupostos!J41+Pressupostos!J42*Pressupostos!J43*Pressupostos!J44,"") | I5: =IF(I$3<>"",Pressupostos!K19*Pressupostos!K21*Pressupostos!K22+Pressupostos!K23*Pressupostos!K24*Pressupostos!K26+Pressupostos!K29+Pressupostos!K30*Pressupostos!K32+Pressupostos!K33*Pressupostos!K34*Pressupostos!K36+Pressupostos!K39*Pressupostos!K40*Pressupostos!K41+Pressupostos!K42*Pressupostos!K43*Pressupostos!K44,"") | J5: =IF(J$3<>"",Pressupostos!L19*Pressupostos!L21*Pressupostos!L22+Pressupostos!L23*Pressupostos!L24*Pressupostos!L26+Pressupostos!L29+Pressupostos!L30*Pressupostos!L32+Pressupostos!L33*Pressupostos!L34*Pressupostos!L36+Pressupostos!L39*Pressupostos!L40*Pressupostos!L41+Pressupostos!L42*Pressupostos!L43*Pressupostos!L44,"") | K5: =IF(K$3<>"",Pressupostos!M19*Pressupostos!M21*Pressupostos!M22+Pressupostos!M23*Pressupostos!M24*Pressupostos!M26+Pressupostos!M29+Pressupostos!M30*Pressupostos!M32+Pressupostos!M33*Pressupostos!M34*Pressupostos!M36+Pressupostos!M39*Pressupostos!M40*Pressupostos!M41+Pressupostos!M42*Pressupostos!M43*Pressupostos!M44,"") | ... R5: =IF(R$3<>"",Pressupostos!T19*Pressupostos!T21*Pressupostos!T22+Pressupostos!T23*Pressupostos!T24*Pressupostos!T26+Pressupostos!T29+Pressupostos!T30*Pressupostos!T32+Pressupostos!T33*Pressupostos!T34*Pressupostos!T36+Pressupostos!T39*Pressupostos!T40*Pressupostos!T41+Pressupostos!T42*Pressupostos!T43*Pressupostos!T44,"")
B6: IVA dedutível | D6: =IF(D$3<>"",SUM(Compras!C23:C24)*Pressupostos!F22+SUM(Compras!C26:C27)*Pressupostos!F26+SUMPRODUCT(Pressupostos!$D$50:$D$80,Pressupostos!F50:F80),"") -> 34870.955 | E6: =IF(E$3<>"",SUM(Compras!D23:D24)*Pressupostos!G22+SUM(Compras!D26:D27)*Pressupostos!G26+SUMPRODUCT(Pressupostos!$D$50:$D$80,Pressupostos!G50:G80),"") -> 49272.541 | F6: =IF(F$3<>"",SUM(Compras!E23:E24)*Pressupostos!H22+SUM(Compras!E26:E27)*Pressupostos!H26+SUMPRODUCT(Pressupostos!$D$50:$D$80,Pressupostos!H50:H80),"") | G6: =IF(G$3<>"",SUM(Compras!F23:F24)*Pressupostos!I22+SUM(Compras!F26:F27)*Pressupostos!I26+SUMPRODUCT(Pressupostos!$D$50:$D$80,Pressupostos!I50:I80),"") | H6: =IF(H$3<>"",SUM(Compras!G23:G24)*Pressupostos!J22+SUM(Compras!G26:G27)*Pressupostos!J26+SUMPRODUCT(Pressupostos!$D$50:$D$80,Pressupostos!J50:J80),"") | I6: =IF(I$3<>"",SUM(Compras!H23:H24)*Pressupostos!K22+SUM(Compras!H26:H27)*Pressupostos!K26+SUMPRODUCT(Pressupostos!$D$50:$D$80,Pressupostos!K50:K80),"") | J6: =IF(J$3<>"",SUM(Compras!I23:I24)*Pressupostos!L22+SUM(Compras!I26:I27)*Pressupostos!L26+SUMPRODUCT(Pressupostos!$D$50:$D$80,Pressupostos!L50:L80),"") | K6: =IF(K$3<>"",SUM(Compras!J23:J24)*Pressupostos!M22+SUM(Compras!J26:J27)*Pressupostos!M26+SUMPRODUCT(Pressupostos!$D$50:$D$80,Pressupostos!M50:M80),"") | ... R6: =IF(R$3<>"",SUM(Compras!Q23:Q24)*Pressupostos!T22+SUM(Compras!Q26:Q27)*Pressupostos!T26+SUMPRODUCT(Pressupostos!$D$50:$D$80,Pressupostos!T50:T80),"")
B7: IVA apuramento | D7: =IF(D$3<>"",D5-D6,"") -> -12168.655 | E7: =IF(E$3<>"",E5-E6,"") -> -16294.781 | F7: =IF(F$3<>"",F5-F6,"") | G7: =IF(G$3<>"",G5-G6,"") | H7: =IF(H$3<>"",H5-H6,"") | I7: =IF(I$3<>"",I5-I6,"") | J7: =IF(J$3<>"",J5-J6,"") | K7: =IF(K$3<>"",K5-K6,"") | ... R7: =IF(R$3<>"",R5-R6,"")
B8: IVA a recuperar | D8: =IF(D$3<>"",IF(D7<0,-D7,),"") -> 12168.655 | E8: =IF(E$3<>"",IF(E7<0,-E7,),"") -> 16294.781 | F8: =IF(F$3<>"",IF(F7<0,-F7,),"") | G8: =IF(G$3<>"",IF(G7<0,-G7,),"") | H8: =IF(H$3<>"",IF(H7<0,-H7,),"") | I8: =IF(I$3<>"",IF(I7<0,-I7,),"") | J8: =IF(J$3<>"",IF(J7<0,-J7,),"") | K8: =IF(K$3<>"",IF(K7<0,-K7,),"") | ... R8: =IF(R$3<>"",IF(R7<0,-R7,),"")
B9: IVA a pagar | D9: =IF(D$3<>"",IF(D7>0,D7-C8,),"") -> 0 | E9: =IF(E$3<>"",IF(E7>0,E7-D8,),"") -> 0 | F9: =IF(F$3<>"",IF(F7>0,F7-E8,),"") | G9: =IF(G$3<>"",IF(G7>0,G7-F8,),"") | H9: =IF(H$3<>"",IF(H7>0,H7-G8,),"") | I9: =IF(I$3<>"",IF(I7>0,I7-H8,),"") | J9: =IF(J$3<>"",IF(J7>0,J7-I8,),"") | K9: =IF(K$3<>"",IF(K7>0,K7-J8,),"") | ... R9: =IF(R$3<>"",IF(R7>0,R7-Q8,),"")
B10: Si Estado IVA | D10: =IF(D$3<>"",C11,"") -> 0 | E10: =IF(E$3<>"",D11,"") -> 0 | F10: =IF(F$3<>"",E11,"") | G10: =IF(G$3<>"",F11,"") | H10: =IF(H$3<>"",G11,"") | I10: =IF(I$3<>"",H11,"") | J10: =IF(J$3<>"",I11,"") | K10: =IF(K$3<>"",J11,"") | ... R10: =IF(R$3<>"",Q11,"")
B11: Sf Estado IVA | D11: =IF(D$3<>"",D9/12*Pressupostos!$D$129,"") -> 0 | E11: =IF(E$3<>"",E9/12*Pressupostos!$D$129,"") -> 0 | F11: =IF(F$3<>"",F9/12*Pressupostos!$D$129,"") | G11: =IF(G$3<>"",G9/12*Pressupostos!$D$129,"") | H11: =IF(H$3<>"",H9/12*Pressupostos!$D$129,"") | I11: =IF(I$3<>"",I9/12*Pressupostos!$D$129,"") | J11: =IF(J$3<>"",J9/12*Pressupostos!$D$129,"") | K11: =IF(K$3<>"",K9/12*Pressupostos!$D$129,"") | ... R11: =IF(R$3<>"",R9/12*Pressupostos!$D$129,"")
B12: Contribuições para a segurança social:
B13: Contribuições para a segurança Social | D13: =IF(D$3<>"",SUM(Pressupostos!F96:F98)*(Pressupostos!$D$118+Pressupostos!$D$119),"") -> 16054.5 | E13: =IF(E$3<>"",SUM(Pressupostos!G96:G98)*(Pressupostos!$D$118+Pressupostos!$D$119),"") -> 16375.59 | F13: =IF(F$3<>"",SUM(Pressupostos!H96:H98)*(Pressupostos!$D$118+Pressupostos!$D$119),"") | G13: =IF(G$3<>"",SUM(Pressupostos!I96:I98)*(Pressupostos!$D$118+Pressupostos!$D$119),"") | H13: =IF(H$3<>"",SUM(Pressupostos!J96:J98)*(Pressupostos!$D$118+Pressupostos!$D$119),"") | I13: =IF(I$3<>"",SUM(Pressupostos!K96:K98)*(Pressupostos!$D$118+Pressupostos!$D$119),"") | J13: =IF(J$3<>"",SUM(Pressupostos!L96:L98)*(Pressupostos!$D$118+Pressupostos!$D$119),"") | K13: =IF(K$3<>"",SUM(Pressupostos!M96:M98)*(Pressupostos!$D$118+Pressupostos!$D$119),"") | ... R13: =IF(R$3<>"",SUM(Pressupostos!T96:T98)*(Pressupostos!$D$118+Pressupostos!$D$119),"")
B14: Si Estado Seg. Social | D14: =IF(D$3<>"",C15,"") -> 0 | E14: =IF(E$3<>"",D15,"") -> 1337.875 | F14: =IF(F$3<>"",E15,"") | G14: =IF(G$3<>"",F15,"") | H14: =IF(H$3<>"",G15,"") | I14: =IF(I$3<>"",H15,"") | J14: =IF(J$3<>"",I15,"") | K14: =IF(K$3<>"",J15,"") | ... R14: =IF(R$3<>"",Q15,"")
B15: Sf Estado Seg. Social | D15: =IF(D$3<>"",D13/12*Pressupostos!$D$130,"") -> 1337.875 | E15: =IF(E$3<>"",E13/12*Pressupostos!$D$130,"") -> 1364.6325 | F15: =IF(F$3<>"",F13/12*Pressupostos!$D$130,"") | G15: =IF(G$3<>"",G13/12*Pressupostos!$D$130,"") | H15: =IF(H$3<>"",H13/12*Pressupostos!$D$130,"") | I15: =IF(I$3<>"",I13/12*Pressupostos!$D$130,"") | J15: =IF(J$3<>"",J13/12*Pressupostos!$D$130,"") | K15: =IF(K$3<>"",K13/12*Pressupostos!$D$130,"") | ... R15: =IF(R$3<>"",R13/12*Pressupostos!$D$130,"")
B16: Imposto sobre o rendimento das pessoas singulares:
B17: Retenções de imposto sobre o rendimento | D17: =IF(D$3<>"",SUM(Pressupostos!F96:F98)*Pressupostos!$D$116,"") -> 2310 | E17: =IF(E$3<>"",SUM(Pressupostos!G96:G98)*Pressupostos!$D$116,"") -> 2356.2 | F17: =IF(F$3<>"",SUM(Pressupostos!H96:H98)*Pressupostos!$D$116,"") | G17: =IF(G$3<>"",SUM(Pressupostos!I96:I98)*Pressupostos!$D$116,"") | H17: =IF(H$3<>"",SUM(Pressupostos!J96:J98)*Pressupostos!$D$116,"") | I17: =IF(I$3<>"",SUM(Pressupostos!K96:K98)*Pressupostos!$D$116,"") | J17: =IF(J$3<>"",SUM(Pressupostos!L96:L98)*Pressupostos!$D$116,"") | K17: =IF(K$3<>"",SUM(Pressupostos!M96:M98)*Pressupostos!$D$116,"") | ... R17: =IF(R$3<>"",SUM(Pressupostos!T96:T98)*Pressupostos!$D$116,"")
B18: Si Estado - IRS | D18: =IF(D$3<>"",C19,"") -> 0 | E18: =IF(E$3<>"",D19,"") -> 192.5 | F18: =IF(F$3<>"",E19,"") | G18: =IF(G$3<>"",F19,"") | H18: =IF(H$3<>"",G19,"") | I18: =IF(I$3<>"",H19,"") | J18: =IF(J$3<>"",I19,"") | K18: =IF(K$3<>"",J19,"") | ... R18: =IF(R$3<>"",Q19,"")
B19: Sf Estado - IRS | D19: =IF(D$3<>"",D17/12*Pressupostos!$D$130,"") -> 192.5 | E19: =IF(E$3<>"",E17/12*Pressupostos!$D$130,"") -> 196.35 | F19: =IF(F$3<>"",F17/12*Pressupostos!$D$130,"") | G19: =IF(G$3<>"",G17/12*Pressupostos!$D$130,"") | H19: =IF(H$3<>"",H17/12*Pressupostos!$D$130,"") | I19: =IF(I$3<>"",I17/12*Pressupostos!$D$130,"") | J19: =IF(J$3<>"",J17/12*Pressupostos!$D$130,"") | K19: =IF(K$3<>"",K17/12*Pressupostos!$D$130,"") | ... R19: =IF(R$3<>"",R17/12*Pressupostos!$D$130,"")
B21: NECESSIDADES DE FUNDO DE MANEIO
B22: Descrição | C22: =IF(Pressupostos!F$10<>"",Pressupostos!F$10-1,"") -> 2023 | D22: =IF(Pressupostos!F$10<>"",Pressupostos!F$10,"") -> 2024 | E22: =IF(Pressupostos!G$10<>"",Pressupostos!G$10,"") -> 2025 | F22: =IF(Pressupostos!H$10<>"",Pressupostos!H$10,"") | G22: =IF(Pressupostos!I$10<>"",Pressupostos!I$10,"") | H22: =IF(Pressupostos!J$10<>"",Pressupostos!J$10,"") | I22: =IF(Pressupostos!K$10<>"",Pressupostos!K$10,"") | J22: =IF(Pressupostos!L$10<>"",Pressupostos!L$10,"") | K22: =IF(Pressupostos!M$10<>"",Pressupostos!M$10,"") | ... R22: =IF(Pressupostos!T$10<>"",Pressupostos!T$10,"")
A24: + | B24: Inventários | D24: =IF(D$3<>"",SUM(Compras!C11:C12)+SUM(Compras!C14:C15)+Compras!C34,"") -> 17916.667 | E24: =IF(E$3<>"",SUM(Compras!D11:D12)+SUM(Compras!D14:D15)+Compras!D34,"") -> 26875 | F24: =IF(F$3<>"",SUM(Compras!E11:E12)+SUM(Compras!E14:E15)+Compras!E34,"") | G24: =IF(G$3<>"",SUM(Compras!F11:F12)+SUM(Compras!F14:F15)+Compras!F34,"") | H24: =IF(H$3<>"",SUM(Compras!G11:G12)+SUM(Compras!G14:G15)+Compras!G34,"") | I24: =IF(I$3<>"",SUM(Compras!H11:H12)+SUM(Compras!H14:H15)+Compras!H34,"") | J24: =IF(J$3<>"",SUM(Compras!I11:I12)+SUM(Compras!I14:I15)+Compras!I34,"") | K24: =IF(K$3<>"",SUM(Compras!J11:J12)+SUM(Compras!J14:J15)+Compras!J34,"") | ... R24: =IF(R$3<>"",SUM(Compras!Q11:Q12)+SUM(Compras!Q14:Q15)+Compras!Q34,"")
A25: + | B25: Clientes | D25: =IF(D$3<>"",(DR!C4+D5)/12*Pressupostos!$D$124,"") -> 53783.717 | E25: =IF(E$3<>"",(DR!D4+E5)/12*Pressupostos!$D$124,"") -> 80496.293 | F25: =IF(F$3<>"",(DR!E4+F5)/12*Pressupostos!$D$124,"") | G25: =IF(G$3<>"",(DR!F4+G5)/12*Pressupostos!$D$124,"") | H25: =IF(H$3<>"",(DR!G4+H5)/12*Pressupostos!$D$124,"") | I25: =IF(I$3<>"",(DR!H4+I5)/12*Pressupostos!$D$124,"") | J25: =IF(J$3<>"",(DR!I4+J5)/12*Pressupostos!$D$124,"") | K25: =IF(K$3<>"",(DR!J4+K5)/12*Pressupostos!$D$124,"") | ... R25: =IF(R$3<>"",(DR!Q4+R5)/12*Pressupostos!$D$124,"")
A26: + | B26: Estado e outros entes públicos (ativo) | D26: =IF(D$3<>"",D8,"") -> 12168.655 | E26: =IF(E$3<>"",E8,"") -> 16294.781 | F26: =IF(F$3<>"",F8,"") | G26: =IF(G$3<>"",G8,"") | H26: =IF(H$3<>"",H8,"") | I26: =IF(I$3<>"",I8,"") | J26: =IF(J$3<>"",J8,"") | K26: =IF(K$3<>"",K8,"") | ... R26: =IF(R$3<>"",R8,"")
A27: + | B27: Caixa
A28: - | B28: Fornecedores | D28: =IF(D$3<>"",(SUM(Compras!C23:C24)+SUM(Compras!C26:C27)-DR!C7+NFM!D6)/12*Pressupostos!$D$129,"") -> 31388.23 | E28: =IF(E$3<>"",(SUM(Compras!D23:D24)+SUM(Compras!D26:D27)-DR!D7+NFM!E6)/12*Pressupostos!$D$129,"") -> 44230.578 | F28: =IF(F$3<>"",(SUM(Compras!E23:E24)+SUM(Compras!E26:E27)-DR!E7+NFM!F6)/12*Pressupostos!$D$129,"") | G28: =IF(G$3<>"",(SUM(Compras!F23:F24)+SUM(Compras!F26:F27)-DR!F7+NFM!G6)/12*Pressupostos!$D$129,"") | H28: =IF(H$3<>"",(SUM(Compras!G23:G24)+SUM(Compras!G26:G27)-DR!G7+NFM!H6)/12*Pressupostos!$D$129,"") | I28: =IF(I$3<>"",(SUM(Compras!H23:H24)+SUM(Compras!H26:H27)-DR!H7+NFM!I6)/12*Pressupostos!$D$129,"") | J28: =IF(J$3<>"",(SUM(Compras!I23:I24)+SUM(Compras!I26:I27)-DR!I7+NFM!J6)/12*Pressupostos!$D$129,"") | K28: =IF(K$3<>"",(SUM(Compras!J23:J24)+SUM(Compras!J26:J27)-DR!J7+NFM!K6)/12*Pressupostos!$D$129,"") | ... R28: =IF(R$3<>"",(SUM(Compras!Q23:Q24)+SUM(Compras!Q26:Q27)-DR!Q7+NFM!R6)/12*Pressupostos!$D$129,"")
A29: - | B29: Estado e outros entes públicos (passivo) | D29: =IF(D$3<>"",D11+D15+D19,"") -> 1530.375 | E29: =IF(E$3<>"",E11+E15+E19,"") -> 1560.9825 | F29: =IF(F$3<>"",F11+F15+F19,"") | G29: =IF(G$3<>"",G11+G15+G19,"") | H29: =IF(H$3<>"",H11+H15+H19,"") | I29: =IF(I$3<>"",I11+I15+I19,"") | J29: =IF(J$3<>"",J11+J15+J19,"") | K29: =IF(K$3<>"",K11+K15+K19,"") | ... R29: =IF(R$3<>"",R11+R15+R19,"")
B30: NFM | D30: =IF(D$3<>"",D24+D25+D26+D27-D28-D29,"") -> 50950.433 | E30: =IF(E$3<>"",E24+E25+E26+E27-E28-E29,"") -> 77874.513 | F30: =IF(F$3<>"",F24+F25+F26+F27-F28-F29,"") | G30: =IF(G$3<>"",G24+G25+G26+G27-G28-G29,"") | H30: =IF(H$3<>"",H24+H25+H26+H27-H28-H29,"") | I30: =IF(I$3<>"",I24+I25+I26+I27-I28-I29,"") | J30: =IF(J$3<>"",J24+J25+J26+J27-J28-J29,"") | K30: =IF(K$3<>"",K24+K25+K26+K27-K28-K29,"") | ... R30: =IF(R$3<>"",R24+R25+R26+R27-R28-R29,"")
B31: D NFM | D31: =IF(D$3<>"",D30-C30,"") -> 50950.433 | E31: =IF(E$3<>"",E30-D30,"") -> 26924.08 | F31: =IF(F$3<>"",F30-E30,"") | G31: =IF(G$3<>"",G30-F30,"") | H31: =IF(H$3<>"",H30-G30,"") | I31: =IF(I$3<>"",I30-H30,"") | J31: =IF(J$3<>"",J30-I30,"") | K31: =IF(K$3<>"",K30-J30,"") | ... R31: =IF(R$3<>"",R30-Q30,"")

Sheet FCF
B2: FREE CASH FLOW TO FIRM E FREE CASH FLOW TO FIRM
B3: Descrição | C3: =IF(Pressupostos!F10<>"",Pressupostos!F10-1,"") -> 2023 | D3: =IF(Pressupostos!F10<>"",Pressupostos!F10,"") -> 2024 | E3: =IF(Pressupostos!G10<>"",Pressupostos!G10,"") -> 2025 | F3: =IF(Pressupostos!H10<>"",Pressupostos!H10,"") | G3: =IF(Pressupostos!I10<>"",Pressupostos!I10,"") | H3: =IF(Pressupostos!J10<>"",Pressupostos!J10,"") | I3: =IF(Pressupostos!K10<>"",Pressupostos!K10,"") | J3: =IF(Pressupostos!L10<>"",Pressupostos!L10,"") | K3: =IF(Pressupostos!M10<>"",Pressupostos!M10,"") | ... R3: =IF(Pressupostos!T10<>"",Pressupostos!T10,"")
B5: EBIT | D5: =IF(D$3<>"",DR!C12,"") -> 76452.74 | E5: =IF(E$3<>"",DR!D12,"") -> 141315.79 | F5: =IF(F$3<>"",DR!E12,"") | G5: =IF(G$3<>"",DR!F12,"") | H5: =IF(H$3<>"",DR!G12,"") | I5: =IF(I$3<>"",DR!H12,"") | J5: =IF(J$3<>"",DR!I12,"") | K5: =IF(K$3<>"",DR!J12,"") | ... R5: =IF(R$3<>"",DR!Q12,"")
B6: Impostos sobre o EBIT | D6: =IF(D$3<>"",-D5*DR!C25,"") -> -17201.866 | E6: =IF(E$3<>"",-E5*DR!D25,"") -> -31796.054 | F6: =IF(F$3<>"",-F5*DR!E25,"") | G6: =IF(G$3<>"",-G5*DR!F25,"") | H6: =IF(H$3<>"",-H5*DR!G25,"") | I6: =IF(I$3<>"",-I5*DR!H25,"") | J6: =IF(J$3<>"",-J5*DR!I25,"") | K6: =IF(K$3<>"",-K5*DR!J25,"") | ... R6: =IF(R$3<>"",-R5*DR!Q25,"")
B7: Gastos de depreciação e de amortização | D7: =IF(D$3<>"",-DR!C11,"") -> 33700 | E7: =IF(E$3<>"",-DR!D11,"") -> 38200 | F7: =IF(F$3<>"",-DR!E11,"") | G7: =IF(G$3<>"",-DR!F11,"") | H7: =IF(H$3<>"",-DR!G11,"") | I7: =IF(I$3<>"",-DR!H11,"") | J7: =IF(J$3<>"",-DR!I11,"") | K7: =IF(K$3<>"",-DR!J11,"") | ... R7: =IF(R$3<>"",-DR!Q11,"")
B8: Investimento em ativo fixo | C8: =IF(C$3<>"",-Pressupostos!E167-Pressupostos!E189,"") -> -424000 | D8: =IF(D$3<>"",-Pressupostos!F167-Pressupostos!F189,"") -> -110000 | E8: =IF(E$3<>"",-Pressupostos!G167-Pressupostos!G189,"") -> -22000 | F8: =IF(F$3<>"",-Pressupostos!H167-Pressupostos!H189,"") | G8: =IF(G$3<>"",-Pressupostos!I167-Pressupostos!I189,"") | H8: =IF(H$3<>"",-Pressupostos!J167-Pressupostos!J189,"") | I8: =IF(I$3<>"",-Pressupostos!K167-Pressupostos!K189,"") | J8: =IF(J$3<>"",-Pressupostos!L167-Pressupostos!L189,"") | ... R8: =IF(R$3<>"",-Pressupostos!T167-Pressupostos!T189,"")
B9: Investimento em necessidades de fundo de maneio | D9: =IF(D$3<>"",-NFM!D31,"") -> -50950.433 | E9: =IF(E$3<>"",-NFM!E31,"") -> -26924.08 | F9: =IF(F$3<>"",-NFM!F31,"") | G9: =IF(G$3<>"",-NFM!G31,"") | H9: =IF(H$3<>"",-NFM!H31,"") | I9: =IF(I$3<>"",-NFM!I31,"") | J9: =IF(J$3<>"",-NFM!J31,"") | K9: =IF(K$3<>"",-NFM!K31,"") | ... R9: =IF(R$3<>"",-NFM!R31,"")
B10: Free Cash Flow to Firm | C10: =IF(C$3<>"",SUM(C5:C9),"") -> -424000 | D10: =IF(D$3<>"",SUM(D5:D9),"") -> -67999.56 | E10: =IF(E$3<>"",SUM(E5:E9),"") -> 98795.661 | F10: =IF(F$3<>"",SUM(F5:F9),"") | G10: =IF(G$3<>"",SUM(G5:G9),"") | H10: =IF(H$3<>"",SUM(H5:H9),"") | I10: =IF(I$3<>"",SUM(I5:I9),"") | J10: =IF(J$3<>"",SUM(J5:J9),"") | ... R10: =IF(R$3<>"",SUM(R5:R9),"")
B11: Gastos de financiamento líquidos de impostos | D11: =IF(D$3<>"",DR!C13*(1-DR!C25),"") -> -6119.5848 | E11: =IF(E$3<>"",DR!D13*(1-DR!D25),"") -> -1956.8363 | F11: =IF(F$3<>"",DR!E13*(1-DR!E25),"") | G11: =IF(G$3<>"",DR!F13*(1-DR!F25),"") | H11: =IF(H$3<>"",DR!G13*(1-DR!G25),"") | I11: =IF(I$3<>"",DR!H13*(1-DR!H25),"") | J11: =IF(J$3<>"",DR!I13*(1-DR!I25),"") | K11: =IF(K$3<>"",DR!J13*(1-DR!J25),"") | ... R11: =IF(R$3<>"",DR!Q13*(1-DR!Q25),"")
B12: Variação do endividamento | C12: =IF(C$3<>"",Empréstimo!E198+Empréstimo!E199-Empréstimo!D198-Empréstimo!D199,"") -> 173600 | D12: =IF(D$3<>"",-Empréstimo!F200,"") -> -84634.957 | E12: =IF(E$3<>"",-Empréstimo!G200,"") -> -88965.043 | F12: =IF(F$3<>"",-Empréstimo!H200,"") | G12: =IF(G$3<>"",-Empréstimo!I200,"") | H12: =IF(H$3<>"",-Empréstimo!J200,"") | I12: =IF(I$3<>"",-Empréstimo!K200,"") | J12: =IF(J$3<>"",-Empréstimo!L200,"") | K12: =IF(K$3<>"",-Empréstimo!M200,"") | ... R12: =IF(R$3<>"",-Empréstimo!T200,"")
B13: Free Cash Flow to Equity | C13: =IF(C$3<>"",SUM(C10:C12),"") -> -250400 | D13: =IF(D$3<>"",SUM(D10:D12),"") -> -158754.1 | E13: =IF(E$3<>"",SUM(E10:E12),"") -> 7873.7818 | F13: =IF(F$3<>"",SUM(F10:F12),"") | G13: =IF(G$3<>"",SUM(G10:G12),"") | H13: =IF(H$3<>"",SUM(H10:H12),"") | I13: =IF(I$3<>"",SUM(I10:I12),"") | J13: =IF(J$3<>"",SUM(J10:J12),"") | ... R13: =IF(R$3<>"",SUM(R10:R12),"")
B15: Caixa e depósitos bancários (antes de prestações suplementares) | C15: =IF(C$3<>"",C13,"") -> -250400 | D15: =IF(D$3<>"",C18+D13,"") -> -148754.1 | E15: =IF(E$3<>"",D18+E13,"") -> 17873.782 | F15: =IF(F$3<>"",E18+F13,"") | G15: =IF(G$3<>"",F18+G13,"") | H15: =IF(H$3<>"",G18+H13,"") | I15: =IF(I$3<>"",H18+I13,"") | J15: =IF(J$3<>"",I18+J13,"") | K15: =IF(K$3<>"",J18+K13,"") | ... R15: =IF(R$3<>"",Q18+R13,"")
B16: Aumento de capital | C16: =IF(C$3<>"",Pressupostos!F262,"") -> 260400
B17: Prestações Suplementares | D17: =IF(D$3<>"",IF(D15<$C$18,-D13,0),"") -> 158754.1 | E17: =IF(E$3<>"",IF(E15<$C$18,-E15+D18,0),"") -> 0 | F17: =IF(F$3<>"",IF(F15<$C$18,-F15+E18,0),"") | G17: =IF(G$3<>"",IF(G15<$C$18,-G15+F18,0),"") | H17: =IF(H$3<>"",IF(H15<$C$18,-H15+G18,0),"") | I17: =IF(I$3<>"",IF(I15<$C$18,-I15+H18,0),"") | J17: =IF(J$3<>"",IF(J15<$C$18,-J15+I18,0),"") | K17: =IF(K$3<>"",IF(K15<$C$18,-K15+J18,0),"") | L17: =IF(L$3<>"",IF(L15<$C$18,-L15+K18,0),"") | ... R17: =IF(R$3<>"",IF(R15<$C$18,-R15+Q18,0),"")
B18: Caixa e depósitos bancários (depois de prestações suplementares) | C18: =IF(C$3<>"",SUM(C15:C17),"") -> 10000 | D18: =IF(D$3<>"",SUM(D15:D17),"") -> 10000 | E18: =IF(E$3<>"",SUM(E15:E17),"") -> 17873.782 | F18: =IF(F$3<>"",SUM(F15:F17),"") | G18: =IF(G$3<>"",SUM(G15:G17),"") | H18: =IF(H$3<>"",SUM(H15:H17),"") | I18: =IF(I$3<>"",SUM(I15:I17),"") | J18: =IF(J$3<>"",SUM(J15:J17),"") | ... R18: =IF(R$3<>"",SUM(R15:R17),"")

Sheet Balanço
B2: BALANÇOS PREVISIONAIS
B3: Descrição | C3: =IF(Pressupostos!F10<>"",Pressupostos!F10-1,"") -> 2023 | D3: =IF(Pressupostos!F10<>"",Pressupostos!F10,"") -> 2024 | E3: =IF(Pressupostos!G10<>"",Pressupostos!G10,"") -> 2025 | F3: =IF(Pressupostos!H10<>"",Pressupostos!H10,"") | G3: =IF(Pressupostos!I10<>"",Pressupostos!I10,"") | H3: =IF(Pressupostos!J10<>"",Pressupostos!J10,"") | I3: =IF(Pressupostos!K10<>"",Pressupostos!K10,"") | J3: =IF(Pressupostos!L10<>"",Pressupostos!L10,"") | K3: =IF(Pressupostos!M10<>"",Pressupostos!M10,"") | ... R3: =IF(Pressupostos!T10<>"",Pressupostos!T10,"")
B5: ACTIVO
B6: ACTIVO NÃO CORRENTE:
B7: Activos fixos tangíveis | C7: =IF(C$3<>"",Pressupostos!E249-Pressupostos!E255,"") -> 412000 | D7: =IF(D$3<>"",Pressupostos!F249-Pressupostos!F255,"") -> 489500 | E7: =IF(E$3<>"",Pressupostos!G249-Pressupostos!G255,"") -> 472500 | F7: =IF(F$3<>"",Pressupostos!H249-Pressupostos!H255,"") | G7: =IF(G$3<>"",Pressupostos!I249-Pressupostos!I255,"") | H7: =IF(H$3<>"",Pressupostos!J249-Pressupostos!J255,"") | I7: =IF(I$3<>"",Pressupostos!K249-Pressupostos!K255,"") | J7: =IF(J$3<>"",Pressupostos!L249-Pressupostos!L255,"") | ... R7: =IF(R$3<>"",Pressupostos!T249-Pressupostos!T255,"")
B8: Propriedades de investimento
B9: Activos intangíveis | C9: =IF(C$3<>"",Pressupostos!E250-Pressupostos!E256,"") -> 12000 | D9: =IF(D$3<>"",Pressupostos!F250-Pressupostos!F256,"") -> 10800 | E9: =IF(E$3<>"",Pressupostos!G250-Pressupostos!G256,"") -> 11600 | F9: =IF(F$3<>"",Pressupostos!H250-Pressupostos!H256,"") | G9: =IF(G$3<>"",Pressupostos!I250-Pressupostos!I256,"") | H9: =IF(H$3<>"",Pressupostos!J250-Pressupostos!J256,"") | I9: =IF(I$3<>"",Pressupostos!K250-Pressupostos!K256,"") | J9: =IF(J$3<>"",Pressupostos!L250-Pressupostos!L256,"") | ... R9: =IF(R$3<>"",Pressupostos!T250-Pressupostos!T256,"")
B10: Activos biológicos
B11: Participações financeiras - método da equivalência patrimonial
B12: Participações financeiras - outros métodos
B13: Accionistas / sócios
B14: Outros activos financeiros
B15: Activos por impostos diferidos
B16: Outros activos não correntes
B17: Total do activo não corrente | C17: =IF(C$3<>"",SUM(C7:C16),"") -> 424000 | D17: =IF(D$3<>"",SUM(D7:D16),"") -> 500300 | E17: =IF(E$3<>"",SUM(E7:E16),"") -> 484100 | F17: =IF(F$3<>"",SUM(F7:F16),"") | G17: =IF(G$3<>"",SUM(G7:G16),"") | H17: =IF(H$3<>"",SUM(H7:H16),"") | I17: =IF(I$3<>"",SUM(I7:I16),"") | J17: =IF(J$3<>"",SUM(J7:J16),"") | ... R17: =IF(R$3<>"",SUM(R7:R16),"")
B19: ACTIVO CORRENTE:
B20: Inventários | C20: =IF(C$3<>"",NFM!C24,"") -> 0 | D20: =IF(D$3<>"",NFM!D24,"") -> 17916.667 | E20: =IF(E$3<>"",NFM!E24,"") -> 26875 | F20: =IF(F$3<>"",NFM!F24,"") | G20: =IF(G$3<>"",NFM!G24,"") | H20: =IF(H$3<>"",NFM!H24,"") | I20: =IF(I$3<>"",NFM!I24,"") | J20: =IF(J$3<>"",NFM!J24,"") | ... R20: =IF(R$3<>"",NFM!R24,"")
B21: Activos biológicos
B22: Clientes | C22: =IF(C$3<>"",NFM!C25,"") -> 0 | D22: =IF(D$3<>"",NFM!D25,"") -> 53783.717 | E22: =IF(E$3<>"",NFM!E25,"") -> 80496.293 | F22: =IF(F$3<>"",NFM!F25,"") | G22: =IF(G$3<>"",NFM!G25,"") | H22: =IF(H$3<>"",NFM!H25,"") | I22: =IF(I$3<>"",NFM!I25,"") | J22: =IF(J$3<>"",NFM!J25,"") | ... R22: =IF(R$3<>"",NFM!R25,"")
B23: Estado e outros entes públicos | C23: =IF(C$3<>"",NFM!C26,"") -> 0 | D23: =IF(D$3<>"",NFM!D26,"") -> 12168.655 | E23: =IF(E$3<>"",NFM!E26,"") -> 16294.781 | F23: =IF(F$3<>"",NFM!F26,"") | G23: =IF(G$3<>"",NFM!G26,"") | H23: =IF(H$3<>"",NFM!H26,"") | I23: =IF(I$3<>"",NFM!I26,"") | J23: =IF(J$3<>"",NFM!J26,"") | ... R23: =IF(R$3<>"",NFM!R26,"")
B24: Accionistas/sócios
B25: Outras contas a receber
B26: Diferimentos
B27: Activos financeiros detidos para negociação
B28: Outros activos financeiros
B29: Activos não correntes detidos para venda
B30: Caixa e depósitos bancários | C30: =IF(C$3<>"",FCF!C18,"") -> 10000 | D30: =IF(D$3<>"",FCF!D18,"") -> 10000 | E30: =IF(E$3<>"",FCF!E18,"") -> 17873.782 | F30: =IF(F$3<>"",FCF!F18,"") | G30: =IF(G$3<>"",FCF!G18,"") | H30: =IF(H$3<>"",FCF!H18,"") | I30: =IF(I$3<>"",FCF!I18,"") | J30: =IF(J$3<>"",FCF!J18,"") | ... R30: =IF(R$3<>"",FCF!R18,"")
B31: Total do activo corrente | C31: =IF(C$3<>"",SUM(C20:C30),"") -> 10000 | D31: =IF(D$3<>"",SUM(D20:D30),"") -> 93869.038 | E31: =IF(E$3<>"",SUM(E20:E30),"") -> 141539.86 | F31: =IF(F$3<>"",SUM(F20:F30),"") | G31: =IF(G$3<>"",SUM(G20:G30),"") | H31: =IF(H$3<>"",SUM(H20:H30),"") | I31: =IF(I$3<>"",SUM(I20:I30),"") | J31: =IF(J$3<>"",SUM(J20:J30),"") | ... R31: =IF(R$3<>"",SUM(R20:R30),"")
B33: Total do activo | C33: =IF(C$3<>"",C17+C31,"") -> 434000 | D33: =IF(D$3<>"",D17+D31,"") -> 594169.04 | E33: =IF(E$3<>"",E17+E31,"") -> 625639.86 | F33: =IF(F$3<>"",F17+F31,"") | G33: =IF(G$3<>"",G17+G31,"") | H33: =IF(H$3<>"",H17+H31,"") | I33: =IF(I$3<>"",I17+I31,"") | J33: =IF(J$3<>"",J17+J31,"") | ... R33: =IF(R$3<>"",R17+R31,"")
B35: CAPITAL PRÓPRIO E PASSIVO
B37: CAPITAL PRÓPRIO:
B38: Capital realizado | C38: =IF(C$3<>"",Pressupostos!$F$262,"") -> 260400 | D38: =IF(D$3<>"",Pressupostos!$F$262,"") -> 260400 | E38: =IF(E$3<>"",Pressupostos!$F$262,"") -> 260400 | F38: =IF(F$3<>"",Pressupostos!$F$262,"") | G38: =IF(G$3<>"",Pressupostos!$F$262,"") | H38: =IF(H$3<>"",Pressupostos!$F$262,"") | I38: =IF(I$3<>"",Pressupostos!$F$262,"") | J38: =IF(J$3<>"",Pressupostos!$F$262,"") | ... R38: =IF(R$3<>"",Pressupostos!$F$262,"")
B39: Acções (quotas) próprias
B40: Prestações suplementares e outros inst. capital próprio | C40: =IF(C$3<>"",FCF!C17,"") -> 0 | D40: =IF(D$3<>"",+C40+FCF!D17,"") -> 158754.1 | E40: =IF(E$3<>"",+D40+FCF!E17,"") -> 158754.1 | F40: =IF(F$3<>"",+E40+FCF!F17,"") | G40: =IF(G$3<>"",+F40+FCF!G17,"") | H40: =IF(H$3<>"",+G40+FCF!H17,"") | I40: =IF(I$3<>"",+H40+FCF!I17,"") | J40: =IF(J$3<>"",+I40+FCF!J17,"") | K40: =IF(K$3<>"",+J40+FCF!K17,"") | ... R40: =IF(R$3<>"",+Q40+FCF!R17,"")
B41: Prémios de emissão
B42: Reservas e resultados transitados | D42: =IF(D$3<>"",C42+C45,"") -> 0 | E42: =IF(E$3<>"",D42+D45,"") -> 53131.289 | F42: =IF(F$3<>"",E42+E45,"") | G42: =IF(G$3<>"",F42+F45,"") | H42: =IF(H$3<>"",G42+G45,"") | I42: =IF(I$3<>"",H42+H45,"") | J42: =IF(J$3<>"",I42+I45,"") | K42: =IF(K$3<>"",J42+J45,"") | ... R42: =IF(R$3<>"",Q42+Q45,"")
B43: Outras variações no capital próprio
B44: CAPITAL, RESERVAS E RESULTADOS TRANSITADOS | C44: =IF(C$3<>"",SUM(C38:C43),"") -> 260400 | D44: =IF(D$3<>"",SUM(D38:D43),"") -> 419154.1 | E44: =IF(E$3<>"",SUM(E38:E43),"") -> 472285.39 | F44: =IF(F$3<>"",SUM(F38:F43),"") | G44: =IF(G$3<>"",SUM(G38:G43),"") | H44: =IF(H$3<>"",SUM(H38:H43),"") | I44: =IF(I$3<>"",SUM(I38:I43),"") | J44: =IF(J$3<>"",SUM(J38:J43),"") | ... R44: =IF(R$3<>"",SUM(R38:R43),"")
B45: Resultado líquido do período | D45: =IF(D$3<>"",DR!C16,"") -> 53131.289 | E45: =IF(E$3<>"",DR!D16,"") -> 107562.9 | F45: =IF(F$3<>"",DR!E16,"") | G45: =IF(G$3<>"",DR!F16,"") | H45: =IF(H$3<>"",DR!G16,"") | I45: =IF(I$3<>"",DR!H16,"") | J45: =IF(J$3<>"",DR!I16,"") | K45: =IF(K$3<>"",DR!J16,"") | ... R45: =IF(R$3<>"",DR!Q16,"")
B46: Dividendos antecipados
B47: Total do capital próprio | C47: =IF(C$3<>"",SUM(C44:C46),"") -> 260400 | D47: =IF(D$3<>"",SUM(D44:D46),"") -> 472285.39 | E47: =IF(E$3<>"",SUM(E44:E46),"") -> 579848.3 | F47: =IF(F$3<>"",SUM(F44:F46),"") | G47: =IF(G$3<>"",SUM(G44:G46),"") | H47: =IF(H$3<>"",SUM(H44:H46),"") | I47: =IF(I$3<>"",SUM(I44:I46),"") | J47: =IF(J$3<>"",SUM(J44:J46),"") | ... R47: =IF(R$3<>"",SUM(R44:R46),"")
B49: PASSIVO:
B50: PASSIVO NÃO CORRENTE:
B51: Provisões
B52: Financiamentos obtidos | C52: =IF(C$3<>"",Empréstimo!E198,"") -> 88965.043 | D52: =IF(D$3<>"",Empréstimo!F198,"") -> -2.910383e-11 | E52: =IF(E$3<>"",Empréstimo!G198,"") | F52: =IF(F$3<>"",Empréstimo!H198,"") | G52: =IF(G$3<>"",Empréstimo!I198,"") | H52: =IF(H$3<>"",Empréstimo!J198,"") | I52: =IF(I$3<>"",Empréstimo!K198,"") | J52: =IF(J$3<>"",Empréstimo!L198,"") | ... R52: =IF(R$3<>"",Empréstimo!T198,"")
B53: Responsabilidades por benefícios pós-emprego
B54: Passivos por impostos diferidos
B55: Outras contas a pagar
B56: Total do passivo não corrente | C56: =IF(C$3<>"",SUM(C51:C55),"") -> 88965.043 | D56: =IF(D$3<>"",SUM(D51:D55),"") -> -2.910383e-11 | E56: =IF(E$3<>"",SUM(E51:E55),"") -> 0 | F56: =IF(F$3<>"",SUM(F51:F55),"") | G56: =IF(G$3<>"",SUM(G51:G55),"") | H56: =IF(H$3<>"",SUM(H51:H55),"") | I56: =IF(I$3<>"",SUM(I51:I55),"") | J56: =IF(J$3<>"",SUM(J51:J55),"") | ... R56: =IF(R$3<>"",SUM(R51:R55),"")
B58: PASSIVO CORRENTE:
B59: Fornecedores | D59: =IF(D$3<>"",NFM!D28,"") -> 31388.23 | E59: =IF(E$3<>"",NFM!E28,"") -> 44230.578 | F59: =IF(F$3<>"",NFM!F28,"") | G59: =IF(G$3<>"",NFM!G28,"") | H59: =IF(H$3<>"",NFM!H28,"") | I59: =IF(I$3<>"",NFM!I28,"") | J59: =IF(J$3<>"",NFM!J28,"") | K59: =IF(K$3<>"",NFM!K28,"") | ... R59: =IF(R$3<>"",NFM!R28,"")
B60: Adiantamentos de clientes
B61: Estado e outros entes publicos | D61: =IF(D$3<>"",NFM!D29,"") -> 1530.375 | E61: =IF(E$3<>"",NFM!E29,"") -> 1560.9825 | F61: =IF(F$3<>"",NFM!F29,"") | G61: =IF(G$3<>"",NFM!G29,"") | H61: =IF(H$3<>"",NFM!H29,"") | I61: =IF(I$3<>"",NFM!I29,"") | J61: =IF(J$3<>"",NFM!J29,"") | K61: =IF(K$3<>"",NFM!K29,"") | ... R61: =IF(R$3<>"",NFM!R29,"")
B62: Accionistas/sócios
B63: Financiamentos obtidos | C63: =IF(C$3<>"",Empréstimo!E199,"") -> 84634.957 | D63: =IF(D$3<>"",Empréstimo!F199,"") -> 88965.043 | E63: =IF(E$3<>"",Empréstimo!G199,"") | F63: =IF(F$3<>"",Empréstimo!H199,"") | G63: =IF(G$3<>"",Empréstimo!I199,"") | H63: =IF(H$3<>"",Empréstimo!J199,"") | I63: =IF(I$3<>"",Empréstimo!K199,"") | J63: =IF(J$3<>"",Empréstimo!L199,"") | ... R63: =IF(R$3<>"",Empréstimo!T199,"")
B64: Outras contas a pagar
B65: Diferimentos
B66: Passivos financeiros detidos para negociação
B67: Outros passivos financeiros
B68: Passivos não correntes detidos para venda
B69: Outros passivos correntes
B70: Total do passivo corrente | C70: =IF(C$3<>"",SUM(C59:C69),"") -> 84634.957 | D70: =IF(D$3<>"",SUM(D59:D69),"") -> 121883.65 | E70: =IF(E$3<>"",SUM(E59:E69),"") -> 45791.561 | F70: =IF(F$3<>"",SUM(F59:F69),"") | G70: =IF(G$3<>"",SUM(G59:G69),"") | H70: =IF(H$3<>"",SUM(H59:H69),"") | I70: =IF(I$3<>"",SUM(I59:I69),"") | J70: =IF(J$3<>"",SUM(J59:J69),"") | ... R70: =IF(R$3<>"",SUM(R59:R69),"")
B71: Total do passivo | C71: =IF(C$3<>"",C70+C56,"") -> 173600 | D71: =IF(D$3<>"",D70+D56,"") -> 121883.65 | E71: =IF(E$3<>"",E70+E56,"") -> 45791.561 | F71: =IF(F$3<>"",F70+F56,"") | G71: =IF(G$3<>"",G70+G56,"") | H71: =IF(H$3<>"",H70+H56,"") | I71: =IF(I$3<>"",I70+I56,"") | J71: =IF(J$3<>"",J70+J56,"") | ... R71: =IF(R$3<>"",R70+R56,"")
B72: Total do capital próprio e do passivo | C72: =IF(C$3<>"",C47+C71,"") -> 434000 | D72: =IF(D$3<>"",D47+D71,"") -> 594169.04 | E72: =IF(E$3<>"",E47+E71,"") -> 625639.86 | F72: =IF(F$3<>"",F47+F71,"") | G72: =IF(G$3<>"",G47+G71,"") | H72: =IF(H$3<>"",H47+H71,"") | I72: =IF(I$3<>"",I47+I71,"") | J72: =IF(J$3<>"",J47+J71,"") | ... R72: =IF(R$3<>"",R47+R71,"")
B74: Controlo | C74: =IF(C$3<>"",C33-C72,"") -> 0 | D74: =IF(D$3<>"",D33-D72,"") -> 0 | E74: =IF(E$3<>"",E33-E72,"") -> 0 | F74: =IF(F$3<>"",F33-F72,"") | G74: =IF(G$3<>"",G33-G72,"") | H74: =IF(H$3<>"",H33-H72,"") | I74: =IF(I$3<>"",I33-I72,"") | J74: =IF(J$3<>"",J33-J72,"") | ... R74: =IF(R$3<>"",R33-R72,"")

Sheet Avaliação
B2: TAXA DE CUSTO DE OPORTUNIDADE DO CAPITAL
B3: Descrição | D3: =IF(Pressupostos!F10<>"",Pressupostos!F10,"") -> 2024 | E3: =IF(Pressupostos!G10<>"",Pressupostos!G10,"") -> 2025 | F3: =IF(Pressupostos!H10<>"",Pressupostos!H10,"") | G3: =IF(Pressupostos!I10<>"",Pressupostos!I10,"") | H3: =IF(Pressupostos!J10<>"",Pressupostos!J10,"") | I3: =IF(Pressupostos!K10<>"",Pressupostos!K10,"") | J3: =IF(Pressupostos!L10<>"",Pressupostos!L10,"") | K3: =IF(Pressupostos!M10<>"",Pressupostos!M10,"") | ... R3: =IF(Pressupostos!T10<>"",Pressupostos!T10,"")
B5: Capital prório (início do ano) | D5: =IF(D$3<>"",Balanço!C47,"") -> 260400 | E5: =IF(E$3<>"",Balanço!D47,"") -> 472285.39 | F5: =IF(F$3<>"",Balanço!E47,"") | G5: =IF(G$3<>"",Balanço!F47,"") | H5: =IF(H$3<>"",Balanço!G47,"") | I5: =IF(I$3<>"",Balanço!H47,"") | J5: =IF(J$3<>"",Balanço!I47,"") | K5: =IF(K$3<>"",Balanço!J47,"") | ... R5: =IF(R$3<>"",Balanço!Q47,"")
B6: Endivivamento (início do ano) | D6: =IF(D$3<>"",Balanço!C52+Balanço!C63,"") -> 173600 | E6: =IF(E$3<>"",Balanço!D52+Balanço!D63,"") -> 88965.043 | F6: =IF(F$3<>"",Balanço!E52+Balanço!E63,"") | G6: =IF(G$3<>"",Balanço!F52+Balanço!F63,"") | H6: =IF(H$3<>"",Balanço!G52+Balanço!G63,"") | I6: =IF(I$3<>"",Balanço!H52+Balanço!H63,"") | J6: =IF(J$3<>"",Balanço!I52+Balanço!I63,"") | K6: =IF(K$3<>"",Balanço!J52+Balanço!J63,"") | ... R6: =IF(R$3<>"",Balanço!Q52+Balanço!Q63,"")
B7: Total do capital (início do ano) | D7: =IF(D$3<>"",SUM(D5:D6),"") -> 434000 | E7: =IF(E$3<>"",SUM(E5:E6),"") -> 561250.43 | F7: =IF(F$3<>"",SUM(F5:F6),"") | G7: =IF(G$3<>"",SUM(G5:G6),"") | H7: =IF(H$3<>"",SUM(H5:H6),"") | I7: =IF(I$3<>"",SUM(I5:I6),"") | J7: =IF(J$3<>"",SUM(J5:J6),"") | K7: =IF(K$3<>"",SUM(K5:K6),"") | ... R7: =IF(R$3<>"",SUM(R5:R6),"")
B8: Capital prório (%) | C8: =IF(C$3<>"",-Pressupostos!E167-Pressupostos!E189,"") | D8: =IF(D$3<>"",D5/D$7,"") -> 0.6 | E8: =IF(E$3<>"",E5/E$7,"") -> 0.8414878 | F8: =IF(F$3<>"",F5/F$7,"") | G8: =IF(G$3<>"",G5/G$7,"") | H8: =IF(H$3<>"",H5/H$7,"") | I8: =IF(I$3<>"",I5/I$7,"") | J8: =IF(J$3<>"",J5/J$7,"") | K8: =IF(K$3<>"",K5/K$7,"") | ... R8: =IF(R$3<>"",R5/R$7,"")
B9: Endivivamento (%) | D9: =IF(D$3<>"",D6/D$7,"") -> 0.4 | E9: =IF(E$3<>"",E6/E$7,"") -> 0.1585122 | F9: =IF(F$3<>"",F6/F$7,"") | G9: =IF(G$3<>"",G6/G$7,"") | H9: =IF(H$3<>"",H6/H$7,"") | I9: =IF(I$3<>"",I6/I$7,"") | J9: =IF(J$3<>"",J6/J$7,"") | K9: =IF(K$3<>"",K6/K$7,"") | ... R9: =IF(R$3<>"",R6/R$7,"")
B11: Taxa de custo médio ponderado do capital | D11: =IF(D$3<>"",D8*Pressupostos!$E$265+D9*((1+IRR(Empréstimo!$J$14:$J$194))^12-1),"") -> 0.090013025 | E11: =IF(E$3<>"",E8*Pressupostos!$E$265+E9*((1+IRR(Empréstimo!$J$14:$J$194))^12-1),"") -> 0.10811675 | F11: =IF(F$3<>"",F8*Pressupostos!$E$265+F9*((1+IRR(Empréstimo!$J$14:$J$194))^12-1),"") | G11: =IF(G$3<>"",G8*Pressupostos!$E$265+G9*((1+IRR(Empréstimo!$J$14:$J$194))^12-1),"") | H11: =IF(H$3<>"",H8*Pressupostos!$E$265+H9*((1+IRR(Empréstimo!$J$14:$J$194))^12-1),"") | I11: =IF(I$3<>"",I8*Pressupostos!$E$265+I9*((1+IRR(Empréstimo!$J$14:$J$194))^12-1),"") | J11: =IF(J$3<>"",J8*Pressupostos!$E$265+J9*((1+IRR(Empréstimo!$J$14:$J$194))^12-1),"") | K11: =IF(K$3<>"",K8*Pressupostos!$E$265+K9*((1+IRR(Empréstimo!$J$14:$J$194))^12-1),"") | ... R11: =IF(R$3<>"",R8*Pressupostos!$E$265+R9*((1+IRR(Empréstimo!$J$14:$J$194))^12-1),"")
B14: AVALIAÇÃO
B15: Descrição | C15: =IF(Pressupostos!F10<>"",Pressupostos!F10-1,"") -> 2023 | D15: =IF(Pressupostos!F10<>"",Pressupostos!F10,"") -> 2024 | E15: =IF(Pressupostos!G10<>"",Pressupostos!G10,"") -> 2025 | F15: =IF(Pressupostos!H10<>"",Pressupostos!H10,"") | G15: =IF(Pressupostos!I10<>"",Pressupostos!I10,"") | H15: =IF(Pressupostos!J10<>"",Pressupostos!J10,"") | I15: =IF(Pressupostos!K10<>"",Pressupostos!K10,"") | J15: =IF(Pressupostos!L10<>"",Pressupostos!L10,"") | K15: =IF(Pressupostos!M10<>"",Pressupostos!M10,"") | ... R15: =IF(Pressupostos!T10<>"",Pressupostos!T10,"")
B17: Free Cash Flow to Firm | C17: =IF(C$15<>"",FCF!C10,"") -> -424000 | D17: =IF(D$15<>"",FCF!D10,"") -> -67999.56 | E17: =IF(E$15<>"",FCF!E10,"") -> 98795.661 | F17: =IF(F$15<>"",FCF!F10,"") | G17: =IF(G$15<>"",FCF!G10,"") | H17: =IF(H$15<>"",FCF!H10,"") | I17: =IF(I$15<>"",FCF!I10,"") | J17: =IF(J$15<>"",FCF!J10,"") | ... R17: =IF(R$15<>"",FCF!R10,"")
B18: Valor residual | D18: =IF(D15="","",IF(D15-$C15=Pressupostos!$F5,D17*(1+Pressupostos!$E$273)/(D11-Pressupostos!$E$273),"")) | E18: =IF(E15="","",IF(E15-$C15=Pressupostos!$F5,E17*(1+Pressupostos!$E$273)/(E11-Pressupostos!$E$273),"")) -> 1143614.3 | F18: =IF(F15="","",IF(F15-$C15=Pressupostos!$F5,F17*(1+Pressupostos!$E$273)/(F11-Pressupostos!$E$273),"")) | G18: =IF(G15="","",IF(G15-$C15=Pressupostos!$F5,G17*(1+Pressupostos!$E$273)/(G11-Pressupostos!$E$273),"")) | H18: =IF(H15="","",IF(H15-$C15=Pressupostos!$F5,H17*(1+Pressupostos!$E$273)/(H11-Pressupostos!$E$273),"")) | I18: =IF(I15="","",IF(I15-$C15=Pressupostos!$F5,I17*(1+Pressupostos!$E$273)/(I11-Pressupostos!$E$273),"")) | J18: =IF(J15="","",IF(J15-$C15=Pressupostos!$F5,J17*(1+Pressupostos!$E$273)/(J11-Pressupostos!$E$273),"")) | K18: =IF(K15="","",IF(K15-$C15=Pressupostos!$F5,K17*(1+Pressupostos!$E$273)/(K11-Pressupostos!$E$273),"")) | ... R18: =IF(R15="","",IF(R15-$C15=Pressupostos!$F5,R17*(1+Pressupostos!$E$273)/(R11-Pressupostos!$E$273),""))
C19: =IF(C15<>"",IF(D15<>"",C17,C17+C18),"") -> -424000 | D19: =IF(D15<>"",IF(E15<>"",D17,D17+D18),"") -> -67999.56 | E19: =IF(E15<>"",IF(F15<>"",E17,E17+E18),"") -> 1242410 | F19: =IF(F15<>"",IF(G15<>"",F17,F17+F18),"") | G19: =IF(G15<>"",IF(H15<>"",G17,G17+G18),"") | H19: =IF(H15<>"",IF(I15<>"",H17,H17+H18),"") | I19: =IF(I15<>"",IF(J15<>"",I17,I17+I18),"") | J19: =IF(J15<>"",IF(K15<>"",J17,J17+J18),"") | ... R19: =IF(R15<>"",IF(S15<>"",R17,R17+R18),"")
B20: Fator de atualização | C20: =IF(C$15<>"",(1+C11)^-1,"") -> 1 | D20: =IF(D$15<>"",C20*(1+D11)^-1,"") -> 0.91742023 | E20: =IF(E$15<>"",D20*(1+E11)^-1,"") -> 0.82790936 | F20: =IF(F$15<>"",E20*(1+F11)^-1,"") | G20: =IF(G$15<>"",F20*(1+G11)^-1,"") | H20: =IF(H$15<>"",G20*(1+H11)^-1,"") | I20: =IF(I$15<>"",H20*(1+I11)^-1,"") | J20: =IF(J$15<>"",I20*(1+J11)^-1,"") | K20: =IF(K$15<>"",J20*(1+K11)^-1,"") | ... R20: =IF(R$15<>"",Q20*(1+R11)^-1,"")
B21: Free Cash Flow to Firm atualizado | C21: =IF(C$15<>"",C19*C20,"") -> -424000 | D21: =IF(D$15<>"",D19*D20,"") -> -62384.172 | E21: =IF(E$15<>"",E19*E20,"") -> 1028602.9 | F21: =IF(F$15<>"",F19*F20,"") | G21: =IF(G$15<>"",G19*G20,"") | H21: =IF(H$15<>"",H19*H20,"") | I21: =IF(I$15<>"",I19*I20,"") | J21: =IF(J$15<>"",J19*J20,"") | ... R21: =IF(R$15<>"",R19*R20,"")
B22: Free Cash Flow to Firm atualizado acumulado | C22: =IF(C$15<>"",C21,"") -> -424000 | D22: =IF(D$15<>"",C22+D21,"") -> -486384.17 | E22: =IF(E$15<>"",D22+E21,"") -> 542218.69 | F22: =IF(F$15<>"",E22+F21,"") | G22: =IF(G$15<>"",F22+G21,"") | H22: =IF(H$15<>"",G22+H21,"") | I22: =IF(I$15<>"",H22+I21,"") | J22: =IF(J$15<>"",I22+J21,"") | K22: =IF(K$15<>"",J22+K21,"") | ... R22: =IF(R$15<>"",Q22+R21,"")
B23: Valor atual líquido | C23: =SUM(C21:R21) -> 542218.69
B24: Taxa interna de retabilidade | C24: =IRR(C19:R19) -> 0.63347528
B25: Payback period modificado | C25: {=INDEX(C15:R22,1,MATCH(TRUE,C22:R22>0,0))-D15+ABS(INDEX(C15:R22,8,MATCH(TRUE,C22:R22>0,0)-1))/INDEX(C15:R22,7,MATCH(TRUE,C22:R22>0,0))} -> 1.472859
